Workbook

Sheet Summary
A1: Virgin Golf bay model — summary
A2: Get Lucky Golf × Virgin Active, financed by RMB. 200 Golfzon bays in 130 clubs. ZAR ex VAT. Change inputs on Assumptions; nothing here is typed in.
A4: The order
A5: Capex, 200 bays landed and installed | B5: =Debt!D5+Debt!J5+Debt!P5 -> 179894000
A6: RMB facility | B6: =B5*Assumptions!$B$18 -> 161904600
A7: Equity deposit | B7: =B5-B6 -> 17989400
A8: Facility rate | B8: =Assumptions!$B$15 -> 0.12
A10: 2031, the first full year at 200 bays
B11: Low | C11: Selected case | D11: High
A12: Booked hours a bay a day | B12: ='Chain low'!F61 -> 3.549 | C12: =Chain!F61 -> 5.07 | D12: ='Chain high'!F61 -> 6.3375
A13: Revenue | B13: ='Chain low'!F68 -> 1.3772789e+08 | C13: =Chain!F68 -> 1.911827e+08 | D13: ='Chain high'!F68 -> 2.3572838e+08
A14: To Virgin Active | B14: =-'Chain low'!F69 -> 26545578 | C14: =-Chain!F69 -> 37236540 | D14: =-'Chain high'!F69 -> 46145675
A15: EBITDA | B15: ='Chain low'!F77 -> 72843581 | C15: =Chain!F77 -> 1.1159832e+08 | D15: ='Chain high'!F77 -> 1.4389393e+08
A16: EBITDA margin | B16: ='Chain low'!F78 -> 0.52889491 | C16: =Chain!F78 -> 0.58372603 | D16: ='Chain high'!F78 -> 0.61042262
A17: Debt service | B17: =-'Chain low'!F81 -> 43217741 | C17: =-Chain!F81 -> 43217741 | D17: =-'Chain high'!F81 -> 43217741
A18: Debt cover | B18: ='Chain low'!F82 -> 1.6855018 | C18: =Chain!F82 -> 2.582234 | D18: ='Chain high'!F82 -> 3.3295108
A19: Cash after debt | B19: ='Chain low'!F83 -> 29625840 | C19: =Chain!F83 -> 68380578 | D19: ='Chain high'!F83 -> 1.0067619e+08
A20: Equity needed, deposits and ramp together | B20: ='Chain low'!B89 -> 24806589 | C20: =Chain!B89 -> 8786747.5 | D20: ='Chain high'!B89 -> 6266344.4
A22: A bay at maturity, selected case
B23: Signature | C23: Play | D23: Practice
A24: Landed and installed | B24: ='Unit economics'!B6 -> 1443000 | C24: ='Unit economics'!C6 -> 841750 | D24: ='Unit economics'!D6 -> 529100
A25: Booked hours a day | B25: ='Unit economics'!B9 -> 6 | C25: ='Unit economics'!C9 -> 4.95 | D25: ='Unit economics'!D9 -> 4.5
A26: Revenue | B26: ='Unit economics'!B16 -> 1399753 | C26: ='Unit economics'!C16 -> 909095.51 | D26: ='Unit economics'!D16 -> 652528.01
A27: To Virgin Active | B27: ='Unit economics'!B29 -> 274950.6 | C27: ='Unit economics'!C29 -> 176819.1 | D27: ='Unit economics'!D29 -> 125505.6
A28: EBITDA | B28: ='Unit economics'!B24 -> 857615.93 | C28: ='Unit economics'!C24 -> 526401.74 | D28: ='Unit economics'!D24 -> 353136.81
A29: EBITDA margin | B29: ='Unit economics'!B25 -> 0.6126909 | C29: ='Unit economics'!C25 -> 0.57903899 | D29: ='Unit economics'!D25 -> 0.5411826
A30: Payback, years | B30: ='Unit economics'!B28 -> 1.6825714 | C30: ='Unit economics'!C28 -> 1.5990639 | D30: ='Unit economics'!D28 -> 1.4982862

Sheet Assumptions
A1: Virgin Golf bay model — Get Lucky Golf × Virgin Active
A2: Blue cells are inputs. Black cells are formulas. Green cells link to another sheet. Yellow is the case selector. All money in ZAR ex VAT.
A5: Case selector
A6: Utilisation multiplier in use (1.00 base, 0.70 low, 1.25 high) | B6: 1 | C6: Change this one cell to run the whole model at a different level of use. Booked hours and add-on take-up both scale with it.
A7: Low case multiplier | B7: 0.7 | C7: 70% of base use: 3.5 booked hours a bay a day at maturity.
A8: Base case multiplier | B8: 1
A9: High case multiplier | B9: 1.25 | C9: 125% of base use: 6.3 booked hours a bay a day.
A11: Money and financing
A12: ZAR per USD | B12: 18.5 | C12: Same rate as the Get Lucky investor model.
A13: SA prime lending rate | B13: 0.105 | C13: 10.5% from 28 May 2026, unchanged at the 23 July 2026 MPC. Source: SARB / debtsolutions4u.co.za prime rate tracker, August 2026.
A14: RMB margin over prime | B14: 0.015 | C14: Assumed asset-finance margin. To be replaced by the RMB term sheet.
A15: Facility rate | B15: =Assumptions!$B$13+Assumptions!$B$14 -> 0.12
A16: Interest-only months per phase | B16: 12 | C16: Capital holiday while a phase is commissioned and ramps.
A17: Amortising months per phase, after interest-only | B17: 60
A18: RMB share of landed capex | B18: 0.9 | C18: Get Lucky Golf funds the balance as an equity deposit.
A19: Landed factor on Golfzon hardware | B19: 1.3 | C19: Freight, duties, enclosure, screen, seating, installation, on top of hardware list price. Assumption; replaced by the Golfzon quote.
A20: Room shell cost carried by Get Lucky Golf, per bay | B20: 0 | C20: Opening position: Virgin Active builds the shell and power inside its refurbishments, so this is 0. If Get Lucky Golf builds, enter about R150,000. Negotiable.
A21: Shell cost per bay if Get Lucky Golf builds (for the negotiation grid) | B21: 150000
A23: The concession
A24: Virgin Active share of bay revenue | B24: 0.2 | C24: Opening position, negotiable. Applies to bay hire, memberships, leagues and the insured shot; not to sponsorship.
A25: Bookable hours a day | B25: 15 | C25: Club hours: about 05:00 to 21:00 weekdays, shorter weekends.
A26: Bookable days a year | B26: 360
A27: Bookable hours a bay a year | B27: =Assumptions!$B$25*Assumptions!$B$26 -> 5400
A28: Maximum utilisation | B28: 0.85 | C28: Cap so the high case cannot exceed a physically bookable level.
A30: Members and the add-on
A31: Virgin Active members, Southern Africa | B31: 623000 | C31: Virgin Active published figures to March 2026 (IOL Business Report, Nov 2025; Brait results).
A32: Virgin Active clubs, Southern Africa | B32: 136 | C32: Published figure, March 2026.
A33: Members a club | B33: =Assumptions!$B$31/Assumptions!$B$32 -> 4580.8824
A34: Golf add-on, R a month ex VAT, on the Virgin Active bill | B34: 299 | C34: One included off-peak hour and 20% off bookings. Included hours sit inside the utilisation figure.
A35: Add-on take-up at maturity, share of members at clubs with bays | B35: 0.015 | C35: Assumption. Scales with the utilisation multiplier.
A36: Add-on take-up ramp, year a club opens | B36: 0.4 | C36: Share of mature take-up.
A37: Add-on take-up ramp, second year | B37: 0.75
A39: Other revenue per bay
A40: Leagues, events and corporate, a bay a year at maturity | B40: 40000 | C40: Assumption.
A41: Naming partner, a bay a year | B41: 25000 | C41: Deliberately modest. Santam, RMB or a beverage brand could take chain naming at a multiple.
A42: Get Lucky insured shot: stake | B42: 50 | C42: R50 for a swing at R25,000, as on course.
A43: Insured shots taken per booked bay-hour | B43: 0.625 | C43: 2.5 players in a bay-hour, one in four takes a shot.
A44: Premium ceded to Santam, share of stake | B44: 0.24 | C44: Same 24% as the on-course product in the investor model.
A45: Insured shot revenue per booked hour, net of premium | B45: =Assumptions!$B$42*Assumptions!$B$43*(1-Assumptions!$B$44) -> 23.75
A47: Operating costs
A48: Card and booking fees, share of shared revenue | B48: 0.025
A49: Marketing, share of revenue | B49: 0.05
A50: Asset insurance, share of capex a year | B50: 0.01
A51: Golfzon software, courses and service, share of hardware a year | B51: 0.04 | C51: Assumption; replaced by the Golfzon service contract.
A52: Consumables and maintenance, a bay a year | B52: 24000 | C52: Balls, mats, tees, screens, projector lamps.
A53: People and central overhead allocated per bay in the unit view | B53: =16000000/200 -> 80000 | C53: R12m people plus R4m central at maturity across 200 bays.
A55: Ramp
A56: Use in the year a bay is commissioned, share of mature | B56: 0.55
A57: Use in the second year, share of mature | B57: 0.8
A58: Depreciation, years (memo only) | B58: 7
A59: Company tax (memo only) | B59: 0.27 | C59: EBITDA and debt service are shown before tax.
A61: Bay types
A62: Bay | B62: Hardware, USD list | C62: Mature utilisation | D62: Blended yield per booked hour, R | E62: Units in the order | F62: Where
A63: Signature | B63: 60000 | C63: 0.4 | D63: 520 | E63: 40 | F63: TwoVision NX, Collection and flagship clubs
A64: Play | B64: 35000 | C64: 0.33 | D64: 360 | E64: 120 | F64: Vision Standard, metro clubs
A65: Practice | B65: 22000 | C65: 0.3 | D65: 240 | E65: 40 | F65: GDR Plus, coaching bays
A67: Phases
A68: Phase | B68: Commissioned | C68: Share of that year live | D68: Signature units | E68: Play units | F68: Practice units | G68: Clubs
A69: Phase 1 | B69: 2027 | C69: 0.5 | D69: 40 | E69: 0 | F69: 0 | G69: 20
A70: Phase 2 | B70: 2028 | C70: 0.5 | D70: 0 | E70: 100 | F70: 0 | G70: 50
A71: Phase 3 | B71: 2029 | C71: 0.6 | D71: 0 | E71: 20 | F71: 40 | G71: 60
A73: Fixed costs by year
A74: Year | B74: 2027 | C74: 2028 | D74: 2029 | E74: 2030 | F74: 2031 | G74: 2032
A75: People: hosts in Collection and flagship clubs, four regional technicians, a small central team | B75: 4000000 | C75: 8000000 | D75: 11000000 | E75: 12000000 | F75: 12000000 | G75: 12000000
A76: Central overhead | B76: 2000000 | C76: 3000000 | D76: 4000000 | E76: 4000000 | F76: 4000000 | G76: 4000000

Sheet Unit economics
A1: A bay at maturity, at the multiplier in use
A2: Per bay, per year, ZAR ex VAT. Membership, people and central are allocated evenly across the 200 bays.
B4: Signature | C4: Play | D4: Practice
A5: Hardware, ZAR | B5: =Assumptions!$B$63*Assumptions!$B$12 -> 1110000 | C5: =Assumptions!$B$64*Assumptions!$B$12 -> 647500 | D5: =Assumptions!$B$65*Assumptions!$B$12 -> 407000
A6: Landed and installed, plus any shell cost carried | B6: =B5*Assumptions!$B$19+Assumptions!$B$20 -> 1443000 | C6: =C5*Assumptions!$B$19+Assumptions!$B$20 -> 841750 | D6: =D5*Assumptions!$B$19+Assumptions!$B$20 -> 529100
A7: Utilisation in use | B7: =MIN(Assumptions!$C$63*Assumptions!$B$6,Assumptions!$B$28) -> 0.4 | C7: =MIN(Assumptions!$C$64*Assumptions!$B$6,Assumptions!$B$28) -> 0.33 | D7: =MIN(Assumptions!$C$65*Assumptions!$B$6,Assumptions!$B$28) -> 0.3
A8: Booked hours a year | B8: =Assumptions!$B$27*B7 -> 2160 | C8: =Assumptions!$B$27*C7 -> 1782 | D8: =Assumptions!$B$27*D7 -> 1620
A9: Booked hours a day | B9: =B8/Assumptions!$B$26 -> 6 | C9: =C8/Assumptions!$B$26 -> 4.95 | D9: =D8/Assumptions!$B$26 -> 4.5
A10: Blended yield per booked hour | B10: =Assumptions!$D$63 -> 520 | C10: =Assumptions!$D$64 -> 360 | D10: =Assumptions!$D$65 -> 240
A11: Bay hire | B11: =B8*B10 -> 1123200 | C11: =C8*C10 -> 641520 | D11: =D8*D10 -> 388800
A12: Golf add-on, allocated per bay | B12: =(Assumptions!$G$69+Assumptions!$G$70+Assumptions!$G$71)*Assumptions!$B$33*Assumptions!$B$35*Assumptions!$B$6*Assumptions!$B$34*12/SUM(Assumptions!$E$63:$E$65) -> 160253.01 | C12: =(Assumptions!$G$69+Assumptions!$G$70+Assumptions!$G$71)*Assumptions!$B$33*Assumptions!$B$35*Assumptions!$B$6*Assumptions!$B$34*12/SUM(Assumptions!$E$63:$E$65) -> 160253.01 | D12: =(Assumptions!$G$69+Assumptions!$G$70+Assumptions!$G$71)*Assumptions!$B$33*Assumptions!$B$35*Assumptions!$B$6*Assumptions!$B$34*12/SUM(Assumptions!$E$63:$E$65) -> 160253.01
A13: Leagues, events, corporate | B13: =Assumptions!$B$40 -> 40000 | C13: =Assumptions!$B$40 -> 40000 | D13: =Assumptions!$B$40 -> 40000
A14: Get Lucky insured shot, net of premium | B14: =B8*Assumptions!$B$45 -> 51300 | C14: =C8*Assumptions!$B$45 -> 42322.5 | D14: =D8*Assumptions!$B$45 -> 38475
A15: Naming partner | B15: =Assumptions!$B$41 -> 25000 | C15: =Assumptions!$B$41 -> 25000 | D15: =Assumptions!$B$41 -> 25000
A16: Revenue | B16: =SUM(B11:B15) -> 1399753 | C16: =SUM(C11:C15) -> 909095.51 | D16: =SUM(D11:D15) -> 652528.01
A17: Virgin Active concession | B17: =-(B16-B15)*Assumptions!$B$24 -> -274950.6 | C17: =-(C16-C15)*Assumptions!$B$24 -> -176819.1 | D17: =-(D16-D15)*Assumptions!$B$24 -> -125505.6
A18: Card and booking fees | B18: =-(B16-B15)*Assumptions!$B$48 -> -34368.825 | C18: =-(C16-C15)*Assumptions!$B$48 -> -22102.388 | D18: =-(D16-D15)*Assumptions!$B$48 -> -15688.2
A19: Marketing | B19: =-B16*Assumptions!$B$49 -> -69987.65 | C19: =-C16*Assumptions!$B$49 -> -45454.775 | D19: =-D16*Assumptions!$B$49 -> -32626.4
A20: Golfzon service and software | B20: =-B5*Assumptions!$B$51 -> -44400 | C20: =-C5*Assumptions!$B$51 -> -25900 | D20: =-D5*Assumptions!$B$51 -> -16280
A21: Consumables and maintenance | B21: =-Assumptions!$B$52 -> -24000 | C21: =-Assumptions!$B$52 -> -24000 | D21: =-Assumptions!$B$52 -> -24000
A22: Asset insurance | B22: =-B6*Assumptions!$B$50 -> -14430 | C22: =-C6*Assumptions!$B$50 -> -8417.5 | D22: =-D6*Assumptions!$B$50 -> -5291
A23: People and central, allocated | B23: =-Assumptions!$B$53 -> -80000 | C23: =-Assumptions!$B$53 -> -80000 | D23: =-Assumptions!$B$53 -> -80000
A24: EBITDA | B24: =SUM(B16:B23) -> 857615.93 | C24: =SUM(C16:C23) -> 526401.74 | D24: =SUM(D16:D23) -> 353136.81
A25: EBITDA margin | B25: =IF(B16=0,0,B24/B16) -> 0.6126909 | C25: =IF(C16=0,0,C24/C16) -> 0.57903899 | D25: =IF(D16=0,0,D24/D16) -> 0.5411826
A26: RMB instalments, full amortising year | B26: =-(B6*Assumptions!$B$18)*(Assumptions!$B$15/12)/(1-(1+Assumptions!$B$15/12)^-Assumptions!$B$17)*12 -> -346666.37 | C26: =-(C6*Assumptions!$B$18)*(Assumptions!$B$15/12)/(1-(1+Assumptions!$B$15/12)^-Assumptions!$B$17)*12 -> -202222.05 | D26: =-(D6*Assumptions!$B$18)*(Assumptions!$B$15/12)/(1-(1+Assumptions!$B$15/12)^-Assumptions!$B$17)*12 -> -127111
A27: Cash after debt | B27: =B24+B26 -> 510949.56 | C27: =C24+C26 -> 324179.69 | D27: =D24+D26 -> 226025.8
A28: Payback on capex from EBITDA, years | B28: =IF(B24<=0,"n/a",B6/B24) -> 1.6825714 | C28: =IF(C24<=0,"n/a",C6/C24) -> 1.5990639 | D28: =IF(D24<=0,"n/a",D6/D24) -> 1.4982862
A29: Memo: to Virgin Active, a bay a year | B29: =-B17 -> 274950.6 | C29: =-C17 -> 176819.1 | D29: =-D17 -> 125505.6

Sheet Debt
A1: RMB facility, monthly, by phase
A2: Each phase is drawn in January of its commissioning year, interest-only for the holiday, then amortised over the term. Capex per phase includes any shell cost carried.
A4: Phase | C4: Phase 1 | I4: Phase 2 | O4: Phase 3
C5: Capex | D5: =Assumptions!$D$69*(Assumptions!$B$63*Assumptions!$B$12*Assumptions!$B$19+Assumptions!$B$20)+Assumptions!$E$69*(Assumptions!$B$64*Assumptions!$B$12*Assumptions!$B$19+Assumptions!$B$20)+Assumptions!$F$69*(Assumptions!$B$65*Assumptions!$B$12*Assumptions!$B$19+Assumptions!$B$20) -> 57720000 | I5: Capex | J5: =Assumptions!$D$70*(Assumptions!$B$63*Assumptions!$B$12*Assumptions!$B$19+Assumptions!$B$20)+Assumptions!$E$70*(Assumptions!$B$64*Assumptions!$B$12*Assumptions!$B$19+Assumptions!$B$20)+Assumptions!$F$70*(Assumptions!$B$65*Assumptions!$B$12*Assumptions!$B$19+Assumptions!$B$20) -> 84175000 | O5: Capex | P5: =Assumptions!$D$71*(Assumptions!$B$63*Assumptions!$B$12*Assumptions!$B$19+Assumptions!$B$20)+Assumptions!$E$71*(Assumptions!$B$64*Assumptions!$B$12*Assumptions!$B$19+Assumptions!$B$20)+Assumptions!$F$71*(Assumptions!$B$65*Assumptions!$B$12*Assumptions!$B$19+Assumptions!$B$20) -> 37999000
C6: Drawn | D6: =D5*Assumptions!$B$18 -> 51948000 | I6: Drawn | J6: =J5*Assumptions!$B$18 -> 75757500 | O6: Drawn | P6: =P5*Assumptions!$B$18 -> 34199100
C7: Draw month # | D7: =(Assumptions!$B$69-2027)*12+1 -> 1 | I7: Draw month # | J7: =(Assumptions!$B$70-2027)*12+1 -> 13 | O7: Draw month # | P7: =(Assumptions!$B$71-2027)*12+1 -> 25
C8: Instalment | D8: =D6*(Assumptions!$B$15/12)/(1-(1+Assumptions!$B$15/12)^-Assumptions!$B$17) -> 1155554.6 | I8: Instalment | J8: =J6*(Assumptions!$B$15/12)/(1-(1+Assumptions!$B$15/12)^-Assumptions!$B$17) -> 1685183.7 | O8: Instalment | P8: =P6*(Assumptions!$B$15/12)/(1-(1+Assumptions!$B$15/12)^-Assumptions!$B$17) -> 760740.09
A10: Month # | B10: Year | C10: Opening | D10: Interest | E10: Principal | F10: Closing | I10: Opening | J10: Interest | K10: Principal | L10: Closing | O10: Opening | P10: Interest | Q10: Principal | R10: Closing
A11: 1 | B11: =2027+INT((A11-1)/12) -> 2027 | C11: =IF(A11=$D$7,$D$6,0) -> 51948000 | D11: =C11*Assumptions!$B$15/12 -> 519480 | E11: =IF(A11-$D$7+1>Assumptions!$B$16,MIN(MAX($D$8-D11,0),C11),0) -> 0 | F11: =C11-E11 -> 51948000 | I11: =IF(A11=$J$7,$J$6,0) -> 0 | J11: =I11*Assumptions!$B$15/12 -> 0 | K11: =IF(A11-$J$7+1>Assumptions!$B$16,MIN(MAX($J$8-J11,0),I11),0) -> 0 | L11: =I11-K11 -> 0 | O11: =IF(A11=$P$7,$P$6,0) -> 0 | P11: =O11*Assumptions!$B$15/12 -> 0 | Q11: =IF(A11-$P$7+1>Assumptions!$B$16,MIN(MAX($P$8-P11,0),O11),0) -> 0 | R11: =O11-Q11 -> 0
A12: 2 | B12: =2027+INT((A12-1)/12) -> 2027 | C12: =IF(A12=$D$7,$D$6,IF(A12>$D$7,F11,0)) -> 51948000 | D12: =C12*Assumptions!$B$15/12 -> 519480 | E12: =IF(A12-$D$7+1>Assumptions!$B$16,MIN(MAX($D$8-D12,0),C12),0) -> 0 | F12: =C12-E12 -> 51948000 | I12: =IF(A12=$J$7,$J$6,IF(A12>$J$7,L11,0)) -> 0 | J12: =I12*Assumptions!$B$15/12 -> 0 | K12: =IF(A12-$J$7+1>Assumptions!$B$16,MIN(MAX($J$8-J12,0),I12),0) -> 0 | L12: =I12-K12 -> 0 | O12: =IF(A12=$P$7,$P$6,IF(A12>$P$7,R11,0)) -> 0 | P12: =O12*Assumptions!$B$15/12 -> 0 | Q12: =IF(A12-$P$7+1>Assumptions!$B$16,MIN(MAX($P$8-P12,0),O12),0) -> 0 | R12: =O12-Q12 -> 0
A13: 3 | B13: =2027+INT((A13-1)/12) -> 2027 | C13: =IF(A13=$D$7,$D$6,IF(A13>$D$7,F12,0)) -> 51948000 | D13: =C13*Assumptions!$B$15/12 -> 519480 | E13: =IF(A13-$D$7+1>Assumptions!$B$16,MIN(MAX($D$8-D13,0),C13),0) -> 0 | F13: =C13-E13 -> 51948000 | I13: =IF(A13=$J$7,$J$6,IF(A13>$J$7,L12,0)) -> 0 | J13: =I13*Assumptions!$B$15/12 -> 0 | K13: =IF(A13-$J$7+1>Assumptions!$B$16,MIN(MAX($J$8-J13,0),I13),0) -> 0 | L13: =I13-K13 -> 0 | O13: =IF(A13=$P$7,$P$6,IF(A13>$P$7,R12,0)) -> 0 | P13: =O13*Assumptions!$B$15/12 -> 0 | Q13: =IF(A13-$P$7+1>Assumptions!$B$16,MIN(MAX($P$8-P13,0),O13),0) -> 0 | R13: =O13-Q13 -> 0
A14: 4 | B14: =2027+INT((A14-1)/12) -> 2027 | C14: =IF(A14=$D$7,$D$6,IF(A14>$D$7,F13,0)) -> 51948000 | D14: =C14*Assumptions!$B$15/12 -> 519480 | E14: =IF(A14-$D$7+1>Assumptions!$B$16,MIN(MAX($D$8-D14,0),C14),0) -> 0 | F14: =C14-E14 -> 51948000 | I14: =IF(A14=$J$7,$J$6,IF(A14>$J$7,L13,0)) -> 0 | J14: =I14*Assumptions!$B$15/12 -> 0 | K14: =IF(A14-$J$7+1>Assumptions!$B$16,MIN(MAX($J$8-J14,0),I14),0) -> 0 | L14: =I14-K14 -> 0 | O14: =IF(A14=$P$7,$P$6,IF(A14>$P$7,R13,0)) -> 0 | P14: =O14*Assumptions!$B$15/12 -> 0 | Q14: =IF(A14-$P$7+1>Assumptions!$B$16,MIN(MAX($P$8-P14,0),O14),0) -> 0 | R14: =O14-Q14 -> 0
A15: 5 | B15: =2027+INT((A15-1)/12) -> 2027 | C15: =IF(A15=$D$7,$D$6,IF(A15>$D$7,F14,0)) -> 51948000 | D15: =C15*Assumptions!$B$15/12 -> 519480 | E15: =IF(A15-$D$7+1>Assumptions!$B$16,MIN(MAX($D$8-D15,0),C15),0) -> 0 | F15: =C15-E15 -> 51948000 | I15: =IF(A15=$J$7,$J$6,IF(A15>$J$7,L14,0)) -> 0 | J15: =I15*Assumptions!$B$15/12 -> 0 | K15: =IF(A15-$J$7+1>Assumptions!$B$16,MIN(MAX($J$8-J15,0),I15),0) -> 0 | L15: =I15-K15 -> 0 | O15: =IF(A15=$P$7,$P$6,IF(A15>$P$7,R14,0)) -> 0 | P15: =O15*Assumptions!$B$15/12 -> 0 | Q15: =IF(A15-$P$7+1>Assumptions!$B$16,MIN(MAX($P$8-P15,0),O15),0) -> 0 | R15: =O15-Q15 -> 0
A16: 6 | B16: =2027+INT((A16-1)/12) -> 2027 | C16: =IF(A16=$D$7,$D$6,IF(A16>$D$7,F15,0)) -> 51948000 | D16: =C16*Assumptions!$B$15/12 -> 519480 | E16: =IF(A16-$D$7+1>Assumptions!$B$16,MIN(MAX($D$8-D16,0),C16),0) -> 0 | F16: =C16-E16 -> 51948000 | I16: =IF(A16=$J$7,$J$6,IF(A16>$J$7,L15,0)) -> 0 | J16: =I16*Assumptions!$B$15/12 -> 0 | K16: =IF(A16-$J$7+1>Assumptions!$B$16,MIN(MAX($J$8-J16,0),I16),0) -> 0 | L16: =I16-K16 -> 0 | O16: =IF(A16=$P$7,$P$6,IF(A16>$P$7,R15,0)) -> 0 | P16: =O16*Assumptions!$B$15/12 -> 0 | Q16: =IF(A16-$P$7+1>Assumptions!$B$16,MIN(MAX($P$8-P16,0),O16),0) -> 0 | R16: =O16-Q16 -> 0
A17: 7 | B17: =2027+INT((A17-1)/12) -> 2027 | C17: =IF(A17=$D$7,$D$6,IF(A17>$D$7,F16,0)) -> 51948000 | D17: =C17*Assumptions!$B$15/12 -> 519480 | E17: =IF(A17-$D$7+1>Assumptions!$B$16,MIN(MAX($D$8-D17,0),C17),0) -> 0 | F17: =C17-E17 -> 51948000 | I17: =IF(A17=$J$7,$J$6,IF(A17>$J$7,L16,0)) -> 0 | J17: =I17*Assumptions!$B$15/12 -> 0 | K17: =IF(A17-$J$7+1>Assumptions!$B$16,MIN(MAX($J$8-J17,0),I17),0) -> 0 | L17: =I17-K17 -> 0 | O17: =IF(A17=$P$7,$P$6,IF(A17>$P$7,R16,0)) -> 0 | P17: =O17*Assumptions!$B$15/12 -> 0 | Q17: =IF(A17-$P$7+1>Assumptions!$B$16,MIN(MAX($P$8-P17,0),O17),0) -> 0 | R17: =O17-Q17 -> 0
A18: 8 | B18: =2027+INT((A18-1)/12) -> 2027 | C18: =IF(A18=$D$7,$D$6,IF(A18>$D$7,F17,0)) -> 51948000 | D18: =C18*Assumptions!$B$15/12 -> 519480 | E18: =IF(A18-$D$7+1>Assumptions!$B$16,MIN(MAX($D$8-D18,0),C18),0) -> 0 | F18: =C18-E18 -> 51948000 | I18: =IF(A18=$J$7,$J$6,IF(A18>$J$7,L17,0)) -> 0 | J18: =I18*Assumptions!$B$15/12 -> 0 | K18: =IF(A18-$J$7+1>Assumptions!$B$16,MIN(MAX($J$8-J18,0),I18),0) -> 0 | L18: =I18-K18 -> 0 | O18: =IF(A18=$P$7,$P$6,IF(A18>$P$7,R17,0)) -> 0 | P18: =O18*Assumptions!$B$15/12 -> 0 | Q18: =IF(A18-$P$7+1>Assumptions!$B$16,MIN(MAX($P$8-P18,0),O18),0) -> 0 | R18: =O18-Q18 -> 0
A19: 9 | B19: =2027+INT((A19-1)/12) -> 2027 | C19: =IF(A19=$D$7,$D$6,IF(A19>$D$7,F18,0)) -> 51948000 | D19: =C19*Assumptions!$B$15/12 -> 519480 | E19: =IF(A19-$D$7+1>Assumptions!$B$16,MIN(MAX($D$8-D19,0),C19),0) -> 0 | F19: =C19-E19 -> 51948000 | I19: =IF(A19=$J$7,$J$6,IF(A19>$J$7,L18,0)) -> 0 | J19: =I19*Assumptions!$B$15/12 -> 0 | K19: =IF(A19-$J$7+1>Assumptions!$B$16,MIN(MAX($J$8-J19,0),I19),0) -> 0 | L19: =I19-K19 -> 0 | O19: =IF(A19=$P$7,$P$6,IF(A19>$P$7,R18,0)) -> 0 | P19: =O19*Assumptions!$B$15/12 -> 0 | Q19: =IF(A19-$P$7+1>Assumptions!$B$16,MIN(MAX($P$8-P19,0),O19),0) -> 0 | R19: =O19-Q19 -> 0
A20: 10 | B20: =2027+INT((A20-1)/12) -> 2027 | C20: =IF(A20=$D$7,$D$6,IF(A20>$D$7,F19,0)) -> 51948000 | D20: =C20*Assumptions!$B$15/12 -> 519480 | E20: =IF(A20-$D$7+1>Assumptions!$B$16,MIN(MAX($D$8-D20,0),C20),0) -> 0 | F20: =C20-E20 -> 51948000 | I20: =IF(A20=$J$7,$J$6,IF(A20>$J$7,L19,0)) -> 0 | J20: =I20*Assumptions!$B$15/12 -> 0 | K20: =IF(A20-$J$7+1>Assumptions!$B$16,MIN(MAX($J$8-J20,0),I20),0) -> 0 | L20: =I20-K20 -> 0 | O20: =IF(A20=$P$7,$P$6,IF(A20>$P$7,R19,0)) -> 0 | P20: =O20*Assumptions!$B$15/12 -> 0 | Q20: =IF(A20-$P$7+1>Assumptions!$B$16,MIN(MAX($P$8-P20,0),O20),0) -> 0 | R20: =O20-Q20 -> 0
A21: 11 | B21: =2027+INT((A21-1)/12) -> 2027 | C21: =IF(A21=$D$7,$D$6,IF(A21>$D$7,F20,0)) -> 51948000 | D21: =C21*Assumptions!$B$15/12 -> 519480 | E21: =IF(A21-$D$7+1>Assumptions!$B$16,MIN(MAX($D$8-D21,0),C21),0) -> 0 | F21: =C21-E21 -> 51948000 | I21: =IF(A21=$J$7,$J$6,IF(A21>$J$7,L20,0)) -> 0 | J21: =I21*Assumptions!$B$15/12 -> 0 | K21: =IF(A21-$J$7+1>Assumptions!$B$16,MIN(MAX($J$8-J21,0),I21),0) -> 0 | L21: =I21-K21 -> 0 | O21: =IF(A21=$P$7,$P$6,IF(A21>$P$7,R20,0)) -> 0 | P21: =O21*Assumptions!$B$15/12 -> 0 | Q21: =IF(A21-$P$7+1>Assumptions!$B$16,MIN(MAX($P$8-P21,0),O21),0) -> 0 | R21: =O21-Q21 -> 0
A22: 12 | B22: =2027+INT((A22-1)/12) -> 2027 | C22: =IF(A22=$D$7,$D$6,IF(A22>$D$7,F21,0)) -> 51948000 | D22: =C22*Assumptions!$B$15/12 -> 519480 | E22: =IF(A22-$D$7+1>Assumptions!$B$16,MIN(MAX($D$8-D22,0),C22),0) -> 0 | F22: =C22-E22 -> 51948000 | I22: =IF(A22=$J$7,$J$6,IF(A22>$J$7,L21,0)) -> 0 | J22: =I22*Assumptions!$B$15/12 -> 0 | K22: =IF(A22-$J$7+1>Assumptions!$B$16,MIN(MAX($J$8-J22,0),I22),0) -> 0 | L22: =I22-K22 -> 0 | O22: =IF(A22=$P$7,$P$6,IF(A22>$P$7,R21,0)) -> 0 | P22: =O22*Assumptions!$B$15/12 -> 0 | Q22: =IF(A22-$P$7+1>Assumptions!$B$16,MIN(MAX($P$8-P22,0),O22),0) -> 0 | R22: =O22-Q22 -> 0
A23: 13 | B23: =2027+INT((A23-1)/12) -> 2028 | C23: =IF(A23=$D$7,$D$6,IF(A23>$D$7,F22,0)) -> 51948000 | D23: =C23*Assumptions!$B$15/12 -> 519480 | E23: =IF(A23-$D$7+1>Assumptions!$B$16,MIN(MAX($D$8-D23,0),C23),0) -> 636074.57 | F23: =C23-E23 -> 51311925 | I23: =IF(A23=$J$7,$J$6,IF(A23>$J$7,L22,0)) -> 75757500 | J23: =I23*Assumptions!$B$15/12 -> 757575 | K23: =IF(A23-$J$7+1>Assumptions!$B$16,MIN(MAX($J$8-J23,0),I23),0) -> 0 | L23: =I23-K23 -> 75757500 | O23: =IF(A23=$P$7,$P$6,IF(A23>$P$7,R22,0)) -> 0 | P23: =O23*Assumptions!$B$15/12 -> 0 | Q23: =IF(A23-$P$7+1>Assumptions!$B$16,MIN(MAX($P$8-P23,0),O23),0) -> 0 | R23: =O23-Q23 -> 0
... A82: 72 | B82: =2027+INT((A82-1)/12) -> 2032 | C82: =IF(A82=$D$7,$D$6,IF(A82>$D$7,F81,0)) -> 1144113.4 | D82: =C82*Assumptions!$B$15/12 -> 11441.134 | E82: =IF(A82-$D$7+1>Assumptions!$B$16,MIN(MAX($D$8-D82,0),C82),0) -> 1144113.4 | F82: =C82-E82 -> 6.8219379e-08 | I82: =IF(A82=$J$7,$J$6,IF(A82>$J$7,L81,0)) -> 20447582 | J82: =I82*Assumptions!$B$15/12 -> 204475.82 | K82: =IF(A82-$J$7+1>Assumptions!$B$16,MIN(MAX($J$8-J82,0),I82),0) -> 1480707.9 | L82: =I82-K82 -> 18966874 | O82: =IF(A82=$P$7,$P$6,IF(A82>$P$7,R81,0)) -> 16753897 | P82: =O82*Assumptions!$B$15/12 -> 167538.97 | Q82: =IF(A82-$P$7+1>Assumptions!$B$16,MIN(MAX($P$8-P82,0),O82),0) -> 593201.12 | R82: =O82-Q82 -> 16160696
A85: Annual
A86: Year | B86: 2027 | C86: 2028 | D86: 2029 | E86: 2030 | F86: 2031 | G86: 2032
A87: Phase 1 interest | B87: =SUMIF($B$11:$B$82,2027,D$11:D$82) -> 6233760 | C87: =SUMIF($B$11:$B$82,2028,D$11:D$82) -> 5799637.2 | D87: =SUMIF($B$11:$B$82,2029,D$11:D$82) -> 4776537.4 | E87: =SUMIF($B$11:$B$82,2030,D$11:D$82) -> 3623683 | F87: =SUMIF($B$11:$B$82,2031,D$11:D$82) -> 2324617.8 | G87: =SUMIF($B$11:$B$82,2032,D$11:D$82) -> 860798.63
A88: Phase 1 principal | B88: =SUMIF($B$11:$B$82,2027,E$11:E$82) -> 0 | C88: =SUMIF($B$11:$B$82,2028,E$11:E$82) -> 8067017.6 | D88: =SUMIF($B$11:$B$82,2029,E$11:E$82) -> 9090117.4 | E88: =SUMIF($B$11:$B$82,2030,E$11:E$82) -> 10242972 | F88: =SUMIF($B$11:$B$82,2031,E$11:E$82) -> 11542037 | G88: =SUMIF($B$11:$B$82,2032,E$11:E$82) -> 13005856
A89: Phase 2 interest | B89: =SUMIF($B$11:$B$82,2027,J$11:J$82) -> 0 | C89: =SUMIF($B$11:$B$82,2028,J$11:J$82) -> 9090900 | D89: =SUMIF($B$11:$B$82,2029,J$11:J$82) -> 8457804.2 | E89: =SUMIF($B$11:$B$82,2030,J$11:J$82) -> 6965783.8 | F89: =SUMIF($B$11:$B$82,2031,J$11:J$82) -> 5284537.7 | G89: =SUMIF($B$11:$B$82,2032,J$11:J$82) -> 3390067.7
A90: Phase 2 principal | B90: =SUMIF($B$11:$B$82,2027,K$11:K$82) -> 0 | C90: =SUMIF($B$11:$B$82,2028,K$11:K$82) -> 0 | D90: =SUMIF($B$11:$B$82,2029,K$11:K$82) -> 11764401 | E90: =SUMIF($B$11:$B$82,2030,K$11:K$82) -> 13256421 | F90: =SUMIF($B$11:$B$82,2031,K$11:K$82) -> 14937667 | G90: =SUMIF($B$11:$B$82,2032,K$11:K$82) -> 16832137
A91: Phase 3 interest | B91: =SUMIF($B$11:$B$82,2027,P$11:P$82) -> 0 | C91: =SUMIF($B$11:$B$82,2028,P$11:P$82) -> 0 | D91: =SUMIF($B$11:$B$82,2029,P$11:P$82) -> 4103892 | E91: =SUMIF($B$11:$B$82,2030,P$11:P$82) -> 3818094.5 | F91: =SUMIF($B$11:$B$82,2031,P$11:P$82) -> 3144553.8 | G91: =SUMIF($B$11:$B$82,2032,P$11:P$82) -> 2385591.3
A92: Phase 3 principal | B92: =SUMIF($B$11:$B$82,2027,Q$11:Q$82) -> 0 | C92: =SUMIF($B$11:$B$82,2028,Q$11:Q$82) -> 0 | D92: =SUMIF($B$11:$B$82,2029,Q$11:Q$82) -> 0 | E92: =SUMIF($B$11:$B$82,2030,Q$11:Q$82) -> 5310786.6 | F92: =SUMIF($B$11:$B$82,2031,Q$11:Q$82) -> 5984327.3 | G92: =SUMIF($B$11:$B$82,2032,Q$11:Q$82) -> 6743289.8
A93: Total interest | B93: =B87+B89+B91 -> 6233760 | C93: =C87+C89+C91 -> 14890537 | D93: =D87+D89+D91 -> 17338234 | E93: =E87+E89+E91 -> 14407561 | F93: =F87+F89+F91 -> 10753709 | G93: =G87+G89+G91 -> 6636457.6
A94: Total principal | B94: =B88+B90+B92 -> 0 | C94: =C88+C90+C92 -> 8067017.6 | D94: =D88+D90+D92 -> 20854518 | E94: =E88+E90+E92 -> 28810180 | F94: =F88+F90+F92 -> 32464031 | G94: =G88+G90+G92 -> 36581283
A95: Total debt service | B95: =B93+B94 -> 6233760 | C95: =C93+C94 -> 22957555 | D95: =D93+D94 -> 38192752 | E95: =E93+E94 -> 43217741 | F95: =F93+F94 -> 43217741 | G95: =G93+G94 -> 43217741
A96: Closing balance | B96: =IF(2027>=Assumptions!$B$69,Debt!$D$6,0)+IF(2027>=Assumptions!$B$70,Debt!$J$6,0)+IF(2027>=Assumptions!$B$71,Debt!$P$6,0)-SUMIF($B$11:$B$82,"<="&2027,$A$11:$A$82)*0-(SUMIF($B$11:$B$82,"<="&2027,E$11:E$82)+SUMIF($B$11:$B$82,"<="&2027,K$11:K$82)+SUMIF($B$11:$B$82,"<="&2027,Q$11:Q$82)) -> 51948000 | C96: =IF(2028>=Assumptions!$B$69,Debt!$D$6,0)+IF(2028>=Assumptions!$B$70,Debt!$J$6,0)+IF(2028>=Assumptions!$B$71,Debt!$P$6,0)-SUMIF($B$11:$B$82,"<="&2028,$A$11:$A$82)*0-(SUMIF($B$11:$B$82,"<="&2028,E$11:E$82)+SUMIF($B$11:$B$82,"<="&2028,K$11:K$82)+SUMIF($B$11:$B$82,"<="&2028,Q$11:Q$82)) -> 1.1963848e+08 | D96: =IF(2029>=Assumptions!$B$69,Debt!$D$6,0)+IF(2029>=Assumptions!$B$70,Debt!$J$6,0)+IF(2029>=Assumptions!$B$71,Debt!$P$6,0)-SUMIF($B$11:$B$82,"<="&2029,$A$11:$A$82)*0-(SUMIF($B$11:$B$82,"<="&2029,E$11:E$82)+SUMIF($B$11:$B$82,"<="&2029,K$11:K$82)+SUMIF($B$11:$B$82,"<="&2029,Q$11:Q$82)) -> 1.3298306e+08 | E96: =IF(2030>=Assumptions!$B$69,Debt!$D$6,0)+IF(2030>=Assumptions!$B$70,Debt!$J$6,0)+IF(2030>=Assumptions!$B$71,Debt!$P$6,0)-SUMIF($B$11:$B$82,"<="&2030,$A$11:$A$82)*0-(SUMIF($B$11:$B$82,"<="&2030,E$11:E$82)+SUMIF($B$11:$B$82,"<="&2030,K$11:K$82)+SUMIF($B$11:$B$82,"<="&2030,Q$11:Q$82)) -> 1.0417288e+08 | F96: =IF(2031>=Assumptions!$B$69,Debt!$D$6,0)+IF(2031>=Assumptions!$B$70,Debt!$J$6,0)+IF(2031>=Assumptions!$B$71,Debt!$P$6,0)-SUMIF($B$11:$B$82,"<="&2031,$A$11:$A$82)*0-(SUMIF($B$11:$B$82,"<="&2031,E$11:E$82)+SUMIF($B$11:$B$82,"<="&2031,K$11:K$82)+SUMIF($B$11:$B$82,"<="&2031,Q$11:Q$82)) -> 71708853 | G96: =IF(2032>=Assumptions!$B$69,Debt!$D$6,0)+IF(2032>=Assumptions!$B$70,Debt!$J$6,0)+IF(2032>=Assumptions!$B$71,Debt!$P$6,0)-SUMIF($B$11:$B$82,"<="&2032,$A$11:$A$82)*0-(SUMIF($B$11:$B$82,"<="&2032,E$11:E$82)+SUMIF($B$11:$B$82,"<="&2032,K$11:K$82)+SUMIF($B$11:$B$82,"<="&2032,Q$11:Q$82)) -> 35127570

Sheet Chain
A1: The chain, 2027 to 2032 — at the multiplier selected on Assumptions
A2: Utilisation multiplier | B2: =Assumptions!$B$6 -> 1
A4: Year | B4: 2027 | C4: 2028 | D4: 2029 | E4: 2030 | F4: 2031 | G4: 2032
A6: Phase 1
A7: Bay age, years | B7: =2027-Assumptions!$B$69 -> 0 | C7: =2028-Assumptions!$B$69 -> 1 | D7: =2029-Assumptions!$B$69 -> 2 | E7: =2030-Assumptions!$B$69 -> 3 | F7: =2031-Assumptions!$B$69 -> 4 | G7: =2032-Assumptions!$B$69 -> 5
A8: Share of year live | B8: =IF(B7<0,0,IF(B7=0,Assumptions!$C$69,1)) -> 0.5 | C8: =IF(C7<0,0,IF(C7=0,Assumptions!$C$69,1)) -> 1 | D8: =IF(D7<0,0,IF(D7=0,Assumptions!$C$69,1)) -> 1 | E8: =IF(E7<0,0,IF(E7=0,Assumptions!$C$69,1)) -> 1 | F8: =IF(F7<0,0,IF(F7=0,Assumptions!$C$69,1)) -> 1 | G8: =IF(G7<0,0,IF(G7=0,Assumptions!$C$69,1)) -> 1
A9: Use factor (live × ramp) | B9: =B8*IF(B7=0,Assumptions!$B$56,IF(B7=1,Assumptions!$B$57,1)) -> 0.275 | C9: =C8*IF(C7=0,Assumptions!$B$56,IF(C7=1,Assumptions!$B$57,1)) -> 0.8 | D9: =D8*IF(D7=0,Assumptions!$B$56,IF(D7=1,Assumptions!$B$57,1)) -> 1 | E9: =E8*IF(E7=0,Assumptions!$B$56,IF(E7=1,Assumptions!$B$57,1)) -> 1 | F9: =F8*IF(F7=0,Assumptions!$B$56,IF(F7=1,Assumptions!$B$57,1)) -> 1 | G9: =G8*IF(G7=0,Assumptions!$B$56,IF(G7=1,Assumptions!$B$57,1)) -> 1
A10: Capex in year | B10: =IF(B7=0,Debt!$D$5,0) -> 57720000 | C10: =IF(C7=0,Debt!$D$5,0) -> 0 | D10: =IF(D7=0,Debt!$D$5,0) -> 0 | E10: =IF(E7=0,Debt!$D$5,0) -> 0 | F10: =IF(F7=0,Debt!$D$5,0) -> 0 | G10: =IF(G7=0,Debt!$D$5,0) -> 0
A11: Bays live | B11: =IF(B7>=0,SUM(Assumptions!$D$69:$F$69),0) -> 40 | C11: =IF(C7>=0,SUM(Assumptions!$D$69:$F$69),0) -> 40 | D11: =IF(D7>=0,SUM(Assumptions!$D$69:$F$69),0) -> 40 | E11: =IF(E7>=0,SUM(Assumptions!$D$69:$F$69),0) -> 40 | F11: =IF(F7>=0,SUM(Assumptions!$D$69:$F$69),0) -> 40 | G11: =IF(G7>=0,SUM(Assumptions!$D$69:$F$69),0) -> 40
A12: Clubs live | B12: =IF(B7>=0,Assumptions!$G$69,0) -> 20 | C12: =IF(C7>=0,Assumptions!$G$69,0) -> 20 | D12: =IF(D7>=0,Assumptions!$G$69,0) -> 20 | E12: =IF(E7>=0,Assumptions!$G$69,0) -> 20 | F12: =IF(F7>=0,Assumptions!$G$69,0) -> 20 | G12: =IF(G7>=0,Assumptions!$G$69,0) -> 20
A13: Booked hours | B13: =(Assumptions!$D$69*MIN(Assumptions!$C$63*$B$2,Assumptions!$B$28)+Assumptions!$E$69*MIN(Assumptions!$C$64*$B$2,Assumptions!$B$28)+Assumptions!$F$69*MIN(Assumptions!$C$65*$B$2,Assumptions!$B$28))*Assumptions!$B$27*B9 -> 23760 | C13: =(Assumptions!$D$69*MIN(Assumptions!$C$63*$B$2,Assumptions!$B$28)+Assumptions!$E$69*MIN(Assumptions!$C$64*$B$2,Assumptions!$B$28)+Assumptions!$F$69*MIN(Assumptions!$C$65*$B$2,Assumptions!$B$28))*Assumptions!$B$27*C9 -> 69120 | D13: =(Assumptions!$D$69*MIN(Assumptions!$C$63*$B$2,Assumptions!$B$28)+Assumptions!$E$69*MIN(Assumptions!$C$64*$B$2,Assumptions!$B$28)+Assumptions!$F$69*MIN(Assumptions!$C$65*$B$2,Assumptions!$B$28))*Assumptions!$B$27*D9 -> 86400 | E13: =(Assumptions!$D$69*MIN(Assumptions!$C$63*$B$2,Assumptions!$B$28)+Assumptions!$E$69*MIN(Assumptions!$C$64*$B$2,Assumptions!$B$28)+Assumptions!$F$69*MIN(Assumptions!$C$65*$B$2,Assumptions!$B$28))*Assumptions!$B$27*E9 -> 86400 | F13: =(Assumptions!$D$69*MIN(Assumptions!$C$63*$B$2,Assumptions!$B$28)+Assumptions!$E$69*MIN(Assumptions!$C$64*$B$2,Assumptions!$B$28)+Assumptions!$F$69*MIN(Assumptions!$C$65*$B$2,Assumptions!$B$28))*Assumptions!$B$27*F9 -> 86400 | G13: =(Assumptions!$D$69*MIN(Assumptions!$C$63*$B$2,Assumptions!$B$28)+Assumptions!$E$69*MIN(Assumptions!$C$64*$B$2,Assumptions!$B$28)+Assumptions!$F$69*MIN(Assumptions!$C$65*$B$2,Assumptions!$B$28))*Assumptions!$B$27*G9 -> 86400
A14: Bay hire | B14: =(Assumptions!$D$69*MIN(Assumptions!$C$63*$B$2,Assumptions!$B$28)*Assumptions!$D$63+Assumptions!$E$69*MIN(Assumptions!$C$64*$B$2,Assumptions!$B$28)*Assumptions!$D$64+Assumptions!$F$69*MIN(Assumptions!$C$65*$B$2,Assumptions!$B$28)*Assumptions!$D$65)*Assumptions!$B$27*B9 -> 12355200 | C14: =(Assumptions!$D$69*MIN(Assumptions!$C$63*$B$2,Assumptions!$B$28)*Assumptions!$D$63+Assumptions!$E$69*MIN(Assumptions!$C$64*$B$2,Assumptions!$B$28)*Assumptions!$D$64+Assumptions!$F$69*MIN(Assumptions!$C$65*$B$2,Assumptions!$B$28)*Assumptions!$D$65)*Assumptions!$B$27*C9 -> 35942400 | D14: =(Assumptions!$D$69*MIN(Assumptions!$C$63*$B$2,Assumptions!$B$28)*Assumptions!$D$63+Assumptions!$E$69*MIN(Assumptions!$C$64*$B$2,Assumptions!$B$28)*Assumptions!$D$64+Assumptions!$F$69*MIN(Assumptions!$C$65*$B$2,Assumptions!$B$28)*Assumptions!$D$65)*Assumptions!$B$27*D9 -> 44928000 | E14: =(Assumptions!$D$69*MIN(Assumptions!$C$63*$B$2,Assumptions!$B$28)*Assumptions!$D$63+Assumptions!$E$69*MIN(Assumptions!$C$64*$B$2,Assumptions!$B$28)*Assumptions!$D$64+Assumptions!$F$69*MIN(Assumptions!$C$65*$B$2,Assumptions!$B$28)*Assumptions!$D$65)*Assumptions!$B$27*E9 -> 44928000 | F14: =(Assumptions!$D$69*MIN(Assumptions!$C$63*$B$2,Assumptions!$B$28)*Assumptions!$D$63+Assumptions!$E$69*MIN(Assumptions!$C$64*$B$2,Assumptions!$B$28)*Assumptions!$D$64+Assumptions!$F$69*MIN(Assumptions!$C$65*$B$2,Assumptions!$B$28)*Assumptions!$D$65)*Assumptions!$B$27*F9 -> 44928000 | G14: =(Assumptions!$D$69*MIN(Assumptions!$C$63*$B$2,Assumptions!$B$28)*Assumptions!$D$63+Assumptions!$E$69*MIN(Assumptions!$C$64*$B$2,Assumptions!$B$28)*Assumptions!$D$64+Assumptions!$F$69*MIN(Assumptions!$C$65*$B$2,Assumptions!$B$28)*Assumptions!$D$65)*Assumptions!$B$27*G9 -> 44928000
A15: Golf add-on | B15: =Assumptions!$G$69*Assumptions!$B$33*Assumptions!$B$35*$B$2*IF(B7=0,Assumptions!$B$36,IF(B7=1,Assumptions!$B$37,1))*Assumptions!$B$34*12*B8 -> 986172.35 | C15: =Assumptions!$G$69*Assumptions!$B$33*Assumptions!$B$35*$B$2*IF(C7=0,Assumptions!$B$36,IF(C7=1,Assumptions!$B$37,1))*Assumptions!$B$34*12*C8 -> 3698146.3 | D15: =Assumptions!$G$69*Assumptions!$B$33*Assumptions!$B$35*$B$2*IF(D7=0,Assumptions!$B$36,IF(D7=1,Assumptions!$B$37,1))*Assumptions!$B$34*12*D8 -> 4930861.8 | E15: =Assumptions!$G$69*Assumptions!$B$33*Assumptions!$B$35*$B$2*IF(E7=0,Assumptions!$B$36,IF(E7=1,Assumptions!$B$37,1))*Assumptions!$B$34*12*E8 -> 4930861.8 | F15: =Assumptions!$G$69*Assumptions!$B$33*Assumptions!$B$35*$B$2*IF(F7=0,Assumptions!$B$36,IF(F7=1,Assumptions!$B$37,1))*Assumptions!$B$34*12*F8 -> 4930861.8 | G15: =Assumptions!$G$69*Assumptions!$B$33*Assumptions!$B$35*$B$2*IF(G7=0,Assumptions!$B$36,IF(G7=1,Assumptions!$B$37,1))*Assumptions!$B$34*12*G8 -> 4930861.8
A16: Leagues, events, corporate | B16: =B11*Assumptions!$B$40*B9 -> 440000 | C16: =C11*Assumptions!$B$40*C9 -> 1280000 | D16: =D11*Assumptions!$B$40*D9 -> 1600000 | E16: =E11*Assumptions!$B$40*E9 -> 1600000 | F16: =F11*Assumptions!$B$40*F9 -> 1600000 | G16: =G11*Assumptions!$B$40*G9 -> 1600000
A17: Insured shot, net of premium | B17: =B13*Assumptions!$B$45 -> 564300 | C17: =C13*Assumptions!$B$45 -> 1641600 | D17: =D13*Assumptions!$B$45 -> 2052000 | E17: =E13*Assumptions!$B$45 -> 2052000 | F17: =F13*Assumptions!$B$45 -> 2052000 | G17: =G13*Assumptions!$B$45 -> 2052000
A18: Naming partner | B18: =B11*Assumptions!$B$41*B8 -> 500000 | C18: =C11*Assumptions!$B$41*C8 -> 1000000 | D18: =D11*Assumptions!$B$41*D8 -> 1000000 | E18: =E11*Assumptions!$B$41*E8 -> 1000000 | F18: =F11*Assumptions!$B$41*F8 -> 1000000 | G18: =G11*Assumptions!$B$41*G8 -> 1000000
A19: Golfzon service and software | B19: =(Assumptions!$D$69*Assumptions!$B$63*Assumptions!$B$12+Assumptions!$E$69*Assumptions!$B$64*Assumptions!$B$12+Assumptions!$F$69*Assumptions!$B$65*Assumptions!$B$12)*Assumptions!$B$51*B8 -> 888000 | C19: =(Assumptions!$D$69*Assumptions!$B$63*Assumptions!$B$12+Assumptions!$E$69*Assumptions!$B$64*Assumptions!$B$12+Assumptions!$F$69*Assumptions!$B$65*Assumptions!$B$12)*Assumptions!$B$51*C8 -> 1776000 | D19: =(Assumptions!$D$69*Assumptions!$B$63*Assumptions!$B$12+Assumptions!$E$69*Assumptions!$B$64*Assumptions!$B$12+Assumptions!$F$69*Assumptions!$B$65*Assumptions!$B$12)*Assumptions!$B$51*D8 -> 1776000 | E19: =(Assumptions!$D$69*Assumptions!$B$63*Assumptions!$B$12+Assumptions!$E$69*Assumptions!$B$64*Assumptions!$B$12+Assumptions!$F$69*Assumptions!$B$65*Assumptions!$B$12)*Assumptions!$B$51*E8 -> 1776000 | F19: =(Assumptions!$D$69*Assumptions!$B$63*Assumptions!$B$12+Assumptions!$E$69*Assumptions!$B$64*Assumptions!$B$12+Assumptions!$F$69*Assumptions!$B$65*Assumptions!$B$12)*Assumptions!$B$51*F8 -> 1776000 | G19: =(Assumptions!$D$69*Assumptions!$B$63*Assumptions!$B$12+Assumptions!$E$69*Assumptions!$B$64*Assumptions!$B$12+Assumptions!$F$69*Assumptions!$B$65*Assumptions!$B$12)*Assumptions!$B$51*G8 -> 1776000
A20: Consumables and maintenance | B20: =B11*Assumptions!$B$52*B8 -> 480000 | C20: =C11*Assumptions!$B$52*C8 -> 960000 | D20: =D11*Assumptions!$B$52*D8 -> 960000 | E20: =E11*Assumptions!$B$52*E8 -> 960000 | F20: =F11*Assumptions!$B$52*F8 -> 960000 | G20: =G11*Assumptions!$B$52*G8 -> 960000
A21: Asset insurance | B21: =Debt!$D$5*Assumptions!$B$50*B8 -> 288600 | C21: =Debt!$D$5*Assumptions!$B$50*C8 -> 577200 | D21: =Debt!$D$5*Assumptions!$B$50*D8 -> 577200 | E21: =Debt!$D$5*Assumptions!$B$50*E8 -> 577200 | F21: =Debt!$D$5*Assumptions!$B$50*F8 -> 577200 | G21: =Debt!$D$5*Assumptions!$B$50*G8 -> 577200
A23: Phase 2
A24: Bay age, years | B24: =2027-Assumptions!$B$70 -> -1 | C24: =2028-Assumptions!$B$70 -> 0 | D24: =2029-Assumptions!$B$70 -> 1 | E24: =2030-Assumptions!$B$70 -> 2 | F24: =2031-Assumptions!$B$70 -> 3 | G24: =2032-Assumptions!$B$70 -> 4
A25: Share of year live | B25: =IF(B24<0,0,IF(B24=0,Assumptions!$C$70,1)) -> 0 | C25: =IF(C24<0,0,IF(C24=0,Assumptions!$C$70,1)) -> 0.5 | D25: =IF(D24<0,0,IF(D24=0,Assumptions!$C$70,1)) -> 1 | E25: =IF(E24<0,0,IF(E24=0,Assumptions!$C$70,1)) -> 1 | F25: =IF(F24<0,0,IF(F24=0,Assumptions!$C$70,1)) -> 1 | G25: =IF(G24<0,0,IF(G24=0,Assumptions!$C$70,1)) -> 1
A26: Use factor (live × ramp) | B26: =B25*IF(B24=0,Assumptions!$B$56,IF(B24=1,Assumptions!$B$57,1)) -> 0 | C26: =C25*IF(C24=0,Assumptions!$B$56,IF(C24=1,Assumptions!$B$57,1)) -> 0.275 | D26: =D25*IF(D24=0,Assumptions!$B$56,IF(D24=1,Assumptions!$B$57,1)) -> 0.8 | E26: =E25*IF(E24=0,Assumptions!$B$56,IF(E24=1,Assumptions!$B$57,1)) -> 1 | F26: =F25*IF(F24=0,Assumptions!$B$56,IF(F24=1,Assumptions!$B$57,1)) -> 1 | G26: =G25*IF(G24=0,Assumptions!$B$56,IF(G24=1,Assumptions!$B$57,1)) -> 1
A27: Capex in year | B27: =IF(B24=0,Debt!$J$5,0) -> 0 | C27: =IF(C24=0,Debt!$J$5,0) -> 84175000 | D27: =IF(D24=0,Debt!$J$5,0) -> 0 | E27: =IF(E24=0,Debt!$J$5,0) -> 0 | F27: =IF(F24=0,Debt!$J$5,0) -> 0 | G27: =IF(G24=0,Debt!$J$5,0) -> 0
A28: Bays live | B28: =IF(B24>=0,SUM(Assumptions!$D$70:$F$70),0) -> 0 | C28: =IF(C24>=0,SUM(Assumptions!$D$70:$F$70),0) -> 100 | D28: =IF(D24>=0,SUM(Assumptions!$D$70:$F$70),0) -> 100 | E28: =IF(E24>=0,SUM(Assumptions!$D$70:$F$70),0) -> 100 | F28: =IF(F24>=0,SUM(Assumptions!$D$70:$F$70),0) -> 100 | G28: =IF(G24>=0,SUM(Assumptions!$D$70:$F$70),0) -> 100
A29: Clubs live | B29: =IF(B24>=0,Assumptions!$G$70,0) -> 0 | C29: =IF(C24>=0,Assumptions!$G$70,0) -> 50 | D29: =IF(D24>=0,Assumptions!$G$70,0) -> 50 | E29: =IF(E24>=0,Assumptions!$G$70,0) -> 50 | F29: =IF(F24>=0,Assumptions!$G$70,0) -> 50 | G29: =IF(G24>=0,Assumptions!$G$70,0) -> 50
A30: Booked hours | B30: =(Assumptions!$D$70*MIN(Assumptions!$C$63*$B$2,Assumptions!$B$28)+Assumptions!$E$70*MIN(Assumptions!$C$64*$B$2,Assumptions!$B$28)+Assumptions!$F$70*MIN(Assumptions!$C$65*$B$2,Assumptions!$B$28))*Assumptions!$B$27*B26 -> 0 | C30: =(Assumptions!$D$70*MIN(Assumptions!$C$63*$B$2,Assumptions!$B$28)+Assumptions!$E$70*MIN(Assumptions!$C$64*$B$2,Assumptions!$B$28)+Assumptions!$F$70*MIN(Assumptions!$C$65*$B$2,Assumptions!$B$28))*Assumptions!$B$27*C26 -> 49005 | D30: =(Assumptions!$D$70*MIN(Assumptions!$C$63*$B$2,Assumptions!$B$28)+Assumptions!$E$70*MIN(Assumptions!$C$64*$B$2,Assumptions!$B$28)+Assumptions!$F$70*MIN(Assumptions!$C$65*$B$2,Assumptions!$B$28))*Assumptions!$B$27*D26 -> 142560 | E30: =(Assumptions!$D$70*MIN(Assumptions!$C$63*$B$2,Assumptions!$B$28)+Assumptions!$E$70*MIN(Assumptions!$C$64*$B$2,Assumptions!$B$28)+Assumptions!$F$70*MIN(Assumptions!$C$65*$B$2,Assumptions!$B$28))*Assumptions!$B$27*E26 -> 178200 | F30: =(Assumptions!$D$70*MIN(Assumptions!$C$63*$B$2,Assumptions!$B$28)+Assumptions!$E$70*MIN(Assumptions!$C$64*$B$2,Assumptions!$B$28)+Assumptions!$F$70*MIN(Assumptions!$C$65*$B$2,Assumptions!$B$28))*Assumptions!$B$27*F26 -> 178200 | G30: =(Assumptions!$D$70*MIN(Assumptions!$C$63*$B$2,Assumptions!$B$28)+Assumptions!$E$70*MIN(Assumptions!$C$64*$B$2,Assumptions!$B$28)+Assumptions!$F$70*MIN(Assumptions!$C$65*$B$2,Assumptions!$B$28))*Assumptions!$B$27*G26 -> 178200
A31: Bay hire | B31: =(Assumptions!$D$70*MIN(Assumptions!$C$63*$B$2,Assumptions!$B$28)*Assumptions!$D$63+Assumptions!$E$70*MIN(Assumptions!$C$64*$B$2,Assumptions!$B$28)*Assumptions!$D$64+Assumptions!$F$70*MIN(Assumptions!$C$65*$B$2,Assumptions!$B$28)*Assumptions!$D$65)*Assumptions!$B$27*B26 -> 0 | C31: =(Assumptions!$D$70*MIN(Assumptions!$C$63*$B$2,Assumptions!$B$28)*Assumptions!$D$63+Assumptions!$E$70*MIN(Assumptions!$C$64*$B$2,Assumptions!$B$28)*Assumptions!$D$64+Assumptions!$F$70*MIN(Assumptions!$C$65*$B$2,Assumptions!$B$28)*Assumptions!$D$65)*Assumptions!$B$27*C26 -> 17641800 | D31: =(Assumptions!$D$70*MIN(Assumptions!$C$63*$B$2,Assumptions!$B$28)*Assumptions!$D$63+Assumptions!$E$70*MIN(Assumptions!$C$64*$B$2,Assumptions!$B$28)*Assumptions!$D$64+Assumptions!$F$70*MIN(Assumptions!$C$65*$B$2,Assumptions!$B$28)*Assumptions!$D$65)*Assumptions!$B$27*D26 -> 51321600 | E31: =(Assumptions!$D$70*MIN(Assumptions!$C$63*$B$2,Assumptions!$B$28)*Assumptions!$D$63+Assumptions!$E$70*MIN(Assumptions!$C$64*$B$2,Assumptions!$B$28)*Assumptions!$D$64+Assumptions!$F$70*MIN(Assumptions!$C$65*$B$2,Assumptions!$B$28)*Assumptions!$D$65)*Assumptions!$B$27*E26 -> 64152000 | F31: =(Assumptions!$D$70*MIN(Assumptions!$C$63*$B$2,Assumptions!$B$28)*Assumptions!$D$63+Assumptions!$E$70*MIN(Assumptions!$C$64*$B$2,Assumptions!$B$28)*Assumptions!$D$64+Assumptions!$F$70*MIN(Assumptions!$C$65*$B$2,Assumptions!$B$28)*Assumptions!$D$65)*Assumptions!$B$27*F26 -> 64152000 | G31: =(Assumptions!$D$70*MIN(Assumptions!$C$63*$B$2,Assumptions!$B$28)*Assumptions!$D$63+Assumptions!$E$70*MIN(Assumptions!$C$64*$B$2,Assumptions!$B$28)*Assumptions!$D$64+Assumptions!$F$70*MIN(Assumptions!$C$65*$B$2,Assumptions!$B$28)*Assumptions!$D$65)*Assumptions!$B$27*G26 -> 64152000
A32: Golf add-on | B32: =Assumptions!$G$70*Assumptions!$B$33*Assumptions!$B$35*$B$2*IF(B24=0,Assumptions!$B$36,IF(B24=1,Assumptions!$B$37,1))*Assumptions!$B$34*12*B25 -> 0 | C32: =Assumptions!$G$70*Assumptions!$B$33*Assumptions!$B$35*$B$2*IF(C24=0,Assumptions!$B$36,IF(C24=1,Assumptions!$B$37,1))*Assumptions!$B$34*12*C25 -> 2465430.9 | D32: =Assumptions!$G$70*Assumptions!$B$33*Assumptions!$B$35*$B$2*IF(D24=0,Assumptions!$B$36,IF(D24=1,Assumptions!$B$37,1))*Assumptions!$B$34*12*D25 -> 9245365.8 | E32: =Assumptions!$G$70*Assumptions!$B$33*Assumptions!$B$35*$B$2*IF(E24=0,Assumptions!$B$36,IF(E24=1,Assumptions!$B$37,1))*Assumptions!$B$34*12*E25 -> 12327154 | F32: =Assumptions!$G$70*Assumptions!$B$33*Assumptions!$B$35*$B$2*IF(F24=0,Assumptions!$B$36,IF(F24=1,Assumptions!$B$37,1))*Assumptions!$B$34*12*F25 -> 12327154 | G32: =Assumptions!$G$70*Assumptions!$B$33*Assumptions!$B$35*$B$2*IF(G24=0,Assumptions!$B$36,IF(G24=1,Assumptions!$B$37,1))*Assumptions!$B$34*12*G25 -> 12327154
A33: Leagues, events, corporate | B33: =B28*Assumptions!$B$40*B26 -> 0 | C33: =C28*Assumptions!$B$40*C26 -> 1100000 | D33: =D28*Assumptions!$B$40*D26 -> 3200000 | E33: =E28*Assumptions!$B$40*E26 -> 4000000 | F33: =F28*Assumptions!$B$40*F26 -> 4000000 | G33: =G28*Assumptions!$B$40*G26 -> 4000000
A34: Insured shot, net of premium | B34: =B30*Assumptions!$B$45 -> 0 | C34: =C30*Assumptions!$B$45 -> 1163868.8 | D34: =D30*Assumptions!$B$45 -> 3385800 | E34: =E30*Assumptions!$B$45 -> 4232250 | F34: =F30*Assumptions!$B$45 -> 4232250 | G34: =G30*Assumptions!$B$45 -> 4232250
A35: Naming partner | B35: =B28*Assumptions!$B$41*B25 -> 0 | C35: =C28*Assumptions!$B$41*C25 -> 1250000 | D35: =D28*Assumptions!$B$41*D25 -> 2500000 | E35: =E28*Assumptions!$B$41*E25 -> 2500000 | F35: =F28*Assumptions!$B$41*F25 -> 2500000 | G35: =G28*Assumptions!$B$41*G25 -> 2500000
A36: Golfzon service and software | B36: =(Assumptions!$D$70*Assumptions!$B$63*Assumptions!$B$12+Assumptions!$E$70*Assumptions!$B$64*Assumptions!$B$12+Assumptions!$F$70*Assumptions!$B$65*Assumptions!$B$12)*Assumptions!$B$51*B25 -> 0 | C36: =(Assumptions!$D$70*Assumptions!$B$63*Assumptions!$B$12+Assumptions!$E$70*Assumptions!$B$64*Assumptions!$B$12+Assumptions!$F$70*Assumptions!$B$65*Assumptions!$B$12)*Assumptions!$B$51*C25 -> 1295000 | D36: =(Assumptions!$D$70*Assumptions!$B$63*Assumptions!$B$12+Assumptions!$E$70*Assumptions!$B$64*Assumptions!$B$12+Assumptions!$F$70*Assumptions!$B$65*Assumptions!$B$12)*Assumptions!$B$51*D25 -> 2590000 | E36: =(Assumptions!$D$70*Assumptions!$B$63*Assumptions!$B$12+Assumptions!$E$70*Assumptions!$B$64*Assumptions!$B$12+Assumptions!$F$70*Assumptions!$B$65*Assumptions!$B$12)*Assumptions!$B$51*E25 -> 2590000 | F36: =(Assumptions!$D$70*Assumptions!$B$63*Assumptions!$B$12+Assumptions!$E$70*Assumptions!$B$64*Assumptions!$B$12+Assumptions!$F$70*Assumptions!$B$65*Assumptions!$B$12)*Assumptions!$B$51*F25 -> 2590000 | G36: =(Assumptions!$D$70*Assumptions!$B$63*Assumptions!$B$12+Assumptions!$E$70*Assumptions!$B$64*Assumptions!$B$12+Assumptions!$F$70*Assumptions!$B$65*Assumptions!$B$12)*Assumptions!$B$51*G25 -> 2590000
A37: Consumables and maintenance | B37: =B28*Assumptions!$B$52*B25 -> 0 | C37: =C28*Assumptions!$B$52*C25 -> 1200000 | D37: =D28*Assumptions!$B$52*D25 -> 2400000 | E37: =E28*Assumptions!$B$52*E25 -> 2400000 | F37: =F28*Assumptions!$B$52*F25 -> 2400000 | G37: =G28*Assumptions!$B$52*G25 -> 2400000
A38: Asset insurance | B38: =Debt!$J$5*Assumptions!$B$50*B25 -> 0 | C38: =Debt!$J$5*Assumptions!$B$50*C25 -> 420875 | D38: =Debt!$J$5*Assumptions!$B$50*D25 -> 841750 | E38: =Debt!$J$5*Assumptions!$B$50*E25 -> 841750 | F38: =Debt!$J$5*Assumptions!$B$50*F25 -> 841750 | G38: =Debt!$J$5*Assumptions!$B$50*G25 -> 841750
A40: Phase 3
A41: Bay age, years | B41: =2027-Assumptions!$B$71 -> -2 | C41: =2028-Assumptions!$B$71 -> -1 | D41: =2029-Assumptions!$B$71 -> 0 | E41: =2030-Assumptions!$B$71 -> 1 | F41: =2031-Assumptions!$B$71 -> 2 | G41: =2032-Assumptions!$B$71 -> 3
A42: Share of year live | B42: =IF(B41<0,0,IF(B41=0,Assumptions!$C$71,1)) -> 0 | C42: =IF(C41<0,0,IF(C41=0,Assumptions!$C$71,1)) -> 0 | D42: =IF(D41<0,0,IF(D41=0,Assumptions!$C$71,1)) -> 0.6 | E42: =IF(E41<0,0,IF(E41=0,Assumptions!$C$71,1)) -> 1 | F42: =IF(F41<0,0,IF(F41=0,Assumptions!$C$71,1)) -> 1 | G42: =IF(G41<0,0,IF(G41=0,Assumptions!$C$71,1)) -> 1
A43: Use factor (live × ramp) | B43: =B42*IF(B41=0,Assumptions!$B$56,IF(B41=1,Assumptions!$B$57,1)) -> 0 | C43: =C42*IF(C41=0,Assumptions!$B$56,IF(C41=1,Assumptions!$B$57,1)) -> 0 | D43: =D42*IF(D41=0,Assumptions!$B$56,IF(D41=1,Assumptions!$B$57,1)) -> 0.33 | E43: =E42*IF(E41=0,Assumptions!$B$56,IF(E41=1,Assumptions!$B$57,1)) -> 0.8 | F43: =F42*IF(F41=0,Assumptions!$B$56,IF(F41=1,Assumptions!$B$57,1)) -> 1 | G43: =G42*IF(G41=0,Assumptions!$B$56,IF(G41=1,Assumptions!$B$57,1)) -> 1
A44: Capex in year | B44: =IF(B41=0,Debt!$P$5,0) -> 0 | C44: =IF(C41=0,Debt!$P$5,0) -> 0 | D44: =IF(D41=0,Debt!$P$5,0) -> 37999000 | E44: =IF(E41=0,Debt!$P$5,0) -> 0 | F44: =IF(F41=0,Debt!$P$5,0) -> 0 | G44: =IF(G41=0,Debt!$P$5,0) -> 0
A45: Bays live | B45: =IF(B41>=0,SUM(Assumptions!$D$71:$F$71),0) -> 0 | C45: =IF(C41>=0,SUM(Assumptions!$D$71:$F$71),0) -> 0 | D45: =IF(D41>=0,SUM(Assumptions!$D$71:$F$71),0) -> 60 | E45: =IF(E41>=0,SUM(Assumptions!$D$71:$F$71),0) -> 60 | F45: =IF(F41>=0,SUM(Assumptions!$D$71:$F$71),0) -> 60 | G45: =IF(G41>=0,SUM(Assumptions!$D$71:$F$71),0) -> 60
A46: Clubs live | B46: =IF(B41>=0,Assumptions!$G$71,0) -> 0 | C46: =IF(C41>=0,Assumptions!$G$71,0) -> 0 | D46: =IF(D41>=0,Assumptions!$G$71,0) -> 60 | E46: =IF(E41>=0,Assumptions!$G$71,0) -> 60 | F46: =IF(F41>=0,Assumptions!$G$71,0) -> 60 | G46: =IF(G41>=0,Assumptions!$G$71,0) -> 60
A47: Booked hours | B47: =(Assumptions!$D$71*MIN(Assumptions!$C$63*$B$2,Assumptions!$B$28)+Assumptions!$E$71*MIN(Assumptions!$C$64*$B$2,Assumptions!$B$28)+Assumptions!$F$71*MIN(Assumptions!$C$65*$B$2,Assumptions!$B$28))*Assumptions!$B$27*B43 -> 0 | C47: =(Assumptions!$D$71*MIN(Assumptions!$C$63*$B$2,Assumptions!$B$28)+Assumptions!$E$71*MIN(Assumptions!$C$64*$B$2,Assumptions!$B$28)+Assumptions!$F$71*MIN(Assumptions!$C$65*$B$2,Assumptions!$B$28))*Assumptions!$B$27*C43 -> 0 | D47: =(Assumptions!$D$71*MIN(Assumptions!$C$63*$B$2,Assumptions!$B$28)+Assumptions!$E$71*MIN(Assumptions!$C$64*$B$2,Assumptions!$B$28)+Assumptions!$F$71*MIN(Assumptions!$C$65*$B$2,Assumptions!$B$28))*Assumptions!$B$27*D43 -> 33145.2 | E47: =(Assumptions!$D$71*MIN(Assumptions!$C$63*$B$2,Assumptions!$B$28)+Assumptions!$E$71*MIN(Assumptions!$C$64*$B$2,Assumptions!$B$28)+Assumptions!$F$71*MIN(Assumptions!$C$65*$B$2,Assumptions!$B$28))*Assumptions!$B$27*E43 -> 80352 | F47: =(Assumptions!$D$71*MIN(Assumptions!$C$63*$B$2,Assumptions!$B$28)+Assumptions!$E$71*MIN(Assumptions!$C$64*$B$2,Assumptions!$B$28)+Assumptions!$F$71*MIN(Assumptions!$C$65*$B$2,Assumptions!$B$28))*Assumptions!$B$27*F43 -> 100440 | G47: =(Assumptions!$D$71*MIN(Assumptions!$C$63*$B$2,Assumptions!$B$28)+Assumptions!$E$71*MIN(Assumptions!$C$64*$B$2,Assumptions!$B$28)+Assumptions!$F$71*MIN(Assumptions!$C$65*$B$2,Assumptions!$B$28))*Assumptions!$B$27*G43 -> 100440
A48: Bay hire | B48: =(Assumptions!$D$71*MIN(Assumptions!$C$63*$B$2,Assumptions!$B$28)*Assumptions!$D$63+Assumptions!$E$71*MIN(Assumptions!$C$64*$B$2,Assumptions!$B$28)*Assumptions!$D$64+Assumptions!$F$71*MIN(Assumptions!$C$65*$B$2,Assumptions!$B$28)*Assumptions!$D$65)*Assumptions!$B$27*B43 -> 0 | C48: =(Assumptions!$D$71*MIN(Assumptions!$C$63*$B$2,Assumptions!$B$28)*Assumptions!$D$63+Assumptions!$E$71*MIN(Assumptions!$C$64*$B$2,Assumptions!$B$28)*Assumptions!$D$64+Assumptions!$F$71*MIN(Assumptions!$C$65*$B$2,Assumptions!$B$28)*Assumptions!$D$65)*Assumptions!$B$27*C43 -> 0 | D48: =(Assumptions!$D$71*MIN(Assumptions!$C$63*$B$2,Assumptions!$B$28)*Assumptions!$D$63+Assumptions!$E$71*MIN(Assumptions!$C$64*$B$2,Assumptions!$B$28)*Assumptions!$D$64+Assumptions!$F$71*MIN(Assumptions!$C$65*$B$2,Assumptions!$B$28)*Assumptions!$D$65)*Assumptions!$B$27*D43 -> 9366192 | E48: =(Assumptions!$D$71*MIN(Assumptions!$C$63*$B$2,Assumptions!$B$28)*Assumptions!$D$63+Assumptions!$E$71*MIN(Assumptions!$C$64*$B$2,Assumptions!$B$28)*Assumptions!$D$64+Assumptions!$F$71*MIN(Assumptions!$C$65*$B$2,Assumptions!$B$28)*Assumptions!$D$65)*Assumptions!$B$27*E43 -> 22705920 | F48: =(Assumptions!$D$71*MIN(Assumptions!$C$63*$B$2,Assumptions!$B$28)*Assumptions!$D$63+Assumptions!$E$71*MIN(Assumptions!$C$64*$B$2,Assumptions!$B$28)*Assumptions!$D$64+Assumptions!$F$71*MIN(Assumptions!$C$65*$B$2,Assumptions!$B$28)*Assumptions!$D$65)*Assumptions!$B$27*F43 -> 28382400 | G48: =(Assumptions!$D$71*MIN(Assumptions!$C$63*$B$2,Assumptions!$B$28)*Assumptions!$D$63+Assumptions!$E$71*MIN(Assumptions!$C$64*$B$2,Assumptions!$B$28)*Assumptions!$D$64+Assumptions!$F$71*MIN(Assumptions!$C$65*$B$2,Assumptions!$B$28)*Assumptions!$D$65)*Assumptions!$B$27*G43 -> 28382400
A49: Golf add-on | B49: =Assumptions!$G$71*Assumptions!$B$33*Assumptions!$B$35*$B$2*IF(B41=0,Assumptions!$B$36,IF(B41=1,Assumptions!$B$37,1))*Assumptions!$B$34*12*B42 -> 0 | C49: =Assumptions!$G$71*Assumptions!$B$33*Assumptions!$B$35*$B$2*IF(C41=0,Assumptions!$B$36,IF(C41=1,Assumptions!$B$37,1))*Assumptions!$B$34*12*C42 -> 0 | D49: =Assumptions!$G$71*Assumptions!$B$33*Assumptions!$B$35*$B$2*IF(D41=0,Assumptions!$B$36,IF(D41=1,Assumptions!$B$37,1))*Assumptions!$B$34*12*D42 -> 3550220.5 | E49: =Assumptions!$G$71*Assumptions!$B$33*Assumptions!$B$35*$B$2*IF(E41=0,Assumptions!$B$36,IF(E41=1,Assumptions!$B$37,1))*Assumptions!$B$34*12*E42 -> 11094439 | F49: =Assumptions!$G$71*Assumptions!$B$33*Assumptions!$B$35*$B$2*IF(F41=0,Assumptions!$B$36,IF(F41=1,Assumptions!$B$37,1))*Assumptions!$B$34*12*F42 -> 14792585 | G49: =Assumptions!$G$71*Assumptions!$B$33*Assumptions!$B$35*$B$2*IF(G41=0,Assumptions!$B$36,IF(G41=1,Assumptions!$B$37,1))*Assumptions!$B$34*12*G42 -> 14792585
A50: Leagues, events, corporate | B50: =B45*Assumptions!$B$40*B43 -> 0 | C50: =C45*Assumptions!$B$40*C43 -> 0 | D50: =D45*Assumptions!$B$40*D43 -> 792000 | E50: =E45*Assumptions!$B$40*E43 -> 1920000 | F50: =F45*Assumptions!$B$40*F43 -> 2400000 | G50: =G45*Assumptions!$B$40*G43 -> 2400000
A51: Insured shot, net of premium | B51: =B47*Assumptions!$B$45 -> 0 | C51: =C47*Assumptions!$B$45 -> 0 | D51: =D47*Assumptions!$B$45 -> 787198.5 | E51: =E47*Assumptions!$B$45 -> 1908360 | F51: =F47*Assumptions!$B$45 -> 2385450 | G51: =G47*Assumptions!$B$45 -> 2385450
A52: Naming partner | B52: =B45*Assumptions!$B$41*B42 -> 0 | C52: =C45*Assumptions!$B$41*C42 -> 0 | D52: =D45*Assumptions!$B$41*D42 -> 900000 | E52: =E45*Assumptions!$B$41*E42 -> 1500000 | F52: =F45*Assumptions!$B$41*F42 -> 1500000 | G52: =G45*Assumptions!$B$41*G42 -> 1500000
A53: Golfzon service and software | B53: =(Assumptions!$D$71*Assumptions!$B$63*Assumptions!$B$12+Assumptions!$E$71*Assumptions!$B$64*Assumptions!$B$12+Assumptions!$F$71*Assumptions!$B$65*Assumptions!$B$12)*Assumptions!$B$51*B42 -> 0 | C53: =(Assumptions!$D$71*Assumptions!$B$63*Assumptions!$B$12+Assumptions!$E$71*Assumptions!$B$64*Assumptions!$B$12+Assumptions!$F$71*Assumptions!$B$65*Assumptions!$B$12)*Assumptions!$B$51*C42 -> 0 | D53: =(Assumptions!$D$71*Assumptions!$B$63*Assumptions!$B$12+Assumptions!$E$71*Assumptions!$B$64*Assumptions!$B$12+Assumptions!$F$71*Assumptions!$B$65*Assumptions!$B$12)*Assumptions!$B$51*D42 -> 701520 | E53: =(Assumptions!$D$71*Assumptions!$B$63*Assumptions!$B$12+Assumptions!$E$71*Assumptions!$B$64*Assumptions!$B$12+Assumptions!$F$71*Assumptions!$B$65*Assumptions!$B$12)*Assumptions!$B$51*E42 -> 1169200 | F53: =(Assumptions!$D$71*Assumptions!$B$63*Assumptions!$B$12+Assumptions!$E$71*Assumptions!$B$64*Assumptions!$B$12+Assumptions!$F$71*Assumptions!$B$65*Assumptions!$B$12)*Assumptions!$B$51*F42 -> 1169200 | G53: =(Assumptions!$D$71*Assumptions!$B$63*Assumptions!$B$12+Assumptions!$E$71*Assumptions!$B$64*Assumptions!$B$12+Assumptions!$F$71*Assumptions!$B$65*Assumptions!$B$12)*Assumptions!$B$51*G42 -> 1169200
A54: Consumables and maintenance | B54: =B45*Assumptions!$B$52*B42 -> 0 | C54: =C45*Assumptions!$B$52*C42 -> 0 | D54: =D45*Assumptions!$B$52*D42 -> 864000 | E54: =E45*Assumptions!$B$52*E42 -> 1440000 | F54: =F45*Assumptions!$B$52*F42 -> 1440000 | G54: =G45*Assumptions!$B$52*G42 -> 1440000
A55: Asset insurance | B55: =Debt!$P$5*Assumptions!$B$50*B42 -> 0 | C55: =Debt!$P$5*Assumptions!$B$50*C42 -> 0 | D55: =Debt!$P$5*Assumptions!$B$50*D42 -> 227994 | E55: =Debt!$P$5*Assumptions!$B$50*E42 -> 379990 | F55: =Debt!$P$5*Assumptions!$B$50*F42 -> 379990 | G55: =Debt!$P$5*Assumptions!$B$50*G42 -> 379990
A57: The chain
A58: Bays live, total | B58: =B11+B28+B45 -> 40 | C58: =C11+C28+C45 -> 140 | D58: =D11+D28+D45 -> 200 | E58: =E11+E28+E45 -> 200 | F58: =F11+F28+F45 -> 200 | G58: =G11+G28+G45 -> 200
A59: Clubs with bays | B59: =B12+B29+B46 -> 20 | C59: =C12+C29+C46 -> 70 | D59: =D12+D29+D46 -> 130 | E59: =E12+E29+E46 -> 130 | F59: =F12+F29+F46 -> 130 | G59: =G12+G29+G46 -> 130
A60: Booked bay-hours | B60: =B13+B30+B47 -> 23760 | C60: =C13+C30+C47 -> 118125 | D60: =D13+D30+D47 -> 262105.2 | E60: =E13+E30+E47 -> 344952 | F60: =F13+F30+F47 -> 365040 | G60: =G13+G30+G47 -> 365040
A61: Booked hours a bay a day | B61: =IF(B58=0,0,B60/B58/Assumptions!$B$26) -> 1.65 | C61: =IF(C58=0,0,C60/C58/Assumptions!$B$26) -> 2.34375 | D61: =IF(D58=0,0,D60/D58/Assumptions!$B$26) -> 3.64035 | E61: =IF(E58=0,0,E60/E58/Assumptions!$B$26) -> 4.791 | F61: =IF(F58=0,0,F60/F58/Assumptions!$B$26) -> 5.07 | G61: =IF(G58=0,0,G60/G58/Assumptions!$B$26) -> 5.07
A62: Bay hire | B62: =B14+B31+B48 -> 12355200 | C62: =C14+C31+C48 -> 53584200 | D62: =D14+D31+D48 -> 105615792 | E62: =E14+E31+E48 -> 131785920 | F62: =F14+F31+F48 -> 137462400 | G62: =G14+G31+G48 -> 137462400
A63: Golf add-on memberships | B63: =B15+B32+B49 -> 986172.35 | C63: =C15+C32+C49 -> 6163577.2 | D63: =D15+D32+D49 -> 17726448 | E63: =E15+E32+E49 -> 28352455 | F63: =F15+F32+F49 -> 32050601 | G63: =G15+G32+G49 -> 32050601
A64: Leagues, events, corporate | B64: =B16+B33+B50 -> 440000 | C64: =C16+C33+C50 -> 2380000 | D64: =D16+D33+D50 -> 5592000 | E64: =E16+E33+E50 -> 7520000 | F64: =F16+F33+F50 -> 8000000 | G64: =G16+G33+G50 -> 8000000
A65: Get Lucky insured shot, net of premium | B65: =B17+B34+B51 -> 564300 | C65: =C17+C34+C51 -> 2805468.8 | D65: =D17+D34+D51 -> 6224998.5 | E65: =E17+E34+E51 -> 8192610 | F65: =F17+F34+F51 -> 8669700 | G65: =G17+G34+G51 -> 8669700
A66: Naming partner | B66: =B18+B35+B52 -> 500000 | C66: =C18+C35+C52 -> 2250000 | D66: =D18+D35+D52 -> 4400000 | E66: =E18+E35+E52 -> 5000000 | F66: =F18+F35+F52 -> 5000000 | G66: =G18+G35+G52 -> 5000000
A67: Revenue shared with Virgin Active | B67: =B62+B63+B64+B65 -> 14345672 | C67: =C62+C63+C64+C65 -> 64933246 | D67: =D62+D63+D64+D65 -> 1.3515924e+08 | E67: =E62+E63+E64+E65 -> 1.7585099e+08 | F67: =F62+F63+F64+F65 -> 1.861827e+08 | G67: =G62+G63+G64+G65 -> 1.861827e+08
A68: Revenue | B68: =B67+B66 -> 14845672 | C68: =C67+C66 -> 67183246 | D68: =D67+D66 -> 1.3955924e+08 | E68: =E67+E66 -> 1.8085099e+08 | F68: =F67+F66 -> 1.911827e+08 | G68: =G67+G66 -> 1.911827e+08
A69: Virgin Active concession | B69: =-B67*Assumptions!$B$24 -> -2869134.5 | C69: =-C67*Assumptions!$B$24 -> -12986649 | D69: =-D67*Assumptions!$B$24 -> -27031848 | E69: =-E67*Assumptions!$B$24 -> -35170197 | F69: =-F67*Assumptions!$B$24 -> -37236540 | G69: =-G67*Assumptions!$B$24 -> -37236540
A70: Card and booking fees | B70: =-B67*Assumptions!$B$48 -> -358641.81 | C70: =-C67*Assumptions!$B$48 -> -1623331.1 | D70: =-D67*Assumptions!$B$48 -> -3378981 | E70: =-E67*Assumptions!$B$48 -> -4396274.6 | F70: =-F67*Assumptions!$B$48 -> -4654567.5 | G70: =-G67*Assumptions!$B$48 -> -4654567.5
A71: Marketing | B71: =-B68*Assumptions!$B$49 -> -742283.62 | C71: =-C68*Assumptions!$B$49 -> -3359162.3 | D71: =-D68*Assumptions!$B$49 -> -6977961.9 | E71: =-E68*Assumptions!$B$49 -> -9042549.3 | F71: =-F68*Assumptions!$B$49 -> -9559135.1 | G71: =-G68*Assumptions!$B$49 -> -9559135.1
A72: Golfzon service and software | B72: =-(B19+B36+B53) -> -888000 | C72: =-(C19+C36+C53) -> -3071000 | D72: =-(D19+D36+D53) -> -5067520 | E72: =-(E19+E36+E53) -> -5535200 | F72: =-(F19+F36+F53) -> -5535200 | G72: =-(G19+G36+G53) -> -5535200
A73: Consumables and maintenance | B73: =-(B20+B37+B54) -> -480000 | C73: =-(C20+C37+C54) -> -2160000 | D73: =-(D20+D37+D54) -> -4224000 | E73: =-(E20+E37+E54) -> -4800000 | F73: =-(F20+F37+F54) -> -4800000 | G73: =-(G20+G37+G54) -> -4800000
A74: Asset insurance | B74: =-(B21+B38+B55) -> -288600 | C74: =-(C21+C38+C55) -> -998075 | D74: =-(D21+D38+D55) -> -1646944 | E74: =-(E21+E38+E55) -> -1798940 | F74: =-(F21+F38+F55) -> -1798940 | G74: =-(G21+G38+G55) -> -1798940
A75: People | B75: =-Assumptions!B75 -> -4000000 | C75: =-Assumptions!C75 -> -8000000 | D75: =-Assumptions!D75 -> -11000000 | E75: =-Assumptions!E75 -> -12000000 | F75: =-Assumptions!F75 -> -12000000 | G75: =-Assumptions!G75 -> -12000000
A76: Central overhead | B76: =-Assumptions!B76 -> -2000000 | C76: =-Assumptions!C76 -> -3000000 | D76: =-Assumptions!D76 -> -4000000 | E76: =-Assumptions!E76 -> -4000000 | F76: =-Assumptions!F76 -> -4000000 | G76: =-Assumptions!G76 -> -4000000
A77: EBITDA | B77: =SUM(B68:B76) -> 3219012.5 | C77: =SUM(C68:C76) -> 31985028 | D77: =SUM(D68:D76) -> 76231984 | E77: =SUM(E68:E76) -> 1.0410782e+08 | F77: =SUM(F68:F76) -> 1.1159832e+08 | G77: =SUM(G68:G76) -> 1.1159832e+08
A78: EBITDA margin | B78: =IF(B68=0,0,B77/B68) -> 0.21683171 | C78: =IF(C68=0,0,C77/C68) -> 0.47608638 | D78: =IF(D68=0,0,D77/D68) -> 0.54623388 | E78: =IF(E68=0,0,E77/E68) -> 0.57565528 | F78: =IF(F68=0,0,F77/F68) -> 0.58372603 | G78: =IF(G68=0,0,G77/G68) -> 0.58372603
A79: RMB interest | B79: =-Debt!B93 -> -6233760 | C79: =-Debt!C93 -> -14890537 | D79: =-Debt!D93 -> -17338234 | E79: =-Debt!E93 -> -14407561 | F79: =-Debt!F93 -> -10753709 | G79: =-Debt!G93 -> -6636457.6
A80: RMB capital | B80: =-Debt!B94 -> 0 | C80: =-Debt!C94 -> -8067017.6 | D80: =-Debt!D94 -> -20854518 | E80: =-Debt!E94 -> -28810180 | F80: =-Debt!F94 -> -32464031 | G80: =-Debt!G94 -> -36581283
A81: Debt service | B81: =B79+B80 -> -6233760 | C81: =C79+C80 -> -22957555 | D81: =D79+D80 -> -38192752 | E81: =E79+E80 -> -43217741 | F81: =F79+F80 -> -43217741 | G81: =G79+G80 -> -43217741
A82: Debt cover (EBITDA ÷ debt service) | B82: =IF(B81=0,0,B77/-B81) -> 0.51638376 | C82: =IF(C81=0,0,C77/-C81) -> 1.3932245 | D82: =IF(D81=0,0,D77/-D81) -> 1.9959804 | E82: =IF(E81=0,0,E77/-E81) -> 2.4089141 | F82: =IF(F81=0,0,F77/-F81) -> 2.582234 | G82: =IF(G81=0,0,G77/-G81) -> 2.582234
A83: Cash after debt | B83: =B77+B81 -> -3014747.5 | C83: =C77+C81 -> 9027473.5 | D83: =D77+D81 -> 38039232 | E83: =E77+E81 -> 60890083 | F83: =F77+F81 -> 68380578 | G83: =G77+G81 -> 68380578
A84: Capex in year | B84: =B10+B27+B44 -> 57720000 | C84: =C10+C27+C44 -> 84175000 | D84: =D10+D27+D44 -> 37999000 | E84: =E10+E27+E44 -> 0 | F84: =F10+F27+F44 -> 0 | G84: =G10+G27+G44 -> 0
A85: Equity deposit (capex not financed by RMB) | B85: =-B84*(1-Assumptions!$B$18) -> -5772000 | C85: =-C84*(1-Assumptions!$B$18) -> -8417500 | D85: =-D84*(1-Assumptions!$B$18) -> -3799900 | E85: =-E84*(1-Assumptions!$B$18) -> 0 | F85: =-F84*(1-Assumptions!$B$18) -> 0 | G85: =-G84*(1-Assumptions!$B$18) -> 0
A86: Cumulative cash after deposits | B86: =B83+B85 -> -8786747.5 | C86: =C83+C85+B86 -> -8176774 | D86: =D83+D85+C86 -> 26062558 | E86: =E83+E85+D86 -> 86952642 | F86: =F83+F85+E86 -> 1.5533322e+08 | G86: =G83+G85+F86 -> 2.237138e+08
A87: Memo: to Virgin Active | B87: =-B69 -> 2869134.5 | C87: =-C69 -> 12986649 | D87: =-D69 -> 27031848 | E87: =-E69 -> 35170197 | F87: =-F69 -> 37236540 | G87: =-G69 -> 37236540
A89: Equity needed (lowest point of cumulative cash) | B89: =-MIN(B86:G86) -> 8786747.5

Sheet Chain low
A1: The chain, 2027 to 2032 — low case (fixed at the low multiplier)
A2: Utilisation multiplier | B2: =Assumptions!$B$7 -> 0.7
A4: Year | B4: 2027 | C4: 2028 | D4: 2029 | E4: 2030 | F4: 2031 | G4: 2032
A6: Phase 1
A7: Bay age, years | B7: =2027-Assumptions!$B$69 -> 0 | C7: =2028-Assumptions!$B$69 -> 1 | D7: =2029-Assumptions!$B$69 -> 2 | E7: =2030-Assumptions!$B$69 -> 3 | F7: =2031-Assumptions!$B$69 -> 4 | G7: =2032-Assumptions!$B$69 -> 5
A8: Share of year live | B8: =IF(B7<0,0,IF(B7=0,Assumptions!$C$69,1)) -> 0.5 | C8: =IF(C7<0,0,IF(C7=0,Assumptions!$C$69,1)) -> 1 | D8: =IF(D7<0,0,IF(D7=0,Assumptions!$C$69,1)) -> 1 | E8: =IF(E7<0,0,IF(E7=0,Assumptions!$C$69,1)) -> 1 | F8: =IF(F7<0,0,IF(F7=0,Assumptions!$C$69,1)) -> 1 | G8: =IF(G7<0,0,IF(G7=0,Assumptions!$C$69,1)) -> 1
A9: Use factor (live × ramp) | B9: =B8*IF(B7=0,Assumptions!$B$56,IF(B7=1,Assumptions!$B$57,1)) -> 0.275 | C9: =C8*IF(C7=0,Assumptions!$B$56,IF(C7=1,Assumptions!$B$57,1)) -> 0.8 | D9: =D8*IF(D7=0,Assumptions!$B$56,IF(D7=1,Assumptions!$B$57,1)) -> 1 | E9: =E8*IF(E7=0,Assumptions!$B$56,IF(E7=1,Assumptions!$B$57,1)) -> 1 | F9: =F8*IF(F7=0,Assumptions!$B$56,IF(F7=1,Assumptions!$B$57,1)) -> 1 | G9: =G8*IF(G7=0,Assumptions!$B$56,IF(G7=1,Assumptions!$B$57,1)) -> 1
A10: Capex in year | B10: =IF(B7=0,Debt!$D$5,0) -> 57720000 | C10: =IF(C7=0,Debt!$D$5,0) -> 0 | D10: =IF(D7=0,Debt!$D$5,0) -> 0 | E10: =IF(E7=0,Debt!$D$5,0) -> 0 | F10: =IF(F7=0,Debt!$D$5,0) -> 0 | G10: =IF(G7=0,Debt!$D$5,0) -> 0
A11: Bays live | B11: =IF(B7>=0,SUM(Assumptions!$D$69:$F$69),0) -> 40 | C11: =IF(C7>=0,SUM(Assumptions!$D$69:$F$69),0) -> 40 | D11: =IF(D7>=0,SUM(Assumptions!$D$69:$F$69),0) -> 40 | E11: =IF(E7>=0,SUM(Assumptions!$D$69:$F$69),0) -> 40 | F11: =IF(F7>=0,SUM(Assumptions!$D$69:$F$69),0) -> 40 | G11: =IF(G7>=0,SUM(Assumptions!$D$69:$F$69),0) -> 40
A12: Clubs live | B12: =IF(B7>=0,Assumptions!$G$69,0) -> 20 | C12: =IF(C7>=0,Assumptions!$G$69,0) -> 20 | D12: =IF(D7>=0,Assumptions!$G$69,0) -> 20 | E12: =IF(E7>=0,Assumptions!$G$69,0) -> 20 | F12: =IF(F7>=0,Assumptions!$G$69,0) -> 20 | G12: =IF(G7>=0,Assumptions!$G$69,0) -> 20
A13: Booked hours | B13: =(Assumptions!$D$69*MIN(Assumptions!$C$63*$B$2,Assumptions!$B$28)+Assumptions!$E$69*MIN(Assumptions!$C$64*$B$2,Assumptions!$B$28)+Assumptions!$F$69*MIN(Assumptions!$C$65*$B$2,Assumptions!$B$28))*Assumptions!$B$27*B9 -> 16632 | C13: =(Assumptions!$D$69*MIN(Assumptions!$C$63*$B$2,Assumptions!$B$28)+Assumptions!$E$69*MIN(Assumptions!$C$64*$B$2,Assumptions!$B$28)+Assumptions!$F$69*MIN(Assumptions!$C$65*$B$2,Assumptions!$B$28))*Assumptions!$B$27*C9 -> 48384 | D13: =(Assumptions!$D$69*MIN(Assumptions!$C$63*$B$2,Assumptions!$B$28)+Assumptions!$E$69*MIN(Assumptions!$C$64*$B$2,Assumptions!$B$28)+Assumptions!$F$69*MIN(Assumptions!$C$65*$B$2,Assumptions!$B$28))*Assumptions!$B$27*D9 -> 60480 | E13: =(Assumptions!$D$69*MIN(Assumptions!$C$63*$B$2,Assumptions!$B$28)+Assumptions!$E$69*MIN(Assumptions!$C$64*$B$2,Assumptions!$B$28)+Assumptions!$F$69*MIN(Assumptions!$C$65*$B$2,Assumptions!$B$28))*Assumptions!$B$27*E9 -> 60480 | F13: =(Assumptions!$D$69*MIN(Assumptions!$C$63*$B$2,Assumptions!$B$28)+Assumptions!$E$69*MIN(Assumptions!$C$64*$B$2,Assumptions!$B$28)+Assumptions!$F$69*MIN(Assumptions!$C$65*$B$2,Assumptions!$B$28))*Assumptions!$B$27*F9 -> 60480 | G13: =(Assumptions!$D$69*MIN(Assumptions!$C$63*$B$2,Assumptions!$B$28)+Assumptions!$E$69*MIN(Assumptions!$C$64*$B$2,Assumptions!$B$28)+Assumptions!$F$69*MIN(Assumptions!$C$65*$B$2,Assumptions!$B$28))*Assumptions!$B$27*G9 -> 60480
A14: Bay hire | B14: =(Assumptions!$D$69*MIN(Assumptions!$C$63*$B$2,Assumptions!$B$28)*Assumptions!$D$63+Assumptions!$E$69*MIN(Assumptions!$C$64*$B$2,Assumptions!$B$28)*Assumptions!$D$64+Assumptions!$F$69*MIN(Assumptions!$C$65*$B$2,Assumptions!$B$28)*Assumptions!$D$65)*Assumptions!$B$27*B9 -> 8648640 | C14: =(Assumptions!$D$69*MIN(Assumptions!$C$63*$B$2,Assumptions!$B$28)*Assumptions!$D$63+Assumptions!$E$69*MIN(Assumptions!$C$64*$B$2,Assumptions!$B$28)*Assumptions!$D$64+Assumptions!$F$69*MIN(Assumptions!$C$65*$B$2,Assumptions!$B$28)*Assumptions!$D$65)*Assumptions!$B$27*C9 -> 25159680 | D14: =(Assumptions!$D$69*MIN(Assumptions!$C$63*$B$2,Assumptions!$B$28)*Assumptions!$D$63+Assumptions!$E$69*MIN(Assumptions!$C$64*$B$2,Assumptions!$B$28)*Assumptions!$D$64+Assumptions!$F$69*MIN(Assumptions!$C$65*$B$2,Assumptions!$B$28)*Assumptions!$D$65)*Assumptions!$B$27*D9 -> 31449600 | E14: =(Assumptions!$D$69*MIN(Assumptions!$C$63*$B$2,Assumptions!$B$28)*Assumptions!$D$63+Assumptions!$E$69*MIN(Assumptions!$C$64*$B$2,Assumptions!$B$28)*Assumptions!$D$64+Assumptions!$F$69*MIN(Assumptions!$C$65*$B$2,Assumptions!$B$28)*Assumptions!$D$65)*Assumptions!$B$27*E9 -> 31449600 | F14: =(Assumptions!$D$69*MIN(Assumptions!$C$63*$B$2,Assumptions!$B$28)*Assumptions!$D$63+Assumptions!$E$69*MIN(Assumptions!$C$64*$B$2,Assumptions!$B$28)*Assumptions!$D$64+Assumptions!$F$69*MIN(Assumptions!$C$65*$B$2,Assumptions!$B$28)*Assumptions!$D$65)*Assumptions!$B$27*F9 -> 31449600 | G14: =(Assumptions!$D$69*MIN(Assumptions!$C$63*$B$2,Assumptions!$B$28)*Assumptions!$D$63+Assumptions!$E$69*MIN(Assumptions!$C$64*$B$2,Assumptions!$B$28)*Assumptions!$D$64+Assumptions!$F$69*MIN(Assumptions!$C$65*$B$2,Assumptions!$B$28)*Assumptions!$D$65)*Assumptions!$B$27*G9 -> 31449600
A15: Golf add-on | B15: =Assumptions!$G$69*Assumptions!$B$33*Assumptions!$B$35*$B$2*IF(B7=0,Assumptions!$B$36,IF(B7=1,Assumptions!$B$37,1))*Assumptions!$B$34*12*B8 -> 690320.65 | C15: =Assumptions!$G$69*Assumptions!$B$33*Assumptions!$B$35*$B$2*IF(C7=0,Assumptions!$B$36,IF(C7=1,Assumptions!$B$37,1))*Assumptions!$B$34*12*C8 -> 2588702.4 | D15: =Assumptions!$G$69*Assumptions!$B$33*Assumptions!$B$35*$B$2*IF(D7=0,Assumptions!$B$36,IF(D7=1,Assumptions!$B$37,1))*Assumptions!$B$34*12*D8 -> 3451603.2 | E15: =Assumptions!$G$69*Assumptions!$B$33*Assumptions!$B$35*$B$2*IF(E7=0,Assumptions!$B$36,IF(E7=1,Assumptions!$B$37,1))*Assumptions!$B$34*12*E8 -> 3451603.2 | F15: =Assumptions!$G$69*Assumptions!$B$33*Assumptions!$B$35*$B$2*IF(F7=0,Assumptions!$B$36,IF(F7=1,Assumptions!$B$37,1))*Assumptions!$B$34*12*F8 -> 3451603.2 | G15: =Assumptions!$G$69*Assumptions!$B$33*Assumptions!$B$35*$B$2*IF(G7=0,Assumptions!$B$36,IF(G7=1,Assumptions!$B$37,1))*Assumptions!$B$34*12*G8 -> 3451603.2
A16: Leagues, events, corporate | B16: =B11*Assumptions!$B$40*B9 -> 440000 | C16: =C11*Assumptions!$B$40*C9 -> 1280000 | D16: =D11*Assumptions!$B$40*D9 -> 1600000 | E16: =E11*Assumptions!$B$40*E9 -> 1600000 | F16: =F11*Assumptions!$B$40*F9 -> 1600000 | G16: =G11*Assumptions!$B$40*G9 -> 1600000
A17: Insured shot, net of premium | B17: =B13*Assumptions!$B$45 -> 395010 | C17: =C13*Assumptions!$B$45 -> 1149120 | D17: =D13*Assumptions!$B$45 -> 1436400 | E17: =E13*Assumptions!$B$45 -> 1436400 | F17: =F13*Assumptions!$B$45 -> 1436400 | G17: =G13*Assumptions!$B$45 -> 1436400
A18: Naming partner | B18: =B11*Assumptions!$B$41*B8 -> 500000 | C18: =C11*Assumptions!$B$41*C8 -> 1000000 | D18: =D11*Assumptions!$B$41*D8 -> 1000000 | E18: =E11*Assumptions!$B$41*E8 -> 1000000 | F18: =F11*Assumptions!$B$41*F8 -> 1000000 | G18: =G11*Assumptions!$B$41*G8 -> 1000000
A19: Golfzon service and software | B19: =(Assumptions!$D$69*Assumptions!$B$63*Assumptions!$B$12+Assumptions!$E$69*Assumptions!$B$64*Assumptions!$B$12+Assumptions!$F$69*Assumptions!$B$65*Assumptions!$B$12)*Assumptions!$B$51*B8 -> 888000 | C19: =(Assumptions!$D$69*Assumptions!$B$63*Assumptions!$B$12+Assumptions!$E$69*Assumptions!$B$64*Assumptions!$B$12+Assumptions!$F$69*Assumptions!$B$65*Assumptions!$B$12)*Assumptions!$B$51*C8 -> 1776000 | D19: =(Assumptions!$D$69*Assumptions!$B$63*Assumptions!$B$12+Assumptions!$E$69*Assumptions!$B$64*Assumptions!$B$12+Assumptions!$F$69*Assumptions!$B$65*Assumptions!$B$12)*Assumptions!$B$51*D8 -> 1776000 | E19: =(Assumptions!$D$69*Assumptions!$B$63*Assumptions!$B$12+Assumptions!$E$69*Assumptions!$B$64*Assumptions!$B$12+Assumptions!$F$69*Assumptions!$B$65*Assumptions!$B$12)*Assumptions!$B$51*E8 -> 1776000 | F19: =(Assumptions!$D$69*Assumptions!$B$63*Assumptions!$B$12+Assumptions!$E$69*Assumptions!$B$64*Assumptions!$B$12+Assumptions!$F$69*Assumptions!$B$65*Assumptions!$B$12)*Assumptions!$B$51*F8 -> 1776000 | G19: =(Assumptions!$D$69*Assumptions!$B$63*Assumptions!$B$12+Assumptions!$E$69*Assumptions!$B$64*Assumptions!$B$12+Assumptions!$F$69*Assumptions!$B$65*Assumptions!$B$12)*Assumptions!$B$51*G8 -> 1776000
A20: Consumables and maintenance | B20: =B11*Assumptions!$B$52*B8 -> 480000 | C20: =C11*Assumptions!$B$52*C8 -> 960000 | D20: =D11*Assumptions!$B$52*D8 -> 960000 | E20: =E11*Assumptions!$B$52*E8 -> 960000 | F20: =F11*Assumptions!$B$52*F8 -> 960000 | G20: =G11*Assumptions!$B$52*G8 -> 960000
A21: Asset insurance | B21: =Debt!$D$5*Assumptions!$B$50*B8 -> 288600 | C21: =Debt!$D$5*Assumptions!$B$50*C8 -> 577200 | D21: =Debt!$D$5*Assumptions!$B$50*D8 -> 577200 | E21: =Debt!$D$5*Assumptions!$B$50*E8 -> 577200 | F21: =Debt!$D$5*Assumptions!$B$50*F8 -> 577200 | G21: =Debt!$D$5*Assumptions!$B$50*G8 -> 577200
A23: Phase 2
A24: Bay age, years | B24: =2027-Assumptions!$B$70 -> -1 | C24: =2028-Assumptions!$B$70 -> 0 | D24: =2029-Assumptions!$B$70 -> 1 | E24: =2030-Assumptions!$B$70 -> 2 | F24: =2031-Assumptions!$B$70 -> 3 | G24: =2032-Assumptions!$B$70 -> 4
A25: Share of year live | B25: =IF(B24<0,0,IF(B24=0,Assumptions!$C$70,1)) -> 0 | C25: =IF(C24<0,0,IF(C24=0,Assumptions!$C$70,1)) -> 0.5 | D25: =IF(D24<0,0,IF(D24=0,Assumptions!$C$70,1)) -> 1 | E25: =IF(E24<0,0,IF(E24=0,Assumptions!$C$70,1)) -> 1 | F25: =IF(F24<0,0,IF(F24=0,Assumptions!$C$70,1)) -> 1 | G25: =IF(G24<0,0,IF(G24=0,Assumptions!$C$70,1)) -> 1
A26: Use factor (live × ramp) | B26: =B25*IF(B24=0,Assumptions!$B$56,IF(B24=1,Assumptions!$B$57,1)) -> 0 | C26: =C25*IF(C24=0,Assumptions!$B$56,IF(C24=1,Assumptions!$B$57,1)) -> 0.275 | D26: =D25*IF(D24=0,Assumptions!$B$56,IF(D24=1,Assumptions!$B$57,1)) -> 0.8 | E26: =E25*IF(E24=0,Assumptions!$B$56,IF(E24=1,Assumptions!$B$57,1)) -> 1 | F26: =F25*IF(F24=0,Assumptions!$B$56,IF(F24=1,Assumptions!$B$57,1)) -> 1 | G26: =G25*IF(G24=0,Assumptions!$B$56,IF(G24=1,Assumptions!$B$57,1)) -> 1
A27: Capex in year | B27: =IF(B24=0,Debt!$J$5,0) -> 0 | C27: =IF(C24=0,Debt!$J$5,0) -> 84175000 | D27: =IF(D24=0,Debt!$J$5,0) -> 0 | E27: =IF(E24=0,Debt!$J$5,0) -> 0 | F27: =IF(F24=0,Debt!$J$5,0) -> 0 | G27: =IF(G24=0,Debt!$J$5,0) -> 0
A28: Bays live | B28: =IF(B24>=0,SUM(Assumptions!$D$70:$F$70),0) -> 0 | C28: =IF(C24>=0,SUM(Assumptions!$D$70:$F$70),0) -> 100 | D28: =IF(D24>=0,SUM(Assumptions!$D$70:$F$70),0) -> 100 | E28: =IF(E24>=0,SUM(Assumptions!$D$70:$F$70),0) -> 100 | F28: =IF(F24>=0,SUM(Assumptions!$D$70:$F$70),0) -> 100 | G28: =IF(G24>=0,SUM(Assumptions!$D$70:$F$70),0) -> 100
A29: Clubs live | B29: =IF(B24>=0,Assumptions!$G$70,0) -> 0 | C29: =IF(C24>=0,Assumptions!$G$70,0) -> 50 | D29: =IF(D24>=0,Assumptions!$G$70,0) -> 50 | E29: =IF(E24>=0,Assumptions!$G$70,0) -> 50 | F29: =IF(F24>=0,Assumptions!$G$70,0) -> 50 | G29: =IF(G24>=0,Assumptions!$G$70,0) -> 50
A30: Booked hours | B30: =(Assumptions!$D$70*MIN(Assumptions!$C$63*$B$2,Assumptions!$B$28)+Assumptions!$E$70*MIN(Assumptions!$C$64*$B$2,Assumptions!$B$28)+Assumptions!$F$70*MIN(Assumptions!$C$65*$B$2,Assumptions!$B$28))*Assumptions!$B$27*B26 -> 0 | C30: =(Assumptions!$D$70*MIN(Assumptions!$C$63*$B$2,Assumptions!$B$28)+Assumptions!$E$70*MIN(Assumptions!$C$64*$B$2,Assumptions!$B$28)+Assumptions!$F$70*MIN(Assumptions!$C$65*$B$2,Assumptions!$B$28))*Assumptions!$B$27*C26 -> 34303.5 | D30: =(Assumptions!$D$70*MIN(Assumptions!$C$63*$B$2,Assumptions!$B$28)+Assumptions!$E$70*MIN(Assumptions!$C$64*$B$2,Assumptions!$B$28)+Assumptions!$F$70*MIN(Assumptions!$C$65*$B$2,Assumptions!$B$28))*Assumptions!$B$27*D26 -> 99792 | E30: =(Assumptions!$D$70*MIN(Assumptions!$C$63*$B$2,Assumptions!$B$28)+Assumptions!$E$70*MIN(Assumptions!$C$64*$B$2,Assumptions!$B$28)+Assumptions!$F$70*MIN(Assumptions!$C$65*$B$2,Assumptions!$B$28))*Assumptions!$B$27*E26 -> 124740 | F30: =(Assumptions!$D$70*MIN(Assumptions!$C$63*$B$2,Assumptions!$B$28)+Assumptions!$E$70*MIN(Assumptions!$C$64*$B$2,Assumptions!$B$28)+Assumptions!$F$70*MIN(Assumptions!$C$65*$B$2,Assumptions!$B$28))*Assumptions!$B$27*F26 -> 124740 | G30: =(Assumptions!$D$70*MIN(Assumptions!$C$63*$B$2,Assumptions!$B$28)+Assumptions!$E$70*MIN(Assumptions!$C$64*$B$2,Assumptions!$B$28)+Assumptions!$F$70*MIN(Assumptions!$C$65*$B$2,Assumptions!$B$28))*Assumptions!$B$27*G26 -> 124740
A31: Bay hire | B31: =(Assumptions!$D$70*MIN(Assumptions!$C$63*$B$2,Assumptions!$B$28)*Assumptions!$D$63+Assumptions!$E$70*MIN(Assumptions!$C$64*$B$2,Assumptions!$B$28)*Assumptions!$D$64+Assumptions!$F$70*MIN(Assumptions!$C$65*$B$2,Assumptions!$B$28)*Assumptions!$D$65)*Assumptions!$B$27*B26 -> 0 | C31: =(Assumptions!$D$70*MIN(Assumptions!$C$63*$B$2,Assumptions!$B$28)*Assumptions!$D$63+Assumptions!$E$70*MIN(Assumptions!$C$64*$B$2,Assumptions!$B$28)*Assumptions!$D$64+Assumptions!$F$70*MIN(Assumptions!$C$65*$B$2,Assumptions!$B$28)*Assumptions!$D$65)*Assumptions!$B$27*C26 -> 12349260 | D31: =(Assumptions!$D$70*MIN(Assumptions!$C$63*$B$2,Assumptions!$B$28)*Assumptions!$D$63+Assumptions!$E$70*MIN(Assumptions!$C$64*$B$2,Assumptions!$B$28)*Assumptions!$D$64+Assumptions!$F$70*MIN(Assumptions!$C$65*$B$2,Assumptions!$B$28)*Assumptions!$D$65)*Assumptions!$B$27*D26 -> 35925120 | E31: =(Assumptions!$D$70*MIN(Assumptions!$C$63*$B$2,Assumptions!$B$28)*Assumptions!$D$63+Assumptions!$E$70*MIN(Assumptions!$C$64*$B$2,Assumptions!$B$28)*Assumptions!$D$64+Assumptions!$F$70*MIN(Assumptions!$C$65*$B$2,Assumptions!$B$28)*Assumptions!$D$65)*Assumptions!$B$27*E26 -> 44906400 | F31: =(Assumptions!$D$70*MIN(Assumptions!$C$63*$B$2,Assumptions!$B$28)*Assumptions!$D$63+Assumptions!$E$70*MIN(Assumptions!$C$64*$B$2,Assumptions!$B$28)*Assumptions!$D$64+Assumptions!$F$70*MIN(Assumptions!$C$65*$B$2,Assumptions!$B$28)*Assumptions!$D$65)*Assumptions!$B$27*F26 -> 44906400 | G31: =(Assumptions!$D$70*MIN(Assumptions!$C$63*$B$2,Assumptions!$B$28)*Assumptions!$D$63+Assumptions!$E$70*MIN(Assumptions!$C$64*$B$2,Assumptions!$B$28)*Assumptions!$D$64+Assumptions!$F$70*MIN(Assumptions!$C$65*$B$2,Assumptions!$B$28)*Assumptions!$D$65)*Assumptions!$B$27*G26 -> 44906400
A32: Golf add-on | B32: =Assumptions!$G$70*Assumptions!$B$33*Assumptions!$B$35*$B$2*IF(B24=0,Assumptions!$B$36,IF(B24=1,Assumptions!$B$37,1))*Assumptions!$B$34*12*B25 -> 0 | C32: =Assumptions!$G$70*Assumptions!$B$33*Assumptions!$B$35*$B$2*IF(C24=0,Assumptions!$B$36,IF(C24=1,Assumptions!$B$37,1))*Assumptions!$B$34*12*C25 -> 1725801.6 | D32: =Assumptions!$G$70*Assumptions!$B$33*Assumptions!$B$35*$B$2*IF(D24=0,Assumptions!$B$36,IF(D24=1,Assumptions!$B$37,1))*Assumptions!$B$34*12*D25 -> 6471756.1 | E32: =Assumptions!$G$70*Assumptions!$B$33*Assumptions!$B$35*$B$2*IF(E24=0,Assumptions!$B$36,IF(E24=1,Assumptions!$B$37,1))*Assumptions!$B$34*12*E25 -> 8629008.1 | F32: =Assumptions!$G$70*Assumptions!$B$33*Assumptions!$B$35*$B$2*IF(F24=0,Assumptions!$B$36,IF(F24=1,Assumptions!$B$37,1))*Assumptions!$B$34*12*F25 -> 8629008.1 | G32: =Assumptions!$G$70*Assumptions!$B$33*Assumptions!$B$35*$B$2*IF(G24=0,Assumptions!$B$36,IF(G24=1,Assumptions!$B$37,1))*Assumptions!$B$34*12*G25 -> 8629008.1
A33: Leagues, events, corporate | B33: =B28*Assumptions!$B$40*B26 -> 0 | C33: =C28*Assumptions!$B$40*C26 -> 1100000 | D33: =D28*Assumptions!$B$40*D26 -> 3200000 | E33: =E28*Assumptions!$B$40*E26 -> 4000000 | F33: =F28*Assumptions!$B$40*F26 -> 4000000 | G33: =G28*Assumptions!$B$40*G26 -> 4000000
A34: Insured shot, net of premium | B34: =B30*Assumptions!$B$45 -> 0 | C34: =C30*Assumptions!$B$45 -> 814708.12 | D34: =D30*Assumptions!$B$45 -> 2370060 | E34: =E30*Assumptions!$B$45 -> 2962575 | F34: =F30*Assumptions!$B$45 -> 2962575 | G34: =G30*Assumptions!$B$45 -> 2962575
A35: Naming partner | B35: =B28*Assumptions!$B$41*B25 -> 0 | C35: =C28*Assumptions!$B$41*C25 -> 1250000 | D35: =D28*Assumptions!$B$41*D25 -> 2500000 | E35: =E28*Assumptions!$B$41*E25 -> 2500000 | F35: =F28*Assumptions!$B$41*F25 -> 2500000 | G35: =G28*Assumptions!$B$41*G25 -> 2500000
A36: Golfzon service and software | B36: =(Assumptions!$D$70*Assumptions!$B$63*Assumptions!$B$12+Assumptions!$E$70*Assumptions!$B$64*Assumptions!$B$12+Assumptions!$F$70*Assumptions!$B$65*Assumptions!$B$12)*Assumptions!$B$51*B25 -> 0 | C36: =(Assumptions!$D$70*Assumptions!$B$63*Assumptions!$B$12+Assumptions!$E$70*Assumptions!$B$64*Assumptions!$B$12+Assumptions!$F$70*Assumptions!$B$65*Assumptions!$B$12)*Assumptions!$B$51*C25 -> 1295000 | D36: =(Assumptions!$D$70*Assumptions!$B$63*Assumptions!$B$12+Assumptions!$E$70*Assumptions!$B$64*Assumptions!$B$12+Assumptions!$F$70*Assumptions!$B$65*Assumptions!$B$12)*Assumptions!$B$51*D25 -> 2590000 | E36: =(Assumptions!$D$70*Assumptions!$B$63*Assumptions!$B$12+Assumptions!$E$70*Assumptions!$B$64*Assumptions!$B$12+Assumptions!$F$70*Assumptions!$B$65*Assumptions!$B$12)*Assumptions!$B$51*E25 -> 2590000 | F36: =(Assumptions!$D$70*Assumptions!$B$63*Assumptions!$B$12+Assumptions!$E$70*Assumptions!$B$64*Assumptions!$B$12+Assumptions!$F$70*Assumptions!$B$65*Assumptions!$B$12)*Assumptions!$B$51*F25 -> 2590000 | G36: =(Assumptions!$D$70*Assumptions!$B$63*Assumptions!$B$12+Assumptions!$E$70*Assumptions!$B$64*Assumptions!$B$12+Assumptions!$F$70*Assumptions!$B$65*Assumptions!$B$12)*Assumptions!$B$51*G25 -> 2590000
A37: Consumables and maintenance | B37: =B28*Assumptions!$B$52*B25 -> 0 | C37: =C28*Assumptions!$B$52*C25 -> 1200000 | D37: =D28*Assumptions!$B$52*D25 -> 2400000 | E37: =E28*Assumptions!$B$52*E25 -> 2400000 | F37: =F28*Assumptions!$B$52*F25 -> 2400000 | G37: =G28*Assumptions!$B$52*G25 -> 2400000
A38: Asset insurance | B38: =Debt!$J$5*Assumptions!$B$50*B25 -> 0 | C38: =Debt!$J$5*Assumptions!$B$50*C25 -> 420875 | D38: =Debt!$J$5*Assumptions!$B$50*D25 -> 841750 | E38: =Debt!$J$5*Assumptions!$B$50*E25 -> 841750 | F38: =Debt!$J$5*Assumptions!$B$50*F25 -> 841750 | G38: =Debt!$J$5*Assumptions!$B$50*G25 -> 841750
A40: Phase 3
A41: Bay age, years | B41: =2027-Assumptions!$B$71 -> -2 | C41: =2028-Assumptions!$B$71 -> -1 | D41: =2029-Assumptions!$B$71 -> 0 | E41: =2030-Assumptions!$B$71 -> 1 | F41: =2031-Assumptions!$B$71 -> 2 | G41: =2032-Assumptions!$B$71 -> 3
A42: Share of year live | B42: =IF(B41<0,0,IF(B41=0,Assumptions!$C$71,1)) -> 0 | C42: =IF(C41<0,0,IF(C41=0,Assumptions!$C$71,1)) -> 0 | D42: =IF(D41<0,0,IF(D41=0,Assumptions!$C$71,1)) -> 0.6 | E42: =IF(E41<0,0,IF(E41=0,Assumptions!$C$71,1)) -> 1 | F42: =IF(F41<0,0,IF(F41=0,Assumptions!$C$71,1)) -> 1 | G42: =IF(G41<0,0,IF(G41=0,Assumptions!$C$71,1)) -> 1
A43: Use factor (live × ramp) | B43: =B42*IF(B41=0,Assumptions!$B$56,IF(B41=1,Assumptions!$B$57,1)) -> 0 | C43: =C42*IF(C41=0,Assumptions!$B$56,IF(C41=1,Assumptions!$B$57,1)) -> 0 | D43: =D42*IF(D41=0,Assumptions!$B$56,IF(D41=1,Assumptions!$B$57,1)) -> 0.33 | E43: =E42*IF(E41=0,Assumptions!$B$56,IF(E41=1,Assumptions!$B$57,1)) -> 0.8 | F43: =F42*IF(F41=0,Assumptions!$B$56,IF(F41=1,Assumptions!$B$57,1)) -> 1 | G43: =G42*IF(G41=0,Assumptions!$B$56,IF(G41=1,Assumptions!$B$57,1)) -> 1
A44: Capex in year | B44: =IF(B41=0,Debt!$P$5,0) -> 0 | C44: =IF(C41=0,Debt!$P$5,0) -> 0 | D44: =IF(D41=0,Debt!$P$5,0) -> 37999000 | E44: =IF(E41=0,Debt!$P$5,0) -> 0 | F44: =IF(F41=0,Debt!$P$5,0) -> 0 | G44: =IF(G41=0,Debt!$P$5,0) -> 0
A45: Bays live | B45: =IF(B41>=0,SUM(Assumptions!$D$71:$F$71),0) -> 0 | C45: =IF(C41>=0,SUM(Assumptions!$D$71:$F$71),0) -> 0 | D45: =IF(D41>=0,SUM(Assumptions!$D$71:$F$71),0) -> 60 | E45: =IF(E41>=0,SUM(Assumptions!$D$71:$F$71),0) -> 60 | F45: =IF(F41>=0,SUM(Assumptions!$D$71:$F$71),0) -> 60 | G45: =IF(G41>=0,SUM(Assumptions!$D$71:$F$71),0) -> 60
A46: Clubs live | B46: =IF(B41>=0,Assumptions!$G$71,0) -> 0 | C46: =IF(C41>=0,Assumptions!$G$71,0) -> 0 | D46: =IF(D41>=0,Assumptions!$G$71,0) -> 60 | E46: =IF(E41>=0,Assumptions!$G$71,0) -> 60 | F46: =IF(F41>=0,Assumptions!$G$71,0) -> 60 | G46: =IF(G41>=0,Assumptions!$G$71,0) -> 60
A47: Booked hours | B47: =(Assumptions!$D$71*MIN(Assumptions!$C$63*$B$2,Assumptions!$B$28)+Assumptions!$E$71*MIN(Assumptions!$C$64*$B$2,Assumptions!$B$28)+Assumptions!$F$71*MIN(Assumptions!$C$65*$B$2,Assumptions!$B$28))*Assumptions!$B$27*B43 -> 0 | C47: =(Assumptions!$D$71*MIN(Assumptions!$C$63*$B$2,Assumptions!$B$28)+Assumptions!$E$71*MIN(Assumptions!$C$64*$B$2,Assumptions!$B$28)+Assumptions!$F$71*MIN(Assumptions!$C$65*$B$2,Assumptions!$B$28))*Assumptions!$B$27*C43 -> 0 | D47: =(Assumptions!$D$71*MIN(Assumptions!$C$63*$B$2,Assumptions!$B$28)+Assumptions!$E$71*MIN(Assumptions!$C$64*$B$2,Assumptions!$B$28)+Assumptions!$F$71*MIN(Assumptions!$C$65*$B$2,Assumptions!$B$28))*Assumptions!$B$27*D43 -> 23201.64 | E47: =(Assumptions!$D$71*MIN(Assumptions!$C$63*$B$2,Assumptions!$B$28)+Assumptions!$E$71*MIN(Assumptions!$C$64*$B$2,Assumptions!$B$28)+Assumptions!$F$71*MIN(Assumptions!$C$65*$B$2,Assumptions!$B$28))*Assumptions!$B$27*E43 -> 56246.4 | F47: =(Assumptions!$D$71*MIN(Assumptions!$C$63*$B$2,Assumptions!$B$28)+Assumptions!$E$71*MIN(Assumptions!$C$64*$B$2,Assumptions!$B$28)+Assumptions!$F$71*MIN(Assumptions!$C$65*$B$2,Assumptions!$B$28))*Assumptions!$B$27*F43 -> 70308 | G47: =(Assumptions!$D$71*MIN(Assumptions!$C$63*$B$2,Assumptions!$B$28)+Assumptions!$E$71*MIN(Assumptions!$C$64*$B$2,Assumptions!$B$28)+Assumptions!$F$71*MIN(Assumptions!$C$65*$B$2,Assumptions!$B$28))*Assumptions!$B$27*G43 -> 70308
A48: Bay hire | B48: =(Assumptions!$D$71*MIN(Assumptions!$C$63*$B$2,Assumptions!$B$28)*Assumptions!$D$63+Assumptions!$E$71*MIN(Assumptions!$C$64*$B$2,Assumptions!$B$28)*Assumptions!$D$64+Assumptions!$F$71*MIN(Assumptions!$C$65*$B$2,Assumptions!$B$28)*Assumptions!$D$65)*Assumptions!$B$27*B43 -> 0 | C48: =(Assumptions!$D$71*MIN(Assumptions!$C$63*$B$2,Assumptions!$B$28)*Assumptions!$D$63+Assumptions!$E$71*MIN(Assumptions!$C$64*$B$2,Assumptions!$B$28)*Assumptions!$D$64+Assumptions!$F$71*MIN(Assumptions!$C$65*$B$2,Assumptions!$B$28)*Assumptions!$D$65)*Assumptions!$B$27*C43 -> 0 | D48: =(Assumptions!$D$71*MIN(Assumptions!$C$63*$B$2,Assumptions!$B$28)*Assumptions!$D$63+Assumptions!$E$71*MIN(Assumptions!$C$64*$B$2,Assumptions!$B$28)*Assumptions!$D$64+Assumptions!$F$71*MIN(Assumptions!$C$65*$B$2,Assumptions!$B$28)*Assumptions!$D$65)*Assumptions!$B$27*D43 -> 6556334.4 | E48: =(Assumptions!$D$71*MIN(Assumptions!$C$63*$B$2,Assumptions!$B$28)*Assumptions!$D$63+Assumptions!$E$71*MIN(Assumptions!$C$64*$B$2,Assumptions!$B$28)*Assumptions!$D$64+Assumptions!$F$71*MIN(Assumptions!$C$65*$B$2,Assumptions!$B$28)*Assumptions!$D$65)*Assumptions!$B$27*E43 -> 15894144 | F48: =(Assumptions!$D$71*MIN(Assumptions!$C$63*$B$2,Assumptions!$B$28)*Assumptions!$D$63+Assumptions!$E$71*MIN(Assumptions!$C$64*$B$2,Assumptions!$B$28)*Assumptions!$D$64+Assumptions!$F$71*MIN(Assumptions!$C$65*$B$2,Assumptions!$B$28)*Assumptions!$D$65)*Assumptions!$B$27*F43 -> 19867680 | G48: =(Assumptions!$D$71*MIN(Assumptions!$C$63*$B$2,Assumptions!$B$28)*Assumptions!$D$63+Assumptions!$E$71*MIN(Assumptions!$C$64*$B$2,Assumptions!$B$28)*Assumptions!$D$64+Assumptions!$F$71*MIN(Assumptions!$C$65*$B$2,Assumptions!$B$28)*Assumptions!$D$65)*Assumptions!$B$27*G43 -> 19867680
A49: Golf add-on | B49: =Assumptions!$G$71*Assumptions!$B$33*Assumptions!$B$35*$B$2*IF(B41=0,Assumptions!$B$36,IF(B41=1,Assumptions!$B$37,1))*Assumptions!$B$34*12*B42 -> 0 | C49: =Assumptions!$G$71*Assumptions!$B$33*Assumptions!$B$35*$B$2*IF(C41=0,Assumptions!$B$36,IF(C41=1,Assumptions!$B$37,1))*Assumptions!$B$34*12*C42 -> 0 | D49: =Assumptions!$G$71*Assumptions!$B$33*Assumptions!$B$35*$B$2*IF(D41=0,Assumptions!$B$36,IF(D41=1,Assumptions!$B$37,1))*Assumptions!$B$34*12*D42 -> 2485154.3 | E49: =Assumptions!$G$71*Assumptions!$B$33*Assumptions!$B$35*$B$2*IF(E41=0,Assumptions!$B$36,IF(E41=1,Assumptions!$B$37,1))*Assumptions!$B$34*12*E42 -> 7766107.3 | F49: =Assumptions!$G$71*Assumptions!$B$33*Assumptions!$B$35*$B$2*IF(F41=0,Assumptions!$B$36,IF(F41=1,Assumptions!$B$37,1))*Assumptions!$B$34*12*F42 -> 10354810 | G49: =Assumptions!$G$71*Assumptions!$B$33*Assumptions!$B$35*$B$2*IF(G41=0,Assumptions!$B$36,IF(G41=1,Assumptions!$B$37,1))*Assumptions!$B$34*12*G42 -> 10354810
A50: Leagues, events, corporate | B50: =B45*Assumptions!$B$40*B43 -> 0 | C50: =C45*Assumptions!$B$40*C43 -> 0 | D50: =D45*Assumptions!$B$40*D43 -> 792000 | E50: =E45*Assumptions!$B$40*E43 -> 1920000 | F50: =F45*Assumptions!$B$40*F43 -> 2400000 | G50: =G45*Assumptions!$B$40*G43 -> 2400000
A51: Insured shot, net of premium | B51: =B47*Assumptions!$B$45 -> 0 | C51: =C47*Assumptions!$B$45 -> 0 | D51: =D47*Assumptions!$B$45 -> 551038.95 | E51: =E47*Assumptions!$B$45 -> 1335852 | F51: =F47*Assumptions!$B$45 -> 1669815 | G51: =G47*Assumptions!$B$45 -> 1669815
A52: Naming partner | B52: =B45*Assumptions!$B$41*B42 -> 0 | C52: =C45*Assumptions!$B$41*C42 -> 0 | D52: =D45*Assumptions!$B$41*D42 -> 900000 | E52: =E45*Assumptions!$B$41*E42 -> 1500000 | F52: =F45*Assumptions!$B$41*F42 -> 1500000 | G52: =G45*Assumptions!$B$41*G42 -> 1500000
A53: Golfzon service and software | B53: =(Assumptions!$D$71*Assumptions!$B$63*Assumptions!$B$12+Assumptions!$E$71*Assumptions!$B$64*Assumptions!$B$12+Assumptions!$F$71*Assumptions!$B$65*Assumptions!$B$12)*Assumptions!$B$51*B42 -> 0 | C53: =(Assumptions!$D$71*Assumptions!$B$63*Assumptions!$B$12+Assumptions!$E$71*Assumptions!$B$64*Assumptions!$B$12+Assumptions!$F$71*Assumptions!$B$65*Assumptions!$B$12)*Assumptions!$B$51*C42 -> 0 | D53: =(Assumptions!$D$71*Assumptions!$B$63*Assumptions!$B$12+Assumptions!$E$71*Assumptions!$B$64*Assumptions!$B$12+Assumptions!$F$71*Assumptions!$B$65*Assumptions!$B$12)*Assumptions!$B$51*D42 -> 701520 | E53: =(Assumptions!$D$71*Assumptions!$B$63*Assumptions!$B$12+Assumptions!$E$71*Assumptions!$B$64*Assumptions!$B$12+Assumptions!$F$71*Assumptions!$B$65*Assumptions!$B$12)*Assumptions!$B$51*E42 -> 1169200 | F53: =(Assumptions!$D$71*Assumptions!$B$63*Assumptions!$B$12+Assumptions!$E$71*Assumptions!$B$64*Assumptions!$B$12+Assumptions!$F$71*Assumptions!$B$65*Assumptions!$B$12)*Assumptions!$B$51*F42 -> 1169200 | G53: =(Assumptions!$D$71*Assumptions!$B$63*Assumptions!$B$12+Assumptions!$E$71*Assumptions!$B$64*Assumptions!$B$12+Assumptions!$F$71*Assumptions!$B$65*Assumptions!$B$12)*Assumptions!$B$51*G42 -> 1169200
A54: Consumables and maintenance | B54: =B45*Assumptions!$B$52*B42 -> 0 | C54: =C45*Assumptions!$B$52*C42 -> 0 | D54: =D45*Assumptions!$B$52*D42 -> 864000 | E54: =E45*Assumptions!$B$52*E42 -> 1440000 | F54: =F45*Assumptions!$B$52*F42 -> 1440000 | G54: =G45*Assumptions!$B$52*G42 -> 1440000
A55: Asset insurance | B55: =Debt!$P$5*Assumptions!$B$50*B42 -> 0 | C55: =Debt!$P$5*Assumptions!$B$50*C42 -> 0 | D55: =Debt!$P$5*Assumptions!$B$50*D42 -> 227994 | E55: =Debt!$P$5*Assumptions!$B$50*E42 -> 379990 | F55: =Debt!$P$5*Assumptions!$B$50*F42 -> 379990 | G55: =Debt!$P$5*Assumptions!$B$50*G42 -> 379990
A57: The chain
A58: Bays live, total | B58: =B11+B28+B45 -> 40 | C58: =C11+C28+C45 -> 140 | D58: =D11+D28+D45 -> 200 | E58: =E11+E28+E45 -> 200 | F58: =F11+F28+F45 -> 200 | G58: =G11+G28+G45 -> 200
A59: Clubs with bays | B59: =B12+B29+B46 -> 20 | C59: =C12+C29+C46 -> 70 | D59: =D12+D29+D46 -> 130 | E59: =E12+E29+E46 -> 130 | F59: =F12+F29+F46 -> 130 | G59: =G12+G29+G46 -> 130
A60: Booked bay-hours | B60: =B13+B30+B47 -> 16632 | C60: =C13+C30+C47 -> 82687.5 | D60: =D13+D30+D47 -> 183473.64 | E60: =E13+E30+E47 -> 241466.4 | F60: =F13+F30+F47 -> 255528 | G60: =G13+G30+G47 -> 255528
A61: Booked hours a bay a day | B61: =IF(B58=0,0,B60/B58/Assumptions!$B$26) -> 1.155 | C61: =IF(C58=0,0,C60/C58/Assumptions!$B$26) -> 1.640625 | D61: =IF(D58=0,0,D60/D58/Assumptions!$B$26) -> 2.548245 | E61: =IF(E58=0,0,E60/E58/Assumptions!$B$26) -> 3.3537 | F61: =IF(F58=0,0,F60/F58/Assumptions!$B$26) -> 3.549 | G61: =IF(G58=0,0,G60/G58/Assumptions!$B$26) -> 3.549
A62: Bay hire | B62: =B14+B31+B48 -> 8648640 | C62: =C14+C31+C48 -> 37508940 | D62: =D14+D31+D48 -> 73931054 | E62: =E14+E31+E48 -> 92250144 | F62: =F14+F31+F48 -> 96223680 | G62: =G14+G31+G48 -> 96223680
A63: Golf add-on memberships | B63: =B15+B32+B49 -> 690320.65 | C63: =C15+C32+C49 -> 4314504 | D63: =D15+D32+D49 -> 12408514 | E63: =E15+E32+E49 -> 19846719 | F63: =F15+F32+F49 -> 22435421 | G63: =G15+G32+G49 -> 22435421
A64: Leagues, events, corporate | B64: =B16+B33+B50 -> 440000 | C64: =C16+C33+C50 -> 2380000 | D64: =D16+D33+D50 -> 5592000 | E64: =E16+E33+E50 -> 7520000 | F64: =F16+F33+F50 -> 8000000 | G64: =G16+G33+G50 -> 8000000
A65: Get Lucky insured shot, net of premium | B65: =B17+B34+B51 -> 395010 | C65: =C17+C34+C51 -> 1963828.1 | D65: =D17+D34+D51 -> 4357499 | E65: =E17+E34+E51 -> 5734827 | F65: =F17+F34+F51 -> 6068790 | G65: =G17+G34+G51 -> 6068790
A66: Naming partner | B66: =B18+B35+B52 -> 500000 | C66: =C18+C35+C52 -> 2250000 | D66: =D18+D35+D52 -> 4400000 | E66: =E18+E35+E52 -> 5000000 | F66: =F18+F35+F52 -> 5000000 | G66: =G18+G35+G52 -> 5000000
A67: Revenue shared with Virgin Active | B67: =B62+B63+B64+B65 -> 10173971 | C67: =C62+C63+C64+C65 -> 46167272 | D67: =D62+D63+D64+D65 -> 96289067 | E67: =E62+E63+E64+E65 -> 1.2535169e+08 | F67: =F62+F63+F64+F65 -> 1.3272789e+08 | G67: =G62+G63+G64+G65 -> 1.3272789e+08
A68: Revenue | B68: =B67+B66 -> 10673971 | C68: =C67+C66 -> 48417272 | D68: =D67+D66 -> 1.0068907e+08 | E68: =E67+E66 -> 1.3035169e+08 | F68: =F67+F66 -> 1.3772789e+08 | G68: =G67+G66 -> 1.3772789e+08
A69: Virgin Active concession | B69: =-B67*Assumptions!$B$24 -> -2034794.1 | C69: =-C67*Assumptions!$B$24 -> -9233454.4 | D69: =-D67*Assumptions!$B$24 -> -19257813 | E69: =-E67*Assumptions!$B$24 -> -25070338 | F69: =-F67*Assumptions!$B$24 -> -26545578 | G69: =-G67*Assumptions!$B$24 -> -26545578
A70: Card and booking fees | B70: =-B67*Assumptions!$B$48 -> -254349.27 | C70: =-C67*Assumptions!$B$48 -> -1154181.8 | D70: =-D67*Assumptions!$B$48 -> -2407226.7 | E70: =-E67*Assumptions!$B$48 -> -3133792.2 | F70: =-F67*Assumptions!$B$48 -> -3318197.3 | G70: =-G67*Assumptions!$B$48 -> -3318197.3
A71: Marketing | B71: =-B68*Assumptions!$B$49 -> -533698.53 | C71: =-C68*Assumptions!$B$49 -> -2420863.6 | D71: =-D68*Assumptions!$B$49 -> -5034453.3 | E71: =-E68*Assumptions!$B$49 -> -6517584.5 | F71: =-F68*Assumptions!$B$49 -> -6886394.6 | G71: =-G68*Assumptions!$B$49 -> -6886394.6
A72: Golfzon service and software | B72: =-(B19+B36+B53) -> -888000 | C72: =-(C19+C36+C53) -> -3071000 | D72: =-(D19+D36+D53) -> -5067520 | E72: =-(E19+E36+E53) -> -5535200 | F72: =-(F19+F36+F53) -> -5535200 | G72: =-(G19+G36+G53) -> -5535200
A73: Consumables and maintenance | B73: =-(B20+B37+B54) -> -480000 | C73: =-(C20+C37+C54) -> -2160000 | D73: =-(D20+D37+D54) -> -4224000 | E73: =-(E20+E37+E54) -> -4800000 | F73: =-(F20+F37+F54) -> -4800000 | G73: =-(G20+G37+G54) -> -4800000
A74: Asset insurance | B74: =-(B21+B38+B55) -> -288600 | C74: =-(C21+C38+C55) -> -998075 | D74: =-(D21+D38+D55) -> -1646944 | E74: =-(E21+E38+E55) -> -1798940 | F74: =-(F21+F38+F55) -> -1798940 | G74: =-(G21+G38+G55) -> -1798940
A75: People | B75: =-Assumptions!B75 -> -4000000 | C75: =-Assumptions!C75 -> -8000000 | D75: =-Assumptions!D75 -> -11000000 | E75: =-Assumptions!E75 -> -12000000 | F75: =-Assumptions!F75 -> -12000000 | G75: =-Assumptions!G75 -> -12000000
A76: Central overhead | B76: =-Assumptions!B76 -> -2000000 | C76: =-Assumptions!C76 -> -3000000 | D76: =-Assumptions!D76 -> -4000000 | E76: =-Assumptions!E76 -> -4000000 | F76: =-Assumptions!F76 -> -4000000 | G76: =-Assumptions!G76 -> -4000000
A77: EBITDA | B77: =SUM(B68:B76) -> 194528.72 | C77: =SUM(C68:C76) -> 18379697 | D77: =SUM(D68:D76) -> 48051110 | E77: =SUM(E68:E76) -> 67495835 | F77: =SUM(F68:F76) -> 72843581 | G77: =SUM(G68:G76) -> 72843581
A78: EBITDA margin | B78: =IF(B68=0,0,B77/B68) -> 0.018224588 | C78: =IF(C68=0,0,C77/C68) -> 0.37961034 | D78: =IF(D68=0,0,D77/D68) -> 0.47722271 | E78: =IF(E68=0,0,E77/E68) -> 0.51779793 | F78: =IF(F68=0,0,F77/F68) -> 0.52889491 | G78: =IF(G68=0,0,G77/G68) -> 0.52889491
A79: RMB interest | B79: =-Debt!B93 -> -6233760 | C79: =-Debt!C93 -> -14890537 | D79: =-Debt!D93 -> -17338234 | E79: =-Debt!E93 -> -14407561 | F79: =-Debt!F93 -> -10753709 | G79: =-Debt!G93 -> -6636457.6
A80: RMB capital | B80: =-Debt!B94 -> 0 | C80: =-Debt!C94 -> -8067017.6 | D80: =-Debt!D94 -> -20854518 | E80: =-Debt!E94 -> -28810180 | F80: =-Debt!F94 -> -32464031 | G80: =-Debt!G94 -> -36581283
A81: Debt service | B81: =B79+B80 -> -6233760 | C81: =C79+C80 -> -22957555 | D81: =D79+D80 -> -38192752 | E81: =E79+E80 -> -43217741 | F81: =F79+F80 -> -43217741 | G81: =G79+G80 -> -43217741
A82: Debt cover (EBITDA ÷ debt service) | B82: =IF(B81=0,0,B77/-B81) -> 0.03120568 | C82: =IF(C81=0,0,C77/-C81) -> 0.80059473 | D82: =IF(D81=0,0,D77/-D81) -> 1.2581212 | E82: =IF(E81=0,0,E77/-E81) -> 1.5617622 | F82: =IF(F81=0,0,F77/-F81) -> 1.6855018 | G82: =IF(G81=0,0,G77/-G81) -> 1.6855018
A83: Cash after debt | B83: =B77+B81 -> -6039231.3 | C83: =C77+C81 -> -4577857.5 | D83: =D77+D81 -> 9858357.8 | E83: =E77+E81 -> 24278094 | F83: =F77+F81 -> 29625840 | G83: =G77+G81 -> 29625840
A84: Capex in year | B84: =B10+B27+B44 -> 57720000 | C84: =C10+C27+C44 -> 84175000 | D84: =D10+D27+D44 -> 37999000 | E84: =E10+E27+E44 -> 0 | F84: =F10+F27+F44 -> 0 | G84: =G10+G27+G44 -> 0
A85: Equity deposit (capex not financed by RMB) | B85: =-B84*(1-Assumptions!$B$18) -> -5772000 | C85: =-C84*(1-Assumptions!$B$18) -> -8417500 | D85: =-D84*(1-Assumptions!$B$18) -> -3799900 | E85: =-E84*(1-Assumptions!$B$18) -> 0 | F85: =-F84*(1-Assumptions!$B$18) -> 0 | G85: =-G84*(1-Assumptions!$B$18) -> 0
A86: Cumulative cash after deposits | B86: =B83+B85 -> -11811231 | C86: =C83+C85+B86 -> -24806589 | D86: =D83+D85+C86 -> -18748131 | E86: =E83+E85+D86 -> 5529963.1 | F86: =F83+F85+E86 -> 35155803 | G86: =G83+G85+F86 -> 64781643
A87: Memo: to Virgin Active | B87: =-B69 -> 2034794.1 | C87: =-C69 -> 9233454.4 | D87: =-D69 -> 19257813 | E87: =-E69 -> 25070338 | F87: =-F69 -> 26545578 | G87: =-G69 -> 26545578
A89: Equity needed (lowest point of cumulative cash) | B89: =-MIN(B86:G86) -> 24806589

Sheet Chain high
A1: The chain, 2027 to 2032 — high case (fixed at the high multiplier)
A2: Utilisation multiplier | B2: =Assumptions!$B$9 -> 1.25
A4: Year | B4: 2027 | C4: 2028 | D4: 2029 | E4: 2030 | F4: 2031 | G4: 2032
A6: Phase 1
A7: Bay age, years | B7: =2027-Assumptions!$B$69 -> 0 | C7: =2028-Assumptions!$B$69 -> 1 | D7: =2029-Assumptions!$B$69 -> 2 | E7: =2030-Assumptions!$B$69 -> 3 | F7: =2031-Assumptions!$B$69 -> 4 | G7: =2032-Assumptions!$B$69 -> 5
A8: Share of year live | B8: =IF(B7<0,0,IF(B7=0,Assumptions!$C$69,1)) -> 0.5 | C8: =IF(C7<0,0,IF(C7=0,Assumptions!$C$69,1)) -> 1 | D8: =IF(D7<0,0,IF(D7=0,Assumptions!$C$69,1)) -> 1 | E8: =IF(E7<0,0,IF(E7=0,Assumptions!$C$69,1)) -> 1 | F8: =IF(F7<0,0,IF(F7=0,Assumptions!$C$69,1)) -> 1 | G8: =IF(G7<0,0,IF(G7=0,Assumptions!$C$69,1)) -> 1
A9: Use factor (live × ramp) | B9: =B8*IF(B7=0,Assumptions!$B$56,IF(B7=1,Assumptions!$B$57,1)) -> 0.275 | C9: =C8*IF(C7=0,Assumptions!$B$56,IF(C7=1,Assumptions!$B$57,1)) -> 0.8 | D9: =D8*IF(D7=0,Assumptions!$B$56,IF(D7=1,Assumptions!$B$57,1)) -> 1 | E9: =E8*IF(E7=0,Assumptions!$B$56,IF(E7=1,Assumptions!$B$57,1)) -> 1 | F9: =F8*IF(F7=0,Assumptions!$B$56,IF(F7=1,Assumptions!$B$57,1)) -> 1 | G9: =G8*IF(G7=0,Assumptions!$B$56,IF(G7=1,Assumptions!$B$57,1)) -> 1
A10: Capex in year | B10: =IF(B7=0,Debt!$D$5,0) -> 57720000 | C10: =IF(C7=0,Debt!$D$5,0) -> 0 | D10: =IF(D7=0,Debt!$D$5,0) -> 0 | E10: =IF(E7=0,Debt!$D$5,0) -> 0 | F10: =IF(F7=0,Debt!$D$5,0) -> 0 | G10: =IF(G7=0,Debt!$D$5,0) -> 0
A11: Bays live | B11: =IF(B7>=0,SUM(Assumptions!$D$69:$F$69),0) -> 40 | C11: =IF(C7>=0,SUM(Assumptions!$D$69:$F$69),0) -> 40 | D11: =IF(D7>=0,SUM(Assumptions!$D$69:$F$69),0) -> 40 | E11: =IF(E7>=0,SUM(Assumptions!$D$69:$F$69),0) -> 40 | F11: =IF(F7>=0,SUM(Assumptions!$D$69:$F$69),0) -> 40 | G11: =IF(G7>=0,SUM(Assumptions!$D$69:$F$69),0) -> 40
A12: Clubs live | B12: =IF(B7>=0,Assumptions!$G$69,0) -> 20 | C12: =IF(C7>=0,Assumptions!$G$69,0) -> 20 | D12: =IF(D7>=0,Assumptions!$G$69,0) -> 20 | E12: =IF(E7>=0,Assumptions!$G$69,0) -> 20 | F12: =IF(F7>=0,Assumptions!$G$69,0) -> 20 | G12: =IF(G7>=0,Assumptions!$G$69,0) -> 20
A13: Booked hours | B13: =(Assumptions!$D$69*MIN(Assumptions!$C$63*$B$2,Assumptions!$B$28)+Assumptions!$E$69*MIN(Assumptions!$C$64*$B$2,Assumptions!$B$28)+Assumptions!$F$69*MIN(Assumptions!$C$65*$B$2,Assumptions!$B$28))*Assumptions!$B$27*B9 -> 29700 | C13: =(Assumptions!$D$69*MIN(Assumptions!$C$63*$B$2,Assumptions!$B$28)+Assumptions!$E$69*MIN(Assumptions!$C$64*$B$2,Assumptions!$B$28)+Assumptions!$F$69*MIN(Assumptions!$C$65*$B$2,Assumptions!$B$28))*Assumptions!$B$27*C9 -> 86400 | D13: =(Assumptions!$D$69*MIN(Assumptions!$C$63*$B$2,Assumptions!$B$28)+Assumptions!$E$69*MIN(Assumptions!$C$64*$B$2,Assumptions!$B$28)+Assumptions!$F$69*MIN(Assumptions!$C$65*$B$2,Assumptions!$B$28))*Assumptions!$B$27*D9 -> 108000 | E13: =(Assumptions!$D$69*MIN(Assumptions!$C$63*$B$2,Assumptions!$B$28)+Assumptions!$E$69*MIN(Assumptions!$C$64*$B$2,Assumptions!$B$28)+Assumptions!$F$69*MIN(Assumptions!$C$65*$B$2,Assumptions!$B$28))*Assumptions!$B$27*E9 -> 108000 | F13: =(Assumptions!$D$69*MIN(Assumptions!$C$63*$B$2,Assumptions!$B$28)+Assumptions!$E$69*MIN(Assumptions!$C$64*$B$2,Assumptions!$B$28)+Assumptions!$F$69*MIN(Assumptions!$C$65*$B$2,Assumptions!$B$28))*Assumptions!$B$27*F9 -> 108000 | G13: =(Assumptions!$D$69*MIN(Assumptions!$C$63*$B$2,Assumptions!$B$28)+Assumptions!$E$69*MIN(Assumptions!$C$64*$B$2,Assumptions!$B$28)+Assumptions!$F$69*MIN(Assumptions!$C$65*$B$2,Assumptions!$B$28))*Assumptions!$B$27*G9 -> 108000
A14: Bay hire | B14: =(Assumptions!$D$69*MIN(Assumptions!$C$63*$B$2,Assumptions!$B$28)*Assumptions!$D$63+Assumptions!$E$69*MIN(Assumptions!$C$64*$B$2,Assumptions!$B$28)*Assumptions!$D$64+Assumptions!$F$69*MIN(Assumptions!$C$65*$B$2,Assumptions!$B$28)*Assumptions!$D$65)*Assumptions!$B$27*B9 -> 15444000 | C14: =(Assumptions!$D$69*MIN(Assumptions!$C$63*$B$2,Assumptions!$B$28)*Assumptions!$D$63+Assumptions!$E$69*MIN(Assumptions!$C$64*$B$2,Assumptions!$B$28)*Assumptions!$D$64+Assumptions!$F$69*MIN(Assumptions!$C$65*$B$2,Assumptions!$B$28)*Assumptions!$D$65)*Assumptions!$B$27*C9 -> 44928000 | D14: =(Assumptions!$D$69*MIN(Assumptions!$C$63*$B$2,Assumptions!$B$28)*Assumptions!$D$63+Assumptions!$E$69*MIN(Assumptions!$C$64*$B$2,Assumptions!$B$28)*Assumptions!$D$64+Assumptions!$F$69*MIN(Assumptions!$C$65*$B$2,Assumptions!$B$28)*Assumptions!$D$65)*Assumptions!$B$27*D9 -> 56160000 | E14: =(Assumptions!$D$69*MIN(Assumptions!$C$63*$B$2,Assumptions!$B$28)*Assumptions!$D$63+Assumptions!$E$69*MIN(Assumptions!$C$64*$B$2,Assumptions!$B$28)*Assumptions!$D$64+Assumptions!$F$69*MIN(Assumptions!$C$65*$B$2,Assumptions!$B$28)*Assumptions!$D$65)*Assumptions!$B$27*E9 -> 56160000 | F14: =(Assumptions!$D$69*MIN(Assumptions!$C$63*$B$2,Assumptions!$B$28)*Assumptions!$D$63+Assumptions!$E$69*MIN(Assumptions!$C$64*$B$2,Assumptions!$B$28)*Assumptions!$D$64+Assumptions!$F$69*MIN(Assumptions!$C$65*$B$2,Assumptions!$B$28)*Assumptions!$D$65)*Assumptions!$B$27*F9 -> 56160000 | G14: =(Assumptions!$D$69*MIN(Assumptions!$C$63*$B$2,Assumptions!$B$28)*Assumptions!$D$63+Assumptions!$E$69*MIN(Assumptions!$C$64*$B$2,Assumptions!$B$28)*Assumptions!$D$64+Assumptions!$F$69*MIN(Assumptions!$C$65*$B$2,Assumptions!$B$28)*Assumptions!$D$65)*Assumptions!$B$27*G9 -> 56160000
A15: Golf add-on | B15: =Assumptions!$G$69*Assumptions!$B$33*Assumptions!$B$35*$B$2*IF(B7=0,Assumptions!$B$36,IF(B7=1,Assumptions!$B$37,1))*Assumptions!$B$34*12*B8 -> 1232715.4 | C15: =Assumptions!$G$69*Assumptions!$B$33*Assumptions!$B$35*$B$2*IF(C7=0,Assumptions!$B$36,IF(C7=1,Assumptions!$B$37,1))*Assumptions!$B$34*12*C8 -> 4622682.9 | D15: =Assumptions!$G$69*Assumptions!$B$33*Assumptions!$B$35*$B$2*IF(D7=0,Assumptions!$B$36,IF(D7=1,Assumptions!$B$37,1))*Assumptions!$B$34*12*D8 -> 6163577.2 | E15: =Assumptions!$G$69*Assumptions!$B$33*Assumptions!$B$35*$B$2*IF(E7=0,Assumptions!$B$36,IF(E7=1,Assumptions!$B$37,1))*Assumptions!$B$34*12*E8 -> 6163577.2 | F15: =Assumptions!$G$69*Assumptions!$B$33*Assumptions!$B$35*$B$2*IF(F7=0,Assumptions!$B$36,IF(F7=1,Assumptions!$B$37,1))*Assumptions!$B$34*12*F8 -> 6163577.2 | G15: =Assumptions!$G$69*Assumptions!$B$33*Assumptions!$B$35*$B$2*IF(G7=0,Assumptions!$B$36,IF(G7=1,Assumptions!$B$37,1))*Assumptions!$B$34*12*G8 -> 6163577.2
A16: Leagues, events, corporate | B16: =B11*Assumptions!$B$40*B9 -> 440000 | C16: =C11*Assumptions!$B$40*C9 -> 1280000 | D16: =D11*Assumptions!$B$40*D9 -> 1600000 | E16: =E11*Assumptions!$B$40*E9 -> 1600000 | F16: =F11*Assumptions!$B$40*F9 -> 1600000 | G16: =G11*Assumptions!$B$40*G9 -> 1600000
A17: Insured shot, net of premium | B17: =B13*Assumptions!$B$45 -> 705375 | C17: =C13*Assumptions!$B$45 -> 2052000 | D17: =D13*Assumptions!$B$45 -> 2565000 | E17: =E13*Assumptions!$B$45 -> 2565000 | F17: =F13*Assumptions!$B$45 -> 2565000 | G17: =G13*Assumptions!$B$45 -> 2565000
A18: Naming partner | B18: =B11*Assumptions!$B$41*B8 -> 500000 | C18: =C11*Assumptions!$B$41*C8 -> 1000000 | D18: =D11*Assumptions!$B$41*D8 -> 1000000 | E18: =E11*Assumptions!$B$41*E8 -> 1000000 | F18: =F11*Assumptions!$B$41*F8 -> 1000000 | G18: =G11*Assumptions!$B$41*G8 -> 1000000
A19: Golfzon service and software | B19: =(Assumptions!$D$69*Assumptions!$B$63*Assumptions!$B$12+Assumptions!$E$69*Assumptions!$B$64*Assumptions!$B$12+Assumptions!$F$69*Assumptions!$B$65*Assumptions!$B$12)*Assumptions!$B$51*B8 -> 888000 | C19: =(Assumptions!$D$69*Assumptions!$B$63*Assumptions!$B$12+Assumptions!$E$69*Assumptions!$B$64*Assumptions!$B$12+Assumptions!$F$69*Assumptions!$B$65*Assumptions!$B$12)*Assumptions!$B$51*C8 -> 1776000 | D19: =(Assumptions!$D$69*Assumptions!$B$63*Assumptions!$B$12+Assumptions!$E$69*Assumptions!$B$64*Assumptions!$B$12+Assumptions!$F$69*Assumptions!$B$65*Assumptions!$B$12)*Assumptions!$B$51*D8 -> 1776000 | E19: =(Assumptions!$D$69*Assumptions!$B$63*Assumptions!$B$12+Assumptions!$E$69*Assumptions!$B$64*Assumptions!$B$12+Assumptions!$F$69*Assumptions!$B$65*Assumptions!$B$12)*Assumptions!$B$51*E8 -> 1776000 | F19: =(Assumptions!$D$69*Assumptions!$B$63*Assumptions!$B$12+Assumptions!$E$69*Assumptions!$B$64*Assumptions!$B$12+Assumptions!$F$69*Assumptions!$B$65*Assumptions!$B$12)*Assumptions!$B$51*F8 -> 1776000 | G19: =(Assumptions!$D$69*Assumptions!$B$63*Assumptions!$B$12+Assumptions!$E$69*Assumptions!$B$64*Assumptions!$B$12+Assumptions!$F$69*Assumptions!$B$65*Assumptions!$B$12)*Assumptions!$B$51*G8 -> 1776000
A20: Consumables and maintenance | B20: =B11*Assumptions!$B$52*B8 -> 480000 | C20: =C11*Assumptions!$B$52*C8 -> 960000 | D20: =D11*Assumptions!$B$52*D8 -> 960000 | E20: =E11*Assumptions!$B$52*E8 -> 960000 | F20: =F11*Assumptions!$B$52*F8 -> 960000 | G20: =G11*Assumptions!$B$52*G8 -> 960000
A21: Asset insurance | B21: =Debt!$D$5*Assumptions!$B$50*B8 -> 288600 | C21: =Debt!$D$5*Assumptions!$B$50*C8 -> 577200 | D21: =Debt!$D$5*Assumptions!$B$50*D8 -> 577200 | E21: =Debt!$D$5*Assumptions!$B$50*E8 -> 577200 | F21: =Debt!$D$5*Assumptions!$B$50*F8 -> 577200 | G21: =Debt!$D$5*Assumptions!$B$50*G8 -> 577200
A23: Phase 2
A24: Bay age, years | B24: =2027-Assumptions!$B$70 -> -1 | C24: =2028-Assumptions!$B$70 -> 0 | D24: =2029-Assumptions!$B$70 -> 1 | E24: =2030-Assumptions!$B$70 -> 2 | F24: =2031-Assumptions!$B$70 -> 3 | G24: =2032-Assumptions!$B$70 -> 4
A25: Share of year live | B25: =IF(B24<0,0,IF(B24=0,Assumptions!$C$70,1)) -> 0 | C25: =IF(C24<0,0,IF(C24=0,Assumptions!$C$70,1)) -> 0.5 | D25: =IF(D24<0,0,IF(D24=0,Assumptions!$C$70,1)) -> 1 | E25: =IF(E24<0,0,IF(E24=0,Assumptions!$C$70,1)) -> 1 | F25: =IF(F24<0,0,IF(F24=0,Assumptions!$C$70,1)) -> 1 | G25: =IF(G24<0,0,IF(G24=0,Assumptions!$C$70,1)) -> 1
A26: Use factor (live × ramp) | B26: =B25*IF(B24=0,Assumptions!$B$56,IF(B24=1,Assumptions!$B$57,1)) -> 0 | C26: =C25*IF(C24=0,Assumptions!$B$56,IF(C24=1,Assumptions!$B$57,1)) -> 0.275 | D26: =D25*IF(D24=0,Assumptions!$B$56,IF(D24=1,Assumptions!$B$57,1)) -> 0.8 | E26: =E25*IF(E24=0,Assumptions!$B$56,IF(E24=1,Assumptions!$B$57,1)) -> 1 | F26: =F25*IF(F24=0,Assumptions!$B$56,IF(F24=1,Assumptions!$B$57,1)) -> 1 | G26: =G25*IF(G24=0,Assumptions!$B$56,IF(G24=1,Assumptions!$B$57,1)) -> 1
A27: Capex in year | B27: =IF(B24=0,Debt!$J$5,0) -> 0 | C27: =IF(C24=0,Debt!$J$5,0) -> 84175000 | D27: =IF(D24=0,Debt!$J$5,0) -> 0 | E27: =IF(E24=0,Debt!$J$5,0) -> 0 | F27: =IF(F24=0,Debt!$J$5,0) -> 0 | G27: =IF(G24=0,Debt!$J$5,0) -> 0
A28: Bays live | B28: =IF(B24>=0,SUM(Assumptions!$D$70:$F$70),0) -> 0 | C28: =IF(C24>=0,SUM(Assumptions!$D$70:$F$70),0) -> 100 | D28: =IF(D24>=0,SUM(Assumptions!$D$70:$F$70),0) -> 100 | E28: =IF(E24>=0,SUM(Assumptions!$D$70:$F$70),0) -> 100 | F28: =IF(F24>=0,SUM(Assumptions!$D$70:$F$70),0) -> 100 | G28: =IF(G24>=0,SUM(Assumptions!$D$70:$F$70),0) -> 100
A29: Clubs live | B29: =IF(B24>=0,Assumptions!$G$70,0) -> 0 | C29: =IF(C24>=0,Assumptions!$G$70,0) -> 50 | D29: =IF(D24>=0,Assumptions!$G$70,0) -> 50 | E29: =IF(E24>=0,Assumptions!$G$70,0) -> 50 | F29: =IF(F24>=0,Assumptions!$G$70,0) -> 50 | G29: =IF(G24>=0,Assumptions!$G$70,0) -> 50
A30: Booked hours | B30: =(Assumptions!$D$70*MIN(Assumptions!$C$63*$B$2,Assumptions!$B$28)+Assumptions!$E$70*MIN(Assumptions!$C$64*$B$2,Assumptions!$B$28)+Assumptions!$F$70*MIN(Assumptions!$C$65*$B$2,Assumptions!$B$28))*Assumptions!$B$27*B26 -> 0 | C30: =(Assumptions!$D$70*MIN(Assumptions!$C$63*$B$2,Assumptions!$B$28)+Assumptions!$E$70*MIN(Assumptions!$C$64*$B$2,Assumptions!$B$28)+Assumptions!$F$70*MIN(Assumptions!$C$65*$B$2,Assumptions!$B$28))*Assumptions!$B$27*C26 -> 61256.25 | D30: =(Assumptions!$D$70*MIN(Assumptions!$C$63*$B$2,Assumptions!$B$28)+Assumptions!$E$70*MIN(Assumptions!$C$64*$B$2,Assumptions!$B$28)+Assumptions!$F$70*MIN(Assumptions!$C$65*$B$2,Assumptions!$B$28))*Assumptions!$B$27*D26 -> 178200 | E30: =(Assumptions!$D$70*MIN(Assumptions!$C$63*$B$2,Assumptions!$B$28)+Assumptions!$E$70*MIN(Assumptions!$C$64*$B$2,Assumptions!$B$28)+Assumptions!$F$70*MIN(Assumptions!$C$65*$B$2,Assumptions!$B$28))*Assumptions!$B$27*E26 -> 222750 | F30: =(Assumptions!$D$70*MIN(Assumptions!$C$63*$B$2,Assumptions!$B$28)+Assumptions!$E$70*MIN(Assumptions!$C$64*$B$2,Assumptions!$B$28)+Assumptions!$F$70*MIN(Assumptions!$C$65*$B$2,Assumptions!$B$28))*Assumptions!$B$27*F26 -> 222750 | G30: =(Assumptions!$D$70*MIN(Assumptions!$C$63*$B$2,Assumptions!$B$28)+Assumptions!$E$70*MIN(Assumptions!$C$64*$B$2,Assumptions!$B$28)+Assumptions!$F$70*MIN(Assumptions!$C$65*$B$2,Assumptions!$B$28))*Assumptions!$B$27*G26 -> 222750
A31: Bay hire | B31: =(Assumptions!$D$70*MIN(Assumptions!$C$63*$B$2,Assumptions!$B$28)*Assumptions!$D$63+Assumptions!$E$70*MIN(Assumptions!$C$64*$B$2,Assumptions!$B$28)*Assumptions!$D$64+Assumptions!$F$70*MIN(Assumptions!$C$65*$B$2,Assumptions!$B$28)*Assumptions!$D$65)*Assumptions!$B$27*B26 -> 0 | C31: =(Assumptions!$D$70*MIN(Assumptions!$C$63*$B$2,Assumptions!$B$28)*Assumptions!$D$63+Assumptions!$E$70*MIN(Assumptions!$C$64*$B$2,Assumptions!$B$28)*Assumptions!$D$64+Assumptions!$F$70*MIN(Assumptions!$C$65*$B$2,Assumptions!$B$28)*Assumptions!$D$65)*Assumptions!$B$27*C26 -> 22052250 | D31: =(Assumptions!$D$70*MIN(Assumptions!$C$63*$B$2,Assumptions!$B$28)*Assumptions!$D$63+Assumptions!$E$70*MIN(Assumptions!$C$64*$B$2,Assumptions!$B$28)*Assumptions!$D$64+Assumptions!$F$70*MIN(Assumptions!$C$65*$B$2,Assumptions!$B$28)*Assumptions!$D$65)*Assumptions!$B$27*D26 -> 64152000 | E31: =(Assumptions!$D$70*MIN(Assumptions!$C$63*$B$2,Assumptions!$B$28)*Assumptions!$D$63+Assumptions!$E$70*MIN(Assumptions!$C$64*$B$2,Assumptions!$B$28)*Assumptions!$D$64+Assumptions!$F$70*MIN(Assumptions!$C$65*$B$2,Assumptions!$B$28)*Assumptions!$D$65)*Assumptions!$B$27*E26 -> 80190000 | F31: =(Assumptions!$D$70*MIN(Assumptions!$C$63*$B$2,Assumptions!$B$28)*Assumptions!$D$63+Assumptions!$E$70*MIN(Assumptions!$C$64*$B$2,Assumptions!$B$28)*Assumptions!$D$64+Assumptions!$F$70*MIN(Assumptions!$C$65*$B$2,Assumptions!$B$28)*Assumptions!$D$65)*Assumptions!$B$27*F26 -> 80190000 | G31: =(Assumptions!$D$70*MIN(Assumptions!$C$63*$B$2,Assumptions!$B$28)*Assumptions!$D$63+Assumptions!$E$70*MIN(Assumptions!$C$64*$B$2,Assumptions!$B$28)*Assumptions!$D$64+Assumptions!$F$70*MIN(Assumptions!$C$65*$B$2,Assumptions!$B$28)*Assumptions!$D$65)*Assumptions!$B$27*G26 -> 80190000
A32: Golf add-on | B32: =Assumptions!$G$70*Assumptions!$B$33*Assumptions!$B$35*$B$2*IF(B24=0,Assumptions!$B$36,IF(B24=1,Assumptions!$B$37,1))*Assumptions!$B$34*12*B25 -> 0 | C32: =Assumptions!$G$70*Assumptions!$B$33*Assumptions!$B$35*$B$2*IF(C24=0,Assumptions!$B$36,IF(C24=1,Assumptions!$B$37,1))*Assumptions!$B$34*12*C25 -> 3081788.6 | D32: =Assumptions!$G$70*Assumptions!$B$33*Assumptions!$B$35*$B$2*IF(D24=0,Assumptions!$B$36,IF(D24=1,Assumptions!$B$37,1))*Assumptions!$B$34*12*D25 -> 11556707 | E32: =Assumptions!$G$70*Assumptions!$B$33*Assumptions!$B$35*$B$2*IF(E24=0,Assumptions!$B$36,IF(E24=1,Assumptions!$B$37,1))*Assumptions!$B$34*12*E25 -> 15408943 | F32: =Assumptions!$G$70*Assumptions!$B$33*Assumptions!$B$35*$B$2*IF(F24=0,Assumptions!$B$36,IF(F24=1,Assumptions!$B$37,1))*Assumptions!$B$34*12*F25 -> 15408943 | G32: =Assumptions!$G$70*Assumptions!$B$33*Assumptions!$B$35*$B$2*IF(G24=0,Assumptions!$B$36,IF(G24=1,Assumptions!$B$37,1))*Assumptions!$B$34*12*G25 -> 15408943
A33: Leagues, events, corporate | B33: =B28*Assumptions!$B$40*B26 -> 0 | C33: =C28*Assumptions!$B$40*C26 -> 1100000 | D33: =D28*Assumptions!$B$40*D26 -> 3200000 | E33: =E28*Assumptions!$B$40*E26 -> 4000000 | F33: =F28*Assumptions!$B$40*F26 -> 4000000 | G33: =G28*Assumptions!$B$40*G26 -> 4000000
A34: Insured shot, net of premium | B34: =B30*Assumptions!$B$45 -> 0 | C34: =C30*Assumptions!$B$45 -> 1454835.9 | D34: =D30*Assumptions!$B$45 -> 4232250 | E34: =E30*Assumptions!$B$45 -> 5290312.5 | F34: =F30*Assumptions!$B$45 -> 5290312.5 | G34: =G30*Assumptions!$B$45 -> 5290312.5
A35: Naming partner | B35: =B28*Assumptions!$B$41*B25 -> 0 | C35: =C28*Assumptions!$B$41*C25 -> 1250000 | D35: =D28*Assumptions!$B$41*D25 -> 2500000 | E35: =E28*Assumptions!$B$41*E25 -> 2500000 | F35: =F28*Assumptions!$B$41*F25 -> 2500000 | G35: =G28*Assumptions!$B$41*G25 -> 2500000
A36: Golfzon service and software | B36: =(Assumptions!$D$70*Assumptions!$B$63*Assumptions!$B$12+Assumptions!$E$70*Assumptions!$B$64*Assumptions!$B$12+Assumptions!$F$70*Assumptions!$B$65*Assumptions!$B$12)*Assumptions!$B$51*B25 -> 0 | C36: =(Assumptions!$D$70*Assumptions!$B$63*Assumptions!$B$12+Assumptions!$E$70*Assumptions!$B$64*Assumptions!$B$12+Assumptions!$F$70*Assumptions!$B$65*Assumptions!$B$12)*Assumptions!$B$51*C25 -> 1295000 | D36: =(Assumptions!$D$70*Assumptions!$B$63*Assumptions!$B$12+Assumptions!$E$70*Assumptions!$B$64*Assumptions!$B$12+Assumptions!$F$70*Assumptions!$B$65*Assumptions!$B$12)*Assumptions!$B$51*D25 -> 2590000 | E36: =(Assumptions!$D$70*Assumptions!$B$63*Assumptions!$B$12+Assumptions!$E$70*Assumptions!$B$64*Assumptions!$B$12+Assumptions!$F$70*Assumptions!$B$65*Assumptions!$B$12)*Assumptions!$B$51*E25 -> 2590000 | F36: =(Assumptions!$D$70*Assumptions!$B$63*Assumptions!$B$12+Assumptions!$E$70*Assumptions!$B$64*Assumptions!$B$12+Assumptions!$F$70*Assumptions!$B$65*Assumptions!$B$12)*Assumptions!$B$51*F25 -> 2590000 | G36: =(Assumptions!$D$70*Assumptions!$B$63*Assumptions!$B$12+Assumptions!$E$70*Assumptions!$B$64*Assumptions!$B$12+Assumptions!$F$70*Assumptions!$B$65*Assumptions!$B$12)*Assumptions!$B$51*G25 -> 2590000
A37: Consumables and maintenance | B37: =B28*Assumptions!$B$52*B25 -> 0 | C37: =C28*Assumptions!$B$52*C25 -> 1200000 | D37: =D28*Assumptions!$B$52*D25 -> 2400000 | E37: =E28*Assumptions!$B$52*E25 -> 2400000 | F37: =F28*Assumptions!$B$52*F25 -> 2400000 | G37: =G28*Assumptions!$B$52*G25 -> 2400000
A38: Asset insurance | B38: =Debt!$J$5*Assumptions!$B$50*B25 -> 0 | C38: =Debt!$J$5*Assumptions!$B$50*C25 -> 420875 | D38: =Debt!$J$5*Assumptions!$B$50*D25 -> 841750 | E38: =Debt!$J$5*Assumptions!$B$50*E25 -> 841750 | F38: =Debt!$J$5*Assumptions!$B$50*F25 -> 841750 | G38: =Debt!$J$5*Assumptions!$B$50*G25 -> 841750
A40: Phase 3
A41: Bay age, years | B41: =2027-Assumptions!$B$71 -> -2 | C41: =2028-Assumptions!$B$71 -> -1 | D41: =2029-Assumptions!$B$71 -> 0 | E41: =2030-Assumptions!$B$71 -> 1 | F41: =2031-Assumptions!$B$71 -> 2 | G41: =2032-Assumptions!$B$71 -> 3
A42: Share of year live | B42: =IF(B41<0,0,IF(B41=0,Assumptions!$C$71,1)) -> 0 | C42: =IF(C41<0,0,IF(C41=0,Assumptions!$C$71,1)) -> 0 | D42: =IF(D41<0,0,IF(D41=0,Assumptions!$C$71,1)) -> 0.6 | E42: =IF(E41<0,0,IF(E41=0,Assumptions!$C$71,1)) -> 1 | F42: =IF(F41<0,0,IF(F41=0,Assumptions!$C$71,1)) -> 1 | G42: =IF(G41<0,0,IF(G41=0,Assumptions!$C$71,1)) -> 1
A43: Use factor (live × ramp) | B43: =B42*IF(B41=0,Assumptions!$B$56,IF(B41=1,Assumptions!$B$57,1)) -> 0 | C43: =C42*IF(C41=0,Assumptions!$B$56,IF(C41=1,Assumptions!$B$57,1)) -> 0 | D43: =D42*IF(D41=0,Assumptions!$B$56,IF(D41=1,Assumptions!$B$57,1)) -> 0.33 | E43: =E42*IF(E41=0,Assumptions!$B$56,IF(E41=1,Assumptions!$B$57,1)) -> 0.8 | F43: =F42*IF(F41=0,Assumptions!$B$56,IF(F41=1,Assumptions!$B$57,1)) -> 1 | G43: =G42*IF(G41=0,Assumptions!$B$56,IF(G41=1,Assumptions!$B$57,1)) -> 1
A44: Capex in year | B44: =IF(B41=0,Debt!$P$5,0) -> 0 | C44: =IF(C41=0,Debt!$P$5,0) -> 0 | D44: =IF(D41=0,Debt!$P$5,0) -> 37999000 | E44: =IF(E41=0,Debt!$P$5,0) -> 0 | F44: =IF(F41=0,Debt!$P$5,0) -> 0 | G44: =IF(G41=0,Debt!$P$5,0) -> 0
A45: Bays live | B45: =IF(B41>=0,SUM(Assumptions!$D$71:$F$71),0) -> 0 | C45: =IF(C41>=0,SUM(Assumptions!$D$71:$F$71),0) -> 0 | D45: =IF(D41>=0,SUM(Assumptions!$D$71:$F$71),0) -> 60 | E45: =IF(E41>=0,SUM(Assumptions!$D$71:$F$71),0) -> 60 | F45: =IF(F41>=0,SUM(Assumptions!$D$71:$F$71),0) -> 60 | G45: =IF(G41>=0,SUM(Assumptions!$D$71:$F$71),0) -> 60
A46: Clubs live | B46: =IF(B41>=0,Assumptions!$G$71,0) -> 0 | C46: =IF(C41>=0,Assumptions!$G$71,0) -> 0 | D46: =IF(D41>=0,Assumptions!$G$71,0) -> 60 | E46: =IF(E41>=0,Assumptions!$G$71,0) -> 60 | F46: =IF(F41>=0,Assumptions!$G$71,0) -> 60 | G46: =IF(G41>=0,Assumptions!$G$71,0) -> 60
A47: Booked hours | B47: =(Assumptions!$D$71*MIN(Assumptions!$C$63*$B$2,Assumptions!$B$28)+Assumptions!$E$71*MIN(Assumptions!$C$64*$B$2,Assumptions!$B$28)+Assumptions!$F$71*MIN(Assumptions!$C$65*$B$2,Assumptions!$B$28))*Assumptions!$B$27*B43 -> 0 | C47: =(Assumptions!$D$71*MIN(Assumptions!$C$63*$B$2,Assumptions!$B$28)+Assumptions!$E$71*MIN(Assumptions!$C$64*$B$2,Assumptions!$B$28)+Assumptions!$F$71*MIN(Assumptions!$C$65*$B$2,Assumptions!$B$28))*Assumptions!$B$27*C43 -> 0 | D47: =(Assumptions!$D$71*MIN(Assumptions!$C$63*$B$2,Assumptions!$B$28)+Assumptions!$E$71*MIN(Assumptions!$C$64*$B$2,Assumptions!$B$28)+Assumptions!$F$71*MIN(Assumptions!$C$65*$B$2,Assumptions!$B$28))*Assumptions!$B$27*D43 -> 41431.5 | E47: =(Assumptions!$D$71*MIN(Assumptions!$C$63*$B$2,Assumptions!$B$28)+Assumptions!$E$71*MIN(Assumptions!$C$64*$B$2,Assumptions!$B$28)+Assumptions!$F$71*MIN(Assumptions!$C$65*$B$2,Assumptions!$B$28))*Assumptions!$B$27*E43 -> 100440 | F47: =(Assumptions!$D$71*MIN(Assumptions!$C$63*$B$2,Assumptions!$B$28)+Assumptions!$E$71*MIN(Assumptions!$C$64*$B$2,Assumptions!$B$28)+Assumptions!$F$71*MIN(Assumptions!$C$65*$B$2,Assumptions!$B$28))*Assumptions!$B$27*F43 -> 125550 | G47: =(Assumptions!$D$71*MIN(Assumptions!$C$63*$B$2,Assumptions!$B$28)+Assumptions!$E$71*MIN(Assumptions!$C$64*$B$2,Assumptions!$B$28)+Assumptions!$F$71*MIN(Assumptions!$C$65*$B$2,Assumptions!$B$28))*Assumptions!$B$27*G43 -> 125550
A48: Bay hire | B48: =(Assumptions!$D$71*MIN(Assumptions!$C$63*$B$2,Assumptions!$B$28)*Assumptions!$D$63+Assumptions!$E$71*MIN(Assumptions!$C$64*$B$2,Assumptions!$B$28)*Assumptions!$D$64+Assumptions!$F$71*MIN(Assumptions!$C$65*$B$2,Assumptions!$B$28)*Assumptions!$D$65)*Assumptions!$B$27*B43 -> 0 | C48: =(Assumptions!$D$71*MIN(Assumptions!$C$63*$B$2,Assumptions!$B$28)*Assumptions!$D$63+Assumptions!$E$71*MIN(Assumptions!$C$64*$B$2,Assumptions!$B$28)*Assumptions!$D$64+Assumptions!$F$71*MIN(Assumptions!$C$65*$B$2,Assumptions!$B$28)*Assumptions!$D$65)*Assumptions!$B$27*C43 -> 0 | D48: =(Assumptions!$D$71*MIN(Assumptions!$C$63*$B$2,Assumptions!$B$28)*Assumptions!$D$63+Assumptions!$E$71*MIN(Assumptions!$C$64*$B$2,Assumptions!$B$28)*Assumptions!$D$64+Assumptions!$F$71*MIN(Assumptions!$C$65*$B$2,Assumptions!$B$28)*Assumptions!$D$65)*Assumptions!$B$27*D43 -> 11707740 | E48: =(Assumptions!$D$71*MIN(Assumptions!$C$63*$B$2,Assumptions!$B$28)*Assumptions!$D$63+Assumptions!$E$71*MIN(Assumptions!$C$64*$B$2,Assumptions!$B$28)*Assumptions!$D$64+Assumptions!$F$71*MIN(Assumptions!$C$65*$B$2,Assumptions!$B$28)*Assumptions!$D$65)*Assumptions!$B$27*E43 -> 28382400 | F48: =(Assumptions!$D$71*MIN(Assumptions!$C$63*$B$2,Assumptions!$B$28)*Assumptions!$D$63+Assumptions!$E$71*MIN(Assumptions!$C$64*$B$2,Assumptions!$B$28)*Assumptions!$D$64+Assumptions!$F$71*MIN(Assumptions!$C$65*$B$2,Assumptions!$B$28)*Assumptions!$D$65)*Assumptions!$B$27*F43 -> 35478000 | G48: =(Assumptions!$D$71*MIN(Assumptions!$C$63*$B$2,Assumptions!$B$28)*Assumptions!$D$63+Assumptions!$E$71*MIN(Assumptions!$C$64*$B$2,Assumptions!$B$28)*Assumptions!$D$64+Assumptions!$F$71*MIN(Assumptions!$C$65*$B$2,Assumptions!$B$28)*Assumptions!$D$65)*Assumptions!$B$27*G43 -> 35478000
A49: Golf add-on | B49: =Assumptions!$G$71*Assumptions!$B$33*Assumptions!$B$35*$B$2*IF(B41=0,Assumptions!$B$36,IF(B41=1,Assumptions!$B$37,1))*Assumptions!$B$34*12*B42 -> 0 | C49: =Assumptions!$G$71*Assumptions!$B$33*Assumptions!$B$35*$B$2*IF(C41=0,Assumptions!$B$36,IF(C41=1,Assumptions!$B$37,1))*Assumptions!$B$34*12*C42 -> 0 | D49: =Assumptions!$G$71*Assumptions!$B$33*Assumptions!$B$35*$B$2*IF(D41=0,Assumptions!$B$36,IF(D41=1,Assumptions!$B$37,1))*Assumptions!$B$34*12*D42 -> 4437775.6 | E49: =Assumptions!$G$71*Assumptions!$B$33*Assumptions!$B$35*$B$2*IF(E41=0,Assumptions!$B$36,IF(E41=1,Assumptions!$B$37,1))*Assumptions!$B$34*12*E42 -> 13868049 | F49: =Assumptions!$G$71*Assumptions!$B$33*Assumptions!$B$35*$B$2*IF(F41=0,Assumptions!$B$36,IF(F41=1,Assumptions!$B$37,1))*Assumptions!$B$34*12*F42 -> 18490732 | G49: =Assumptions!$G$71*Assumptions!$B$33*Assumptions!$B$35*$B$2*IF(G41=0,Assumptions!$B$36,IF(G41=1,Assumptions!$B$37,1))*Assumptions!$B$34*12*G42 -> 18490732
A50: Leagues, events, corporate | B50: =B45*Assumptions!$B$40*B43 -> 0 | C50: =C45*Assumptions!$B$40*C43 -> 0 | D50: =D45*Assumptions!$B$40*D43 -> 792000 | E50: =E45*Assumptions!$B$40*E43 -> 1920000 | F50: =F45*Assumptions!$B$40*F43 -> 2400000 | G50: =G45*Assumptions!$B$40*G43 -> 2400000
A51: Insured shot, net of premium | B51: =B47*Assumptions!$B$45 -> 0 | C51: =C47*Assumptions!$B$45 -> 0 | D51: =D47*Assumptions!$B$45 -> 983998.12 | E51: =E47*Assumptions!$B$45 -> 2385450 | F51: =F47*Assumptions!$B$45 -> 2981812.5 | G51: =G47*Assumptions!$B$45 -> 2981812.5
A52: Naming partner | B52: =B45*Assumptions!$B$41*B42 -> 0 | C52: =C45*Assumptions!$B$41*C42 -> 0 | D52: =D45*Assumptions!$B$41*D42 -> 900000 | E52: =E45*Assumptions!$B$41*E42 -> 1500000 | F52: =F45*Assumptions!$B$41*F42 -> 1500000 | G52: =G45*Assumptions!$B$41*G42 -> 1500000
A53: Golfzon service and software | B53: =(Assumptions!$D$71*Assumptions!$B$63*Assumptions!$B$12+Assumptions!$E$71*Assumptions!$B$64*Assumptions!$B$12+Assumptions!$F$71*Assumptions!$B$65*Assumptions!$B$12)*Assumptions!$B$51*B42 -> 0 | C53: =(Assumptions!$D$71*Assumptions!$B$63*Assumptions!$B$12+Assumptions!$E$71*Assumptions!$B$64*Assumptions!$B$12+Assumptions!$F$71*Assumptions!$B$65*Assumptions!$B$12)*Assumptions!$B$51*C42 -> 0 | D53: =(Assumptions!$D$71*Assumptions!$B$63*Assumptions!$B$12+Assumptions!$E$71*Assumptions!$B$64*Assumptions!$B$12+Assumptions!$F$71*Assumptions!$B$65*Assumptions!$B$12)*Assumptions!$B$51*D42 -> 701520 | E53: =(Assumptions!$D$71*Assumptions!$B$63*Assumptions!$B$12+Assumptions!$E$71*Assumptions!$B$64*Assumptions!$B$12+Assumptions!$F$71*Assumptions!$B$65*Assumptions!$B$12)*Assumptions!$B$51*E42 -> 1169200 | F53: =(Assumptions!$D$71*Assumptions!$B$63*Assumptions!$B$12+Assumptions!$E$71*Assumptions!$B$64*Assumptions!$B$12+Assumptions!$F$71*Assumptions!$B$65*Assumptions!$B$12)*Assumptions!$B$51*F42 -> 1169200 | G53: =(Assumptions!$D$71*Assumptions!$B$63*Assumptions!$B$12+Assumptions!$E$71*Assumptions!$B$64*Assumptions!$B$12+Assumptions!$F$71*Assumptions!$B$65*Assumptions!$B$12)*Assumptions!$B$51*G42 -> 1169200
A54: Consumables and maintenance | B54: =B45*Assumptions!$B$52*B42 -> 0 | C54: =C45*Assumptions!$B$52*C42 -> 0 | D54: =D45*Assumptions!$B$52*D42 -> 864000 | E54: =E45*Assumptions!$B$52*E42 -> 1440000 | F54: =F45*Assumptions!$B$52*F42 -> 1440000 | G54: =G45*Assumptions!$B$52*G42 -> 1440000
A55: Asset insurance | B55: =Debt!$P$5*Assumptions!$B$50*B42 -> 0 | C55: =Debt!$P$5*Assumptions!$B$50*C42 -> 0 | D55: =Debt!$P$5*Assumptions!$B$50*D42 -> 227994 | E55: =Debt!$P$5*Assumptions!$B$50*E42 -> 379990 | F55: =Debt!$P$5*Assumptions!$B$50*F42 -> 379990 | G55: =Debt!$P$5*Assumptions!$B$50*G42 -> 379990
A57: The chain
A58: Bays live, total | B58: =B11+B28+B45 -> 40 | C58: =C11+C28+C45 -> 140 | D58: =D11+D28+D45 -> 200 | E58: =E11+E28+E45 -> 200 | F58: =F11+F28+F45 -> 200 | G58: =G11+G28+G45 -> 200
A59: Clubs with bays | B59: =B12+B29+B46 -> 20 | C59: =C12+C29+C46 -> 70 | D59: =D12+D29+D46 -> 130 | E59: =E12+E29+E46 -> 130 | F59: =F12+F29+F46 -> 130 | G59: =G12+G29+G46 -> 130
A60: Booked bay-hours | B60: =B13+B30+B47 -> 29700 | C60: =C13+C30+C47 -> 147656.25 | D60: =D13+D30+D47 -> 327631.5 | E60: =E13+E30+E47 -> 431190 | F60: =F13+F30+F47 -> 456300 | G60: =G13+G30+G47 -> 456300
A61: Booked hours a bay a day | B61: =IF(B58=0,0,B60/B58/Assumptions!$B$26) -> 2.0625 | C61: =IF(C58=0,0,C60/C58/Assumptions!$B$26) -> 2.9296875 | D61: =IF(D58=0,0,D60/D58/Assumptions!$B$26) -> 4.5504375 | E61: =IF(E58=0,0,E60/E58/Assumptions!$B$26) -> 5.98875 | F61: =IF(F58=0,0,F60/F58/Assumptions!$B$26) -> 6.3375 | G61: =IF(G58=0,0,G60/G58/Assumptions!$B$26) -> 6.3375
A62: Bay hire | B62: =B14+B31+B48 -> 15444000 | C62: =C14+C31+C48 -> 66980250 | D62: =D14+D31+D48 -> 132019740 | E62: =E14+E31+E48 -> 164732400 | F62: =F14+F31+F48 -> 171828000 | G62: =G14+G31+G48 -> 171828000
A63: Golf add-on memberships | B63: =B15+B32+B49 -> 1232715.4 | C63: =C15+C32+C49 -> 7704471.5 | D63: =D15+D32+D49 -> 22158060 | E63: =E15+E32+E49 -> 35440569 | F63: =F15+F32+F49 -> 40063252 | G63: =G15+G32+G49 -> 40063252
A64: Leagues, events, corporate | B64: =B16+B33+B50 -> 440000 | C64: =C16+C33+C50 -> 2380000 | D64: =D16+D33+D50 -> 5592000 | E64: =E16+E33+E50 -> 7520000 | F64: =F16+F33+F50 -> 8000000 | G64: =G16+G33+G50 -> 8000000
A65: Get Lucky insured shot, net of premium | B65: =B17+B34+B51 -> 705375 | C65: =C17+C34+C51 -> 3506835.9 | D65: =D17+D34+D51 -> 7781248.1 | E65: =E17+E34+E51 -> 10240762 | F65: =F17+F34+F51 -> 10837125 | G65: =G17+G34+G51 -> 10837125
A66: Naming partner | B66: =B18+B35+B52 -> 500000 | C66: =C18+C35+C52 -> 2250000 | D66: =D18+D35+D52 -> 4400000 | E66: =E18+E35+E52 -> 5000000 | F66: =F18+F35+F52 -> 5000000 | G66: =G18+G35+G52 -> 5000000
A67: Revenue shared with Virgin Active | B67: =B62+B63+B64+B65 -> 17822090 | C67: =C62+C63+C64+C65 -> 80571557 | D67: =D62+D63+D64+D65 -> 1.6755105e+08 | E67: =E62+E63+E64+E65 -> 2.1793373e+08 | F67: =F62+F63+F64+F65 -> 2.3072838e+08 | G67: =G62+G63+G64+G65 -> 2.3072838e+08
A68: Revenue | B68: =B67+B66 -> 18322090 | C68: =C67+C66 -> 82821557 | D68: =D67+D66 -> 1.7195105e+08 | E68: =E67+E66 -> 2.2293373e+08 | F68: =F67+F66 -> 2.3572838e+08 | G68: =G67+G66 -> 2.3572838e+08
A69: Virgin Active concession | B69: =-B67*Assumptions!$B$24 -> -3564418.1 | C69: =-C67*Assumptions!$B$24 -> -16114311 | D69: =-D67*Assumptions!$B$24 -> -33510210 | E69: =-E67*Assumptions!$B$24 -> -43586746 | F69: =-F67*Assumptions!$B$24 -> -46145675 | G69: =-G67*Assumptions!$B$24 -> -46145675
A70: Card and booking fees | B70: =-B67*Assumptions!$B$48 -> -445552.26 | C70: =-C67*Assumptions!$B$48 -> -2014288.9 | D70: =-D67*Assumptions!$B$48 -> -4188776.2 | E70: =-E67*Assumptions!$B$48 -> -5448343.3 | F70: =-F67*Assumptions!$B$48 -> -5768209.4 | G70: =-G67*Assumptions!$B$48 -> -5768209.4
A71: Marketing | B71: =-B68*Assumptions!$B$49 -> -916104.52 | C71: =-C68*Assumptions!$B$49 -> -4141077.9 | D71: =-D68*Assumptions!$B$49 -> -8597552.4 | E71: =-E68*Assumptions!$B$49 -> -11146687 | F71: =-F68*Assumptions!$B$49 -> -11786419 | G71: =-G68*Assumptions!$B$49 -> -11786419
A72: Golfzon service and software | B72: =-(B19+B36+B53) -> -888000 | C72: =-(C19+C36+C53) -> -3071000 | D72: =-(D19+D36+D53) -> -5067520 | E72: =-(E19+E36+E53) -> -5535200 | F72: =-(F19+F36+F53) -> -5535200 | G72: =-(G19+G36+G53) -> -5535200
A73: Consumables and maintenance | B73: =-(B20+B37+B54) -> -480000 | C73: =-(C20+C37+C54) -> -2160000 | D73: =-(D20+D37+D54) -> -4224000 | E73: =-(E20+E37+E54) -> -4800000 | F73: =-(F20+F37+F54) -> -4800000 | G73: =-(G20+G37+G54) -> -4800000
A74: Asset insurance | B74: =-(B21+B38+B55) -> -288600 | C74: =-(C21+C38+C55) -> -998075 | D74: =-(D21+D38+D55) -> -1646944 | E74: =-(E21+E38+E55) -> -1798940 | F74: =-(F21+F38+F55) -> -1798940 | G74: =-(G21+G38+G55) -> -1798940
A75: People | B75: =-Assumptions!B75 -> -4000000 | C75: =-Assumptions!C75 -> -8000000 | D75: =-Assumptions!D75 -> -11000000 | E75: =-Assumptions!E75 -> -12000000 | F75: =-Assumptions!F75 -> -12000000 | G75: =-Assumptions!G75 -> -12000000
A76: Central overhead | B76: =-Assumptions!B76 -> -2000000 | C76: =-Assumptions!C76 -> -3000000 | D76: =-Assumptions!D76 -> -4000000 | E76: =-Assumptions!E76 -> -4000000 | F76: =-Assumptions!F76 -> -4000000 | G76: =-Assumptions!G76 -> -4000000
A77: EBITDA | B77: =SUM(B68:B76) -> 5739415.6 | C77: =SUM(C68:C76) -> 43322804 | D77: =SUM(D68:D76) -> 99716046 | E77: =SUM(E68:E76) -> 1.3461782e+08 | F77: =SUM(F68:F76) -> 1.4389393e+08 | G77: =SUM(G68:G76) -> 1.4389393e+08
A78: EBITDA margin | B78: =IF(B68=0,0,B77/B68) -> 0.31325113 | C78: =IF(C68=0,0,C77/C68) -> 0.52308608 | D78: =IF(D68=0,0,D77/D68) -> 0.5799095 | E78: =IF(E68=0,0,E77/E68) -> 0.60384678 | F78: =IF(F68=0,0,F77/F68) -> 0.61042262 | G78: =IF(G68=0,0,G77/G68) -> 0.61042262
A79: RMB interest | B79: =-Debt!B93 -> -6233760 | C79: =-Debt!C93 -> -14890537 | D79: =-Debt!D93 -> -17338234 | E79: =-Debt!E93 -> -14407561 | F79: =-Debt!F93 -> -10753709 | G79: =-Debt!G93 -> -6636457.6
A80: RMB capital | B80: =-Debt!B94 -> 0 | C80: =-Debt!C94 -> -8067017.6 | D80: =-Debt!D94 -> -20854518 | E80: =-Debt!E94 -> -28810180 | F80: =-Debt!F94 -> -32464031 | G80: =-Debt!G94 -> -36581283
A81: Debt service | B81: =B79+B80 -> -6233760 | C81: =C79+C80 -> -22957555 | D81: =D79+D80 -> -38192752 | E81: =E79+E80 -> -43217741 | F81: =F79+F80 -> -43217741 | G81: =G79+G80 -> -43217741
A82: Debt cover (EBITDA ÷ debt service) | B82: =IF(B81=0,0,B77/-B81) -> 0.92069884 | C82: =IF(C81=0,0,C77/-C81) -> 1.8870827 | D82: =IF(D81=0,0,D77/-D81) -> 2.6108631 | E82: =IF(E81=0,0,E77/-E81) -> 3.114874 | F82: =IF(F81=0,0,F77/-F81) -> 3.3295108 | G82: =IF(G81=0,0,G77/-G81) -> 3.3295108
A83: Cash after debt | B83: =B77+B81 -> -494344.43 | C83: =C77+C81 -> 20365249 | D83: =D77+D81 -> 61523294 | E83: =E77+E81 -> 91400074 | F83: =F77+F81 -> 1.0067619e+08 | G83: =G77+G81 -> 1.0067619e+08
A84: Capex in year | B84: =B10+B27+B44 -> 57720000 | C84: =C10+C27+C44 -> 84175000 | D84: =D10+D27+D44 -> 37999000 | E84: =E10+E27+E44 -> 0 | F84: =F10+F27+F44 -> 0 | G84: =G10+G27+G44 -> 0
A85: Equity deposit (capex not financed by RMB) | B85: =-B84*(1-Assumptions!$B$18) -> -5772000 | C85: =-C84*(1-Assumptions!$B$18) -> -8417500 | D85: =-D84*(1-Assumptions!$B$18) -> -3799900 | E85: =-E84*(1-Assumptions!$B$18) -> 0 | F85: =-F84*(1-Assumptions!$B$18) -> 0 | G85: =-G84*(1-Assumptions!$B$18) -> 0
A86: Cumulative cash after deposits | B86: =B83+B85 -> -6266344.4 | C86: =C83+C85+B86 -> 5681404.9 | D86: =D83+D85+C86 -> 63404799 | E86: =E83+E85+D86 -> 1.5480487e+08 | F86: =F83+F85+E86 -> 2.5548107e+08 | G86: =G83+G85+F86 -> 3.5615726e+08
A87: Memo: to Virgin Active | B87: =-B69 -> 3564418.1 | C87: =-C69 -> 16114311 | D87: =-D69 -> 33510210 | E87: =-E69 -> 43586746 | F87: =-F69 -> 46145675 | G87: =-G69 -> 46145675
A89: Equity needed (lowest point of cumulative cash) | B89: =-MIN(B86:G86) -> 6266344.4

Sheet Negotiation
A1: The two movable posts — 2031 outcome by Virgin Active's share and who builds the shell
A2: Computed from the selected-case chain: a different share moves the concession line; a shell cost carried by Get Lucky Golf moves capex, the RMB instalments, asset insurance and the equity deposit. Debt cover uses 2031 EBITDA over 2031 debt service.
A4: Shell built by | B4: Virgin Active share | C4: Capex | D4: To Virgin Active | E4: Get Lucky Golf EBITDA | F4: Debt service | G4: Debt cover | H4: Equity needed
A5: Virgin Active | B5: 0.15 | C5: =Debt!$D$5*(1+IF($A5="Get Lucky Golf",Assumptions!$B$21-Assumptions!$B$20,0)*SUM(Assumptions!$D$69:$F$69)/Debt!$D$5)+Debt!$J$5*(1+IF($A5="Get Lucky Golf",Assumptions!$B$21-Assumptions!$B$20,0)*SUM(Assumptions!$D$70:$F$70)/Debt!$J$5)+Debt!$P$5*(1+IF($A5="Get Lucky Golf",Assumptions!$B$21-Assumptions!$B$20,0)*SUM(Assumptions!$D$71:$F$71)/Debt!$P$5) -> 179894000 | D5: =Chain!F67*$B5 -> 27927405 | E5: =Chain!F77-($B5-Assumptions!$B$24)*Chain!F67-IF($A5="Get Lucky Golf",Assumptions!$B$21-Assumptions!$B$20,0)*(SUM(Assumptions!$D$69:$F$69)*Chain!F8+SUM(Assumptions!$D$70:$F$70)*Chain!F25+SUM(Assumptions!$D$71:$F$71)*Chain!F42)*Assumptions!$B$50 -> 1.2090745e+08 | F5: =(Debt!F87+Debt!F88)*(1+IF($A5="Get Lucky Golf",Assumptions!$B$21-Assumptions!$B$20,0)*SUM(Assumptions!$D$69:$F$69)/Debt!$D$5)+(Debt!F89+Debt!F90)*(1+IF($A5="Get Lucky Golf",Assumptions!$B$21-Assumptions!$B$20,0)*SUM(Assumptions!$D$70:$F$70)/Debt!$J$5)+(Debt!F91+Debt!F92)*(1+IF($A5="Get Lucky Golf",Assumptions!$B$21-Assumptions!$B$20,0)*SUM(Assumptions!$D$71:$F$71)/Debt!$P$5) -> 43217741 | G5: =IF(F5=0,0,E5/F5) -> 2.7976348 | H5: =-MIN(C16:H16) -> 8069463.9
A6: Virgin Active | B6: 0.2 | C6: =Debt!$D$5*(1+IF($A6="Get Lucky Golf",Assumptions!$B$21-Assumptions!$B$20,0)*SUM(Assumptions!$D$69:$F$69)/Debt!$D$5)+Debt!$J$5*(1+IF($A6="Get Lucky Golf",Assumptions!$B$21-Assumptions!$B$20,0)*SUM(Assumptions!$D$70:$F$70)/Debt!$J$5)+Debt!$P$5*(1+IF($A6="Get Lucky Golf",Assumptions!$B$21-Assumptions!$B$20,0)*SUM(Assumptions!$D$71:$F$71)/Debt!$P$5) -> 179894000 | D6: =Chain!F67*$B6 -> 37236540 | E6: =Chain!F77-($B6-Assumptions!$B$24)*Chain!F67-IF($A6="Get Lucky Golf",Assumptions!$B$21-Assumptions!$B$20,0)*(SUM(Assumptions!$D$69:$F$69)*Chain!F8+SUM(Assumptions!$D$70:$F$70)*Chain!F25+SUM(Assumptions!$D$71:$F$71)*Chain!F42)*Assumptions!$B$50 -> 1.1159832e+08 | F6: =(Debt!F87+Debt!F88)*(1+IF($A6="Get Lucky Golf",Assumptions!$B$21-Assumptions!$B$20,0)*SUM(Assumptions!$D$69:$F$69)/Debt!$D$5)+(Debt!F89+Debt!F90)*(1+IF($A6="Get Lucky Golf",Assumptions!$B$21-Assumptions!$B$20,0)*SUM(Assumptions!$D$70:$F$70)/Debt!$J$5)+(Debt!F91+Debt!F92)*(1+IF($A6="Get Lucky Golf",Assumptions!$B$21-Assumptions!$B$20,0)*SUM(Assumptions!$D$71:$F$71)/Debt!$P$5) -> 43217741 | G6: =IF(F6=0,0,E6/F6) -> 2.582234 | H6: =-MIN(C17:H17) -> 8786747.5
A7: Virgin Active | B7: 0.25 | C7: =Debt!$D$5*(1+IF($A7="Get Lucky Golf",Assumptions!$B$21-Assumptions!$B$20,0)*SUM(Assumptions!$D$69:$F$69)/Debt!$D$5)+Debt!$J$5*(1+IF($A7="Get Lucky Golf",Assumptions!$B$21-Assumptions!$B$20,0)*SUM(Assumptions!$D$70:$F$70)/Debt!$J$5)+Debt!$P$5*(1+IF($A7="Get Lucky Golf",Assumptions!$B$21-Assumptions!$B$20,0)*SUM(Assumptions!$D$71:$F$71)/Debt!$P$5) -> 179894000 | D7: =Chain!F67*$B7 -> 46545675 | E7: =Chain!F77-($B7-Assumptions!$B$24)*Chain!F67-IF($A7="Get Lucky Golf",Assumptions!$B$21-Assumptions!$B$20,0)*(SUM(Assumptions!$D$69:$F$69)*Chain!F8+SUM(Assumptions!$D$70:$F$70)*Chain!F25+SUM(Assumptions!$D$71:$F$71)*Chain!F42)*Assumptions!$B$50 -> 1.0228918e+08 | F7: =(Debt!F87+Debt!F88)*(1+IF($A7="Get Lucky Golf",Assumptions!$B$21-Assumptions!$B$20,0)*SUM(Assumptions!$D$69:$F$69)/Debt!$D$5)+(Debt!F89+Debt!F90)*(1+IF($A7="Get Lucky Golf",Assumptions!$B$21-Assumptions!$B$20,0)*SUM(Assumptions!$D$70:$F$70)/Debt!$J$5)+(Debt!F91+Debt!F92)*(1+IF($A7="Get Lucky Golf",Assumptions!$B$21-Assumptions!$B$20,0)*SUM(Assumptions!$D$71:$F$71)/Debt!$P$5) -> 43217741 | G7: =IF(F7=0,0,E7/F7) -> 2.3668332 | H7: =-MIN(C18:H18) -> 12140720
A8: Get Lucky Golf | B8: 0.15 | C8: =Debt!$D$5*(1+IF($A8="Get Lucky Golf",Assumptions!$B$21-Assumptions!$B$20,0)*SUM(Assumptions!$D$69:$F$69)/Debt!$D$5)+Debt!$J$5*(1+IF($A8="Get Lucky Golf",Assumptions!$B$21-Assumptions!$B$20,0)*SUM(Assumptions!$D$70:$F$70)/Debt!$J$5)+Debt!$P$5*(1+IF($A8="Get Lucky Golf",Assumptions!$B$21-Assumptions!$B$20,0)*SUM(Assumptions!$D$71:$F$71)/Debt!$P$5) -> 209894000 | D8: =Chain!F67*$B8 -> 27927405 | E8: =Chain!F77-($B8-Assumptions!$B$24)*Chain!F67-IF($A8="Get Lucky Golf",Assumptions!$B$21-Assumptions!$B$20,0)*(SUM(Assumptions!$D$69:$F$69)*Chain!F8+SUM(Assumptions!$D$70:$F$70)*Chain!F25+SUM(Assumptions!$D$71:$F$71)*Chain!F42)*Assumptions!$B$50 -> 1.2060745e+08 | F8: =(Debt!F87+Debt!F88)*(1+IF($A8="Get Lucky Golf",Assumptions!$B$21-Assumptions!$B$20,0)*SUM(Assumptions!$D$69:$F$69)/Debt!$D$5)+(Debt!F89+Debt!F90)*(1+IF($A8="Get Lucky Golf",Assumptions!$B$21-Assumptions!$B$20,0)*SUM(Assumptions!$D$70:$F$70)/Debt!$J$5)+(Debt!F91+Debt!F92)*(1+IF($A8="Get Lucky Golf",Assumptions!$B$21-Assumptions!$B$20,0)*SUM(Assumptions!$D$71:$F$71)/Debt!$P$5) -> 50424942 | G8: =IF(F8=0,0,E8/F8) -> 2.3918214 | H8: =-MIN(C19:H19) -> 10187268
A9: Get Lucky Golf | B9: 0.2 | C9: =Debt!$D$5*(1+IF($A9="Get Lucky Golf",Assumptions!$B$21-Assumptions!$B$20,0)*SUM(Assumptions!$D$69:$F$69)/Debt!$D$5)+Debt!$J$5*(1+IF($A9="Get Lucky Golf",Assumptions!$B$21-Assumptions!$B$20,0)*SUM(Assumptions!$D$70:$F$70)/Debt!$J$5)+Debt!$P$5*(1+IF($A9="Get Lucky Golf",Assumptions!$B$21-Assumptions!$B$20,0)*SUM(Assumptions!$D$71:$F$71)/Debt!$P$5) -> 209894000 | D9: =Chain!F67*$B9 -> 37236540 | E9: =Chain!F77-($B9-Assumptions!$B$24)*Chain!F67-IF($A9="Get Lucky Golf",Assumptions!$B$21-Assumptions!$B$20,0)*(SUM(Assumptions!$D$69:$F$69)*Chain!F8+SUM(Assumptions!$D$70:$F$70)*Chain!F25+SUM(Assumptions!$D$71:$F$71)*Chain!F42)*Assumptions!$B$50 -> 1.1129832e+08 | F9: =(Debt!F87+Debt!F88)*(1+IF($A9="Get Lucky Golf",Assumptions!$B$21-Assumptions!$B$20,0)*SUM(Assumptions!$D$69:$F$69)/Debt!$D$5)+(Debt!F89+Debt!F90)*(1+IF($A9="Get Lucky Golf",Assumptions!$B$21-Assumptions!$B$20,0)*SUM(Assumptions!$D$70:$F$70)/Debt!$J$5)+(Debt!F91+Debt!F92)*(1+IF($A9="Get Lucky Golf",Assumptions!$B$21-Assumptions!$B$20,0)*SUM(Assumptions!$D$71:$F$71)/Debt!$P$5) -> 50424942 | G9: =IF(F9=0,0,E9/F9) -> 2.2072077 | H9: =-MIN(C20:H20) -> 14151214
A10: Get Lucky Golf | B10: 0.25 | C10: =Debt!$D$5*(1+IF($A10="Get Lucky Golf",Assumptions!$B$21-Assumptions!$B$20,0)*SUM(Assumptions!$D$69:$F$69)/Debt!$D$5)+Debt!$J$5*(1+IF($A10="Get Lucky Golf",Assumptions!$B$21-Assumptions!$B$20,0)*SUM(Assumptions!$D$70:$F$70)/Debt!$J$5)+Debt!$P$5*(1+IF($A10="Get Lucky Golf",Assumptions!$B$21-Assumptions!$B$20,0)*SUM(Assumptions!$D$71:$F$71)/Debt!$P$5) -> 209894000 | D10: =Chain!F67*$B10 -> 46545675 | E10: =Chain!F77-($B10-Assumptions!$B$24)*Chain!F67-IF($A10="Get Lucky Golf",Assumptions!$B$21-Assumptions!$B$20,0)*(SUM(Assumptions!$D$69:$F$69)*Chain!F8+SUM(Assumptions!$D$70:$F$70)*Chain!F25+SUM(Assumptions!$D$71:$F$71)*Chain!F42)*Assumptions!$B$50 -> 1.0198918e+08 | F10: =(Debt!F87+Debt!F88)*(1+IF($A10="Get Lucky Golf",Assumptions!$B$21-Assumptions!$B$20,0)*SUM(Assumptions!$D$69:$F$69)/Debt!$D$5)+(Debt!F89+Debt!F90)*(1+IF($A10="Get Lucky Golf",Assumptions!$B$21-Assumptions!$B$20,0)*SUM(Assumptions!$D$70:$F$70)/Debt!$J$5)+(Debt!F91+Debt!F92)*(1+IF($A10="Get Lucky Golf",Assumptions!$B$21-Assumptions!$B$20,0)*SUM(Assumptions!$D$71:$F$71)/Debt!$P$5) -> 50424942 | G10: =IF(F10=0,0,E10/F10) -> 2.022594 | H10: =-MIN(C21:H21) -> 18115160
A12: Opening position: 20% and Virgin Active builds the shell. Both posts move to make the deal fit. A bank's usual floor is 1.3× debt cover on the low case; run the selector on Assumptions at 0.7 to see it.
A14: Helper: cumulative cash after deposits by year, per combination
C15: 2027 | D15: 2028 | E15: 2029 | F15: 2030 | G15: 2031 | H15: 2032
A16: Virgin Active | B16: =B5 -> 0.15 | C16: =(Chain!B77-($B16-Assumptions!$B$24)*Chain!B67-IF($A16="Get Lucky Golf",Assumptions!$B$21-Assumptions!$B$20,0)*(SUM(Assumptions!$D$69:$F$69)*Chain!B8+SUM(Assumptions!$D$70:$F$70)*Chain!B25+SUM(Assumptions!$D$71:$F$71)*Chain!B42)*Assumptions!$B$50)-((Debt!B87+Debt!B88)*(1+IF($A16="Get Lucky Golf",Assumptions!$B$21-Assumptions!$B$20,0)*SUM(Assumptions!$D$69:$F$69)/Debt!$D$5)+(Debt!B89+Debt!B90)*(1+IF($A16="Get Lucky Golf",Assumptions!$B$21-Assumptions!$B$20,0)*SUM(Assumptions!$D$70:$F$70)/Debt!$J$5)+(Debt!B91+Debt!B92)*(1+IF($A16="Get Lucky Golf",Assumptions!$B$21-Assumptions!$B$20,0)*SUM(Assumptions!$D$71:$F$71)/Debt!$P$5))-(Chain!B10*(1-Assumptions!$B$18)*(1+IF($A16="Get Lucky Golf",Assumptions!$B$21-Assumptions!$B$20,0)*SUM(Assumptions!$D$69:$F$69)/Debt!$D$5)+Chain!B27*(1-Assumptions!$B$18)*(1+IF($A16="Get Lucky Golf",Assumptions!$B$21-Assumptions!$B$20,0)*SUM(Assumptions!$D$70:$F$70)/Debt!$J$5)+Chain!B44*(1-Assumptions!$B$18)*(1+IF($A16="Get Lucky Golf",Assumptions!$B$21-Assumptions!$B$20,0)*SUM(Assumptions!$D$71:$F$71)/Debt!$P$5)) -> -8069463.9 | D16: =(Chain!C77-($B16-Assumptions!$B$24)*Chain!C67-IF($A16="Get Lucky Golf",Assumptions!$B$21-Assumptions!$B$20,0)*(SUM(Assumptions!$D$69:$F$69)*Chain!C8+SUM(Assumptions!$D$70:$F$70)*Chain!C25+SUM(Assumptions!$D$71:$F$71)*Chain!C42)*Assumptions!$B$50)-((Debt!C87+Debt!C88)*(1+IF($A16="Get Lucky Golf",Assumptions!$B$21-Assumptions!$B$20,0)*SUM(Assumptions!$D$69:$F$69)/Debt!$D$5)+(Debt!C89+Debt!C90)*(1+IF($A16="Get Lucky Golf",Assumptions!$B$21-Assumptions!$B$20,0)*SUM(Assumptions!$D$70:$F$70)/Debt!$J$5)+(Debt!C91+Debt!C92)*(1+IF($A16="Get Lucky Golf",Assumptions!$B$21-Assumptions!$B$20,0)*SUM(Assumptions!$D$71:$F$71)/Debt!$P$5))-(Chain!C10*(1-Assumptions!$B$18)*(1+IF($A16="Get Lucky Golf",Assumptions!$B$21-Assumptions!$B$20,0)*SUM(Assumptions!$D$69:$F$69)/Debt!$D$5)+Chain!C27*(1-Assumptions!$B$18)*(1+IF($A16="Get Lucky Golf",Assumptions!$B$21-Assumptions!$B$20,0)*SUM(Assumptions!$D$70:$F$70)/Debt!$J$5)+Chain!C44*(1-Assumptions!$B$18)*(1+IF($A16="Get Lucky Golf",Assumptions!$B$21-Assumptions!$B$20,0)*SUM(Assumptions!$D$71:$F$71)/Debt!$P$5))+C16 -> -4212828.1 | E16: =(Chain!D77-($B16-Assumptions!$B$24)*Chain!D67-IF($A16="Get Lucky Golf",Assumptions!$B$21-Assumptions!$B$20,0)*(SUM(Assumptions!$D$69:$F$69)*Chain!D8+SUM(Assumptions!$D$70:$F$70)*Chain!D25+SUM(Assumptions!$D$71:$F$71)*Chain!D42)*Assumptions!$B$50)-((Debt!D87+Debt!D88)*(1+IF($A16="Get Lucky Golf",Assumptions!$B$21-Assumptions!$B$20,0)*SUM(Assumptions!$D$69:$F$69)/Debt!$D$5)+(Debt!D89+Debt!D90)*(1+IF($A16="Get Lucky Golf",Assumptions!$B$21-Assumptions!$B$20,0)*SUM(Assumptions!$D$70:$F$70)/Debt!$J$5)+(Debt!D91+Debt!D92)*(1+IF($A16="Get Lucky Golf",Assumptions!$B$21-Assumptions!$B$20,0)*SUM(Assumptions!$D$71:$F$71)/Debt!$P$5))-(Chain!D10*(1-Assumptions!$B$18)*(1+IF($A16="Get Lucky Golf",Assumptions!$B$21-Assumptions!$B$20,0)*SUM(Assumptions!$D$69:$F$69)/Debt!$D$5)+Chain!D27*(1-Assumptions!$B$18)*(1+IF($A16="Get Lucky Golf",Assumptions!$B$21-Assumptions!$B$20,0)*SUM(Assumptions!$D$70:$F$70)/Debt!$J$5)+Chain!D44*(1-Assumptions!$B$18)*(1+IF($A16="Get Lucky Golf",Assumptions!$B$21-Assumptions!$B$20,0)*SUM(Assumptions!$D$71:$F$71)/Debt!$P$5))+D16 -> 36784466 | F16: =(Chain!E77-($B16-Assumptions!$B$24)*Chain!E67-IF($A16="Get Lucky Golf",Assumptions!$B$21-Assumptions!$B$20,0)*(SUM(Assumptions!$D$69:$F$69)*Chain!E8+SUM(Assumptions!$D$70:$F$70)*Chain!E25+SUM(Assumptions!$D$71:$F$71)*Chain!E42)*Assumptions!$B$50)-((Debt!E87+Debt!E88)*(1+IF($A16="Get Lucky Golf",Assumptions!$B$21-Assumptions!$B$20,0)*SUM(Assumptions!$D$69:$F$69)/Debt!$D$5)+(Debt!E89+Debt!E90)*(1+IF($A16="Get Lucky Golf",Assumptions!$B$21-Assumptions!$B$20,0)*SUM(Assumptions!$D$70:$F$70)/Debt!$J$5)+(Debt!E91+Debt!E92)*(1+IF($A16="Get Lucky Golf",Assumptions!$B$21-Assumptions!$B$20,0)*SUM(Assumptions!$D$71:$F$71)/Debt!$P$5))-(Chain!E10*(1-Assumptions!$B$18)*(1+IF($A16="Get Lucky Golf",Assumptions!$B$21-Assumptions!$B$20,0)*SUM(Assumptions!$D$69:$F$69)/Debt!$D$5)+Chain!E27*(1-Assumptions!$B$18)*(1+IF($A16="Get Lucky Golf",Assumptions!$B$21-Assumptions!$B$20,0)*SUM(Assumptions!$D$70:$F$70)/Debt!$J$5)+Chain!E44*(1-Assumptions!$B$18)*(1+IF($A16="Get Lucky Golf",Assumptions!$B$21-Assumptions!$B$20,0)*SUM(Assumptions!$D$71:$F$71)/Debt!$P$5))+E16 -> 1.064671e+08 | G16: =(Chain!F77-($B16-Assumptions!$B$24)*Chain!F67-IF($A16="Get Lucky Golf",Assumptions!$B$21-Assumptions!$B$20,0)*(SUM(Assumptions!$D$69:$F$69)*Chain!F8+SUM(Assumptions!$D$70:$F$70)*Chain!F25+SUM(Assumptions!$D$71:$F$71)*Chain!F42)*Assumptions!$B$50)-((Debt!F87+Debt!F88)*(1+IF($A16="Get Lucky Golf",Assumptions!$B$21-Assumptions!$B$20,0)*SUM(Assumptions!$D$69:$F$69)/Debt!$D$5)+(Debt!F89+Debt!F90)*(1+IF($A16="Get Lucky Golf",Assumptions!$B$21-Assumptions!$B$20,0)*SUM(Assumptions!$D$70:$F$70)/Debt!$J$5)+(Debt!F91+Debt!F92)*(1+IF($A16="Get Lucky Golf",Assumptions!$B$21-Assumptions!$B$20,0)*SUM(Assumptions!$D$71:$F$71)/Debt!$P$5))-(Chain!F10*(1-Assumptions!$B$18)*(1+IF($A16="Get Lucky Golf",Assumptions!$B$21-Assumptions!$B$20,0)*SUM(Assumptions!$D$69:$F$69)/Debt!$D$5)+Chain!F27*(1-Assumptions!$B$18)*(1+IF($A16="Get Lucky Golf",Assumptions!$B$21-Assumptions!$B$20,0)*SUM(Assumptions!$D$70:$F$70)/Debt!$J$5)+Chain!F44*(1-Assumptions!$B$18)*(1+IF($A16="Get Lucky Golf",Assumptions!$B$21-Assumptions!$B$20,0)*SUM(Assumptions!$D$71:$F$71)/Debt!$P$5))+F16 -> 1.8415681e+08 | H16: =(Chain!G77-($B16-Assumptions!$B$24)*Chain!G67-IF($A16="Get Lucky Golf",Assumptions!$B$21-Assumptions!$B$20,0)*(SUM(Assumptions!$D$69:$F$69)*Chain!G8+SUM(Assumptions!$D$70:$F$70)*Chain!G25+SUM(Assumptions!$D$71:$F$71)*Chain!G42)*Assumptions!$B$50)-((Debt!G87+Debt!G88)*(1+IF($A16="Get Lucky Golf",Assumptions!$B$21-Assumptions!$B$20,0)*SUM(Assumptions!$D$69:$F$69)/Debt!$D$5)+(Debt!G89+Debt!G90)*(1+IF($A16="Get Lucky Golf",Assumptions!$B$21-Assumptions!$B$20,0)*SUM(Assumptions!$D$70:$F$70)/Debt!$J$5)+(Debt!G91+Debt!G92)*(1+IF($A16="Get Lucky Golf",Assumptions!$B$21-Assumptions!$B$20,0)*SUM(Assumptions!$D$71:$F$71)/Debt!$P$5))-(Chain!G10*(1-Assumptions!$B$18)*(1+IF($A16="Get Lucky Golf",Assumptions!$B$21-Assumptions!$B$20,0)*SUM(Assumptions!$D$69:$F$69)/Debt!$D$5)+Chain!G27*(1-Assumptions!$B$18)*(1+IF($A16="Get Lucky Golf",Assumptions!$B$21-Assumptions!$B$20,0)*SUM(Assumptions!$D$70:$F$70)/Debt!$J$5)+Chain!G44*(1-Assumptions!$B$18)*(1+IF($A16="Get Lucky Golf",Assumptions!$B$21-Assumptions!$B$20,0)*SUM(Assumptions!$D$71:$F$71)/Debt!$P$5))+G16 -> 2.6184652e+08
A17: Virgin Active | B17: =B6 -> 0.2 | C17: =(Chain!B77-($B17-Assumptions!$B$24)*Chain!B67-IF($A17="Get Lucky Golf",Assumptions!$B$21-Assumptions!$B$20,0)*(SUM(Assumptions!$D$69:$F$69)*Chain!B8+SUM(Assumptions!$D$70:$F$70)*Chain!B25+SUM(Assumptions!$D$71:$F$71)*Chain!B42)*Assumptions!$B$50)-((Debt!B87+Debt!B88)*(1+IF($A17="Get Lucky Golf",Assumptions!$B$21-Assumptions!$B$20,0)*SUM(Assumptions!$D$69:$F$69)/Debt!$D$5)+(Debt!B89+Debt!B90)*(1+IF($A17="Get Lucky Golf",Assumptions!$B$21-Assumptions!$B$20,0)*SUM(Assumptions!$D$70:$F$70)/Debt!$J$5)+(Debt!B91+Debt!B92)*(1+IF($A17="Get Lucky Golf",Assumptions!$B$21-Assumptions!$B$20,0)*SUM(Assumptions!$D$71:$F$71)/Debt!$P$5))-(Chain!B10*(1-Assumptions!$B$18)*(1+IF($A17="Get Lucky Golf",Assumptions!$B$21-Assumptions!$B$20,0)*SUM(Assumptions!$D$69:$F$69)/Debt!$D$5)+Chain!B27*(1-Assumptions!$B$18)*(1+IF($A17="Get Lucky Golf",Assumptions!$B$21-Assumptions!$B$20,0)*SUM(Assumptions!$D$70:$F$70)/Debt!$J$5)+Chain!B44*(1-Assumptions!$B$18)*(1+IF($A17="Get Lucky Golf",Assumptions!$B$21-Assumptions!$B$20,0)*SUM(Assumptions!$D$71:$F$71)/Debt!$P$5)) -> -8786747.5 | D17: =(Chain!C77-($B17-Assumptions!$B$24)*Chain!C67-IF($A17="Get Lucky Golf",Assumptions!$B$21-Assumptions!$B$20,0)*(SUM(Assumptions!$D$69:$F$69)*Chain!C8+SUM(Assumptions!$D$70:$F$70)*Chain!C25+SUM(Assumptions!$D$71:$F$71)*Chain!C42)*Assumptions!$B$50)-((Debt!C87+Debt!C88)*(1+IF($A17="Get Lucky Golf",Assumptions!$B$21-Assumptions!$B$20,0)*SUM(Assumptions!$D$69:$F$69)/Debt!$D$5)+(Debt!C89+Debt!C90)*(1+IF($A17="Get Lucky Golf",Assumptions!$B$21-Assumptions!$B$20,0)*SUM(Assumptions!$D$70:$F$70)/Debt!$J$5)+(Debt!C91+Debt!C92)*(1+IF($A17="Get Lucky Golf",Assumptions!$B$21-Assumptions!$B$20,0)*SUM(Assumptions!$D$71:$F$71)/Debt!$P$5))-(Chain!C10*(1-Assumptions!$B$18)*(1+IF($A17="Get Lucky Golf",Assumptions!$B$21-Assumptions!$B$20,0)*SUM(Assumptions!$D$69:$F$69)/Debt!$D$5)+Chain!C27*(1-Assumptions!$B$18)*(1+IF($A17="Get Lucky Golf",Assumptions!$B$21-Assumptions!$B$20,0)*SUM(Assumptions!$D$70:$F$70)/Debt!$J$5)+Chain!C44*(1-Assumptions!$B$18)*(1+IF($A17="Get Lucky Golf",Assumptions!$B$21-Assumptions!$B$20,0)*SUM(Assumptions!$D$71:$F$71)/Debt!$P$5))+C17 -> -8176774 | E17: =(Chain!D77-($B17-Assumptions!$B$24)*Chain!D67-IF($A17="Get Lucky Golf",Assumptions!$B$21-Assumptions!$B$20,0)*(SUM(Assumptions!$D$69:$F$69)*Chain!D8+SUM(Assumptions!$D$70:$F$70)*Chain!D25+SUM(Assumptions!$D$71:$F$71)*Chain!D42)*Assumptions!$B$50)-((Debt!D87+Debt!D88)*(1+IF($A17="Get Lucky Golf",Assumptions!$B$21-Assumptions!$B$20,0)*SUM(Assumptions!$D$69:$F$69)/Debt!$D$5)+(Debt!D89+Debt!D90)*(1+IF($A17="Get Lucky Golf",Assumptions!$B$21-Assumptions!$B$20,0)*SUM(Assumptions!$D$70:$F$70)/Debt!$J$5)+(Debt!D91+Debt!D92)*(1+IF($A17="Get Lucky Golf",Assumptions!$B$21-Assumptions!$B$20,0)*SUM(Assumptions!$D$71:$F$71)/Debt!$P$5))-(Chain!D10*(1-Assumptions!$B$18)*(1+IF($A17="Get Lucky Golf",Assumptions!$B$21-Assumptions!$B$20,0)*SUM(Assumptions!$D$69:$F$69)/Debt!$D$5)+Chain!D27*(1-Assumptions!$B$18)*(1+IF($A17="Get Lucky Golf",Assumptions!$B$21-Assumptions!$B$20,0)*SUM(Assumptions!$D$70:$F$70)/Debt!$J$5)+Chain!D44*(1-Assumptions!$B$18)*(1+IF($A17="Get Lucky Golf",Assumptions!$B$21-Assumptions!$B$20,0)*SUM(Assumptions!$D$71:$F$71)/Debt!$P$5))+D17 -> 26062558 | F17: =(Chain!E77-($B17-Assumptions!$B$24)*Chain!E67-IF($A17="Get Lucky Golf",Assumptions!$B$21-Assumptions!$B$20,0)*(SUM(Assumptions!$D$69:$F$69)*Chain!E8+SUM(Assumptions!$D$70:$F$70)*Chain!E25+SUM(Assumptions!$D$71:$F$71)*Chain!E42)*Assumptions!$B$50)-((Debt!E87+Debt!E88)*(1+IF($A17="Get Lucky Golf",Assumptions!$B$21-Assumptions!$B$20,0)*SUM(Assumptions!$D$69:$F$69)/Debt!$D$5)+(Debt!E89+Debt!E90)*(1+IF($A17="Get Lucky Golf",Assumptions!$B$21-Assumptions!$B$20,0)*SUM(Assumptions!$D$70:$F$70)/Debt!$J$5)+(Debt!E91+Debt!E92)*(1+IF($A17="Get Lucky Golf",Assumptions!$B$21-Assumptions!$B$20,0)*SUM(Assumptions!$D$71:$F$71)/Debt!$P$5))-(Chain!E10*(1-Assumptions!$B$18)*(1+IF($A17="Get Lucky Golf",Assumptions!$B$21-Assumptions!$B$20,0)*SUM(Assumptions!$D$69:$F$69)/Debt!$D$5)+Chain!E27*(1-Assumptions!$B$18)*(1+IF($A17="Get Lucky Golf",Assumptions!$B$21-Assumptions!$B$20,0)*SUM(Assumptions!$D$70:$F$70)/Debt!$J$5)+Chain!E44*(1-Assumptions!$B$18)*(1+IF($A17="Get Lucky Golf",Assumptions!$B$21-Assumptions!$B$20,0)*SUM(Assumptions!$D$71:$F$71)/Debt!$P$5))+E17 -> 86952642 | G17: =(Chain!F77-($B17-Assumptions!$B$24)*Chain!F67-IF($A17="Get Lucky Golf",Assumptions!$B$21-Assumptions!$B$20,0)*(SUM(Assumptions!$D$69:$F$69)*Chain!F8+SUM(Assumptions!$D$70:$F$70)*Chain!F25+SUM(Assumptions!$D$71:$F$71)*Chain!F42)*Assumptions!$B$50)-((Debt!F87+Debt!F88)*(1+IF($A17="Get Lucky Golf",Assumptions!$B$21-Assumptions!$B$20,0)*SUM(Assumptions!$D$69:$F$69)/Debt!$D$5)+(Debt!F89+Debt!F90)*(1+IF($A17="Get Lucky Golf",Assumptions!$B$21-Assumptions!$B$20,0)*SUM(Assumptions!$D$70:$F$70)/Debt!$J$5)+(Debt!F91+Debt!F92)*(1+IF($A17="Get Lucky Golf",Assumptions!$B$21-Assumptions!$B$20,0)*SUM(Assumptions!$D$71:$F$71)/Debt!$P$5))-(Chain!F10*(1-Assumptions!$B$18)*(1+IF($A17="Get Lucky Golf",Assumptions!$B$21-Assumptions!$B$20,0)*SUM(Assumptions!$D$69:$F$69)/Debt!$D$5)+Chain!F27*(1-Assumptions!$B$18)*(1+IF($A17="Get Lucky Golf",Assumptions!$B$21-Assumptions!$B$20,0)*SUM(Assumptions!$D$70:$F$70)/Debt!$J$5)+Chain!F44*(1-Assumptions!$B$18)*(1+IF($A17="Get Lucky Golf",Assumptions!$B$21-Assumptions!$B$20,0)*SUM(Assumptions!$D$71:$F$71)/Debt!$P$5))+F17 -> 1.5533322e+08 | H17: =(Chain!G77-($B17-Assumptions!$B$24)*Chain!G67-IF($A17="Get Lucky Golf",Assumptions!$B$21-Assumptions!$B$20,0)*(SUM(Assumptions!$D$69:$F$69)*Chain!G8+SUM(Assumptions!$D$70:$F$70)*Chain!G25+SUM(Assumptions!$D$71:$F$71)*Chain!G42)*Assumptions!$B$50)-((Debt!G87+Debt!G88)*(1+IF($A17="Get Lucky Golf",Assumptions!$B$21-Assumptions!$B$20,0)*SUM(Assumptions!$D$69:$F$69)/Debt!$D$5)+(Debt!G89+Debt!G90)*(1+IF($A17="Get Lucky Golf",Assumptions!$B$21-Assumptions!$B$20,0)*SUM(Assumptions!$D$70:$F$70)/Debt!$J$5)+(Debt!G91+Debt!G92)*(1+IF($A17="Get Lucky Golf",Assumptions!$B$21-Assumptions!$B$20,0)*SUM(Assumptions!$D$71:$F$71)/Debt!$P$5))-(Chain!G10*(1-Assumptions!$B$18)*(1+IF($A17="Get Lucky Golf",Assumptions!$B$21-Assumptions!$B$20,0)*SUM(Assumptions!$D$69:$F$69)/Debt!$D$5)+Chain!G27*(1-Assumptions!$B$18)*(1+IF($A17="Get Lucky Golf",Assumptions!$B$21-Assumptions!$B$20,0)*SUM(Assumptions!$D$70:$F$70)/Debt!$J$5)+Chain!G44*(1-Assumptions!$B$18)*(1+IF($A17="Get Lucky Golf",Assumptions!$B$21-Assumptions!$B$20,0)*SUM(Assumptions!$D$71:$F$71)/Debt!$P$5))+G17 -> 2.237138e+08
A18: Virgin Active | B18: =B7 -> 0.25 | C18: =(Chain!B77-($B18-Assumptions!$B$24)*Chain!B67-IF($A18="Get Lucky Golf",Assumptions!$B$21-Assumptions!$B$20,0)*(SUM(Assumptions!$D$69:$F$69)*Chain!B8+SUM(Assumptions!$D$70:$F$70)*Chain!B25+SUM(Assumptions!$D$71:$F$71)*Chain!B42)*Assumptions!$B$50)-((Debt!B87+Debt!B88)*(1+IF($A18="Get Lucky Golf",Assumptions!$B$21-Assumptions!$B$20,0)*SUM(Assumptions!$D$69:$F$69)/Debt!$D$5)+(Debt!B89+Debt!B90)*(1+IF($A18="Get Lucky Golf",Assumptions!$B$21-Assumptions!$B$20,0)*SUM(Assumptions!$D$70:$F$70)/Debt!$J$5)+(Debt!B91+Debt!B92)*(1+IF($A18="Get Lucky Golf",Assumptions!$B$21-Assumptions!$B$20,0)*SUM(Assumptions!$D$71:$F$71)/Debt!$P$5))-(Chain!B10*(1-Assumptions!$B$18)*(1+IF($A18="Get Lucky Golf",Assumptions!$B$21-Assumptions!$B$20,0)*SUM(Assumptions!$D$69:$F$69)/Debt!$D$5)+Chain!B27*(1-Assumptions!$B$18)*(1+IF($A18="Get Lucky Golf",Assumptions!$B$21-Assumptions!$B$20,0)*SUM(Assumptions!$D$70:$F$70)/Debt!$J$5)+Chain!B44*(1-Assumptions!$B$18)*(1+IF($A18="Get Lucky Golf",Assumptions!$B$21-Assumptions!$B$20,0)*SUM(Assumptions!$D$71:$F$71)/Debt!$P$5)) -> -9504031.2 | D18: =(Chain!C77-($B18-Assumptions!$B$24)*Chain!C67-IF($A18="Get Lucky Golf",Assumptions!$B$21-Assumptions!$B$20,0)*(SUM(Assumptions!$D$69:$F$69)*Chain!C8+SUM(Assumptions!$D$70:$F$70)*Chain!C25+SUM(Assumptions!$D$71:$F$71)*Chain!C42)*Assumptions!$B$50)-((Debt!C87+Debt!C88)*(1+IF($A18="Get Lucky Golf",Assumptions!$B$21-Assumptions!$B$20,0)*SUM(Assumptions!$D$69:$F$69)/Debt!$D$5)+(Debt!C89+Debt!C90)*(1+IF($A18="Get Lucky Golf",Assumptions!$B$21-Assumptions!$B$20,0)*SUM(Assumptions!$D$70:$F$70)/Debt!$J$5)+(Debt!C91+Debt!C92)*(1+IF($A18="Get Lucky Golf",Assumptions!$B$21-Assumptions!$B$20,0)*SUM(Assumptions!$D$71:$F$71)/Debt!$P$5))-(Chain!C10*(1-Assumptions!$B$18)*(1+IF($A18="Get Lucky Golf",Assumptions!$B$21-Assumptions!$B$20,0)*SUM(Assumptions!$D$69:$F$69)/Debt!$D$5)+Chain!C27*(1-Assumptions!$B$18)*(1+IF($A18="Get Lucky Golf",Assumptions!$B$21-Assumptions!$B$20,0)*SUM(Assumptions!$D$70:$F$70)/Debt!$J$5)+Chain!C44*(1-Assumptions!$B$18)*(1+IF($A18="Get Lucky Golf",Assumptions!$B$21-Assumptions!$B$20,0)*SUM(Assumptions!$D$71:$F$71)/Debt!$P$5))+C18 -> -12140720 | E18: =(Chain!D77-($B18-Assumptions!$B$24)*Chain!D67-IF($A18="Get Lucky Golf",Assumptions!$B$21-Assumptions!$B$20,0)*(SUM(Assumptions!$D$69:$F$69)*Chain!D8+SUM(Assumptions!$D$70:$F$70)*Chain!D25+SUM(Assumptions!$D$71:$F$71)*Chain!D42)*Assumptions!$B$50)-((Debt!D87+Debt!D88)*(1+IF($A18="Get Lucky Golf",Assumptions!$B$21-Assumptions!$B$20,0)*SUM(Assumptions!$D$69:$F$69)/Debt!$D$5)+(Debt!D89+Debt!D90)*(1+IF($A18="Get Lucky Golf",Assumptions!$B$21-Assumptions!$B$20,0)*SUM(Assumptions!$D$70:$F$70)/Debt!$J$5)+(Debt!D91+Debt!D92)*(1+IF($A18="Get Lucky Golf",Assumptions!$B$21-Assumptions!$B$20,0)*SUM(Assumptions!$D$71:$F$71)/Debt!$P$5))-(Chain!D10*(1-Assumptions!$B$18)*(1+IF($A18="Get Lucky Golf",Assumptions!$B$21-Assumptions!$B$20,0)*SUM(Assumptions!$D$69:$F$69)/Debt!$D$5)+Chain!D27*(1-Assumptions!$B$18)*(1+IF($A18="Get Lucky Golf",Assumptions!$B$21-Assumptions!$B$20,0)*SUM(Assumptions!$D$70:$F$70)/Debt!$J$5)+Chain!D44*(1-Assumptions!$B$18)*(1+IF($A18="Get Lucky Golf",Assumptions!$B$21-Assumptions!$B$20,0)*SUM(Assumptions!$D$71:$F$71)/Debt!$P$5))+D18 -> 15340650 | F18: =(Chain!E77-($B18-Assumptions!$B$24)*Chain!E67-IF($A18="Get Lucky Golf",Assumptions!$B$21-Assumptions!$B$20,0)*(SUM(Assumptions!$D$69:$F$69)*Chain!E8+SUM(Assumptions!$D$70:$F$70)*Chain!E25+SUM(Assumptions!$D$71:$F$71)*Chain!E42)*Assumptions!$B$50)-((Debt!E87+Debt!E88)*(1+IF($A18="Get Lucky Golf",Assumptions!$B$21-Assumptions!$B$20,0)*SUM(Assumptions!$D$69:$F$69)/Debt!$D$5)+(Debt!E89+Debt!E90)*(1+IF($A18="Get Lucky Golf",Assumptions!$B$21-Assumptions!$B$20,0)*SUM(Assumptions!$D$70:$F$70)/Debt!$J$5)+(Debt!E91+Debt!E92)*(1+IF($A18="Get Lucky Golf",Assumptions!$B$21-Assumptions!$B$20,0)*SUM(Assumptions!$D$71:$F$71)/Debt!$P$5))-(Chain!E10*(1-Assumptions!$B$18)*(1+IF($A18="Get Lucky Golf",Assumptions!$B$21-Assumptions!$B$20,0)*SUM(Assumptions!$D$69:$F$69)/Debt!$D$5)+Chain!E27*(1-Assumptions!$B$18)*(1+IF($A18="Get Lucky Golf",Assumptions!$B$21-Assumptions!$B$20,0)*SUM(Assumptions!$D$70:$F$70)/Debt!$J$5)+Chain!E44*(1-Assumptions!$B$18)*(1+IF($A18="Get Lucky Golf",Assumptions!$B$21-Assumptions!$B$20,0)*SUM(Assumptions!$D$71:$F$71)/Debt!$P$5))+E18 -> 67438184 | G18: =(Chain!F77-($B18-Assumptions!$B$24)*Chain!F67-IF($A18="Get Lucky Golf",Assumptions!$B$21-Assumptions!$B$20,0)*(SUM(Assumptions!$D$69:$F$69)*Chain!F8+SUM(Assumptions!$D$70:$F$70)*Chain!F25+SUM(Assumptions!$D$71:$F$71)*Chain!F42)*Assumptions!$B$50)-((Debt!F87+Debt!F88)*(1+IF($A18="Get Lucky Golf",Assumptions!$B$21-Assumptions!$B$20,0)*SUM(Assumptions!$D$69:$F$69)/Debt!$D$5)+(Debt!F89+Debt!F90)*(1+IF($A18="Get Lucky Golf",Assumptions!$B$21-Assumptions!$B$20,0)*SUM(Assumptions!$D$70:$F$70)/Debt!$J$5)+(Debt!F91+Debt!F92)*(1+IF($A18="Get Lucky Golf",Assumptions!$B$21-Assumptions!$B$20,0)*SUM(Assumptions!$D$71:$F$71)/Debt!$P$5))-(Chain!F10*(1-Assumptions!$B$18)*(1+IF($A18="Get Lucky Golf",Assumptions!$B$21-Assumptions!$B$20,0)*SUM(Assumptions!$D$69:$F$69)/Debt!$D$5)+Chain!F27*(1-Assumptions!$B$18)*(1+IF($A18="Get Lucky Golf",Assumptions!$B$21-Assumptions!$B$20,0)*SUM(Assumptions!$D$70:$F$70)/Debt!$J$5)+Chain!F44*(1-Assumptions!$B$18)*(1+IF($A18="Get Lucky Golf",Assumptions!$B$21-Assumptions!$B$20,0)*SUM(Assumptions!$D$71:$F$71)/Debt!$P$5))+F18 -> 1.2650963e+08 | H18: =(Chain!G77-($B18-Assumptions!$B$24)*Chain!G67-IF($A18="Get Lucky Golf",Assumptions!$B$21-Assumptions!$B$20,0)*(SUM(Assumptions!$D$69:$F$69)*Chain!G8+SUM(Assumptions!$D$70:$F$70)*Chain!G25+SUM(Assumptions!$D$71:$F$71)*Chain!G42)*Assumptions!$B$50)-((Debt!G87+Debt!G88)*(1+IF($A18="Get Lucky Golf",Assumptions!$B$21-Assumptions!$B$20,0)*SUM(Assumptions!$D$69:$F$69)/Debt!$D$5)+(Debt!G89+Debt!G90)*(1+IF($A18="Get Lucky Golf",Assumptions!$B$21-Assumptions!$B$20,0)*SUM(Assumptions!$D$70:$F$70)/Debt!$J$5)+(Debt!G91+Debt!G92)*(1+IF($A18="Get Lucky Golf",Assumptions!$B$21-Assumptions!$B$20,0)*SUM(Assumptions!$D$71:$F$71)/Debt!$P$5))-(Chain!G10*(1-Assumptions!$B$18)*(1+IF($A18="Get Lucky Golf",Assumptions!$B$21-Assumptions!$B$20,0)*SUM(Assumptions!$D$69:$F$69)/Debt!$D$5)+Chain!G27*(1-Assumptions!$B$18)*(1+IF($A18="Get Lucky Golf",Assumptions!$B$21-Assumptions!$B$20,0)*SUM(Assumptions!$D$70:$F$70)/Debt!$J$5)+Chain!G44*(1-Assumptions!$B$18)*(1+IF($A18="Get Lucky Golf",Assumptions!$B$21-Assumptions!$B$20,0)*SUM(Assumptions!$D$71:$F$71)/Debt!$P$5))+G18 -> 1.8558107e+08
A19: Get Lucky Golf | B19: =B8 -> 0.15 | C19: =(Chain!B77-($B19-Assumptions!$B$24)*Chain!B67-IF($A19="Get Lucky Golf",Assumptions!$B$21-Assumptions!$B$20,0)*(SUM(Assumptions!$D$69:$F$69)*Chain!B8+SUM(Assumptions!$D$70:$F$70)*Chain!B25+SUM(Assumptions!$D$71:$F$71)*Chain!B42)*Assumptions!$B$50)-((Debt!B87+Debt!B88)*(1+IF($A19="Get Lucky Golf",Assumptions!$B$21-Assumptions!$B$20,0)*SUM(Assumptions!$D$69:$F$69)/Debt!$D$5)+(Debt!B89+Debt!B90)*(1+IF($A19="Get Lucky Golf",Assumptions!$B$21-Assumptions!$B$20,0)*SUM(Assumptions!$D$70:$F$70)/Debt!$J$5)+(Debt!B91+Debt!B92)*(1+IF($A19="Get Lucky Golf",Assumptions!$B$21-Assumptions!$B$20,0)*SUM(Assumptions!$D$71:$F$71)/Debt!$P$5))-(Chain!B10*(1-Assumptions!$B$18)*(1+IF($A19="Get Lucky Golf",Assumptions!$B$21-Assumptions!$B$20,0)*SUM(Assumptions!$D$69:$F$69)/Debt!$D$5)+Chain!B27*(1-Assumptions!$B$18)*(1+IF($A19="Get Lucky Golf",Assumptions!$B$21-Assumptions!$B$20,0)*SUM(Assumptions!$D$70:$F$70)/Debt!$J$5)+Chain!B44*(1-Assumptions!$B$18)*(1+IF($A19="Get Lucky Golf",Assumptions!$B$21-Assumptions!$B$20,0)*SUM(Assumptions!$D$71:$F$71)/Debt!$P$5)) -> -9347463.9 | D19: =(Chain!C77-($B19-Assumptions!$B$24)*Chain!C67-IF($A19="Get Lucky Golf",Assumptions!$B$21-Assumptions!$B$20,0)*(SUM(Assumptions!$D$69:$F$69)*Chain!C8+SUM(Assumptions!$D$70:$F$70)*Chain!C25+SUM(Assumptions!$D$71:$F$71)*Chain!C42)*Assumptions!$B$50)-((Debt!C87+Debt!C88)*(1+IF($A19="Get Lucky Golf",Assumptions!$B$21-Assumptions!$B$20,0)*SUM(Assumptions!$D$69:$F$69)/Debt!$D$5)+(Debt!C89+Debt!C90)*(1+IF($A19="Get Lucky Golf",Assumptions!$B$21-Assumptions!$B$20,0)*SUM(Assumptions!$D$70:$F$70)/Debt!$J$5)+(Debt!C91+Debt!C92)*(1+IF($A19="Get Lucky Golf",Assumptions!$B$21-Assumptions!$B$20,0)*SUM(Assumptions!$D$71:$F$71)/Debt!$P$5))-(Chain!C10*(1-Assumptions!$B$18)*(1+IF($A19="Get Lucky Golf",Assumptions!$B$21-Assumptions!$B$20,0)*SUM(Assumptions!$D$69:$F$69)/Debt!$D$5)+Chain!C27*(1-Assumptions!$B$18)*(1+IF($A19="Get Lucky Golf",Assumptions!$B$21-Assumptions!$B$20,0)*SUM(Assumptions!$D$70:$F$70)/Debt!$J$5)+Chain!C44*(1-Assumptions!$B$18)*(1+IF($A19="Get Lucky Golf",Assumptions!$B$21-Assumptions!$B$20,0)*SUM(Assumptions!$D$71:$F$71)/Debt!$P$5))+C19 -> -10187268 | E19: =(Chain!D77-($B19-Assumptions!$B$24)*Chain!D67-IF($A19="Get Lucky Golf",Assumptions!$B$21-Assumptions!$B$20,0)*(SUM(Assumptions!$D$69:$F$69)*Chain!D8+SUM(Assumptions!$D$70:$F$70)*Chain!D25+SUM(Assumptions!$D$71:$F$71)*Chain!D42)*Assumptions!$B$50)-((Debt!D87+Debt!D88)*(1+IF($A19="Get Lucky Golf",Assumptions!$B$21-Assumptions!$B$20,0)*SUM(Assumptions!$D$69:$F$69)/Debt!$D$5)+(Debt!D89+Debt!D90)*(1+IF($A19="Get Lucky Golf",Assumptions!$B$21-Assumptions!$B$20,0)*SUM(Assumptions!$D$70:$F$70)/Debt!$J$5)+(Debt!D91+Debt!D92)*(1+IF($A19="Get Lucky Golf",Assumptions!$B$21-Assumptions!$B$20,0)*SUM(Assumptions!$D$71:$F$71)/Debt!$P$5))-(Chain!D10*(1-Assumptions!$B$18)*(1+IF($A19="Get Lucky Golf",Assumptions!$B$21-Assumptions!$B$20,0)*SUM(Assumptions!$D$69:$F$69)/Debt!$D$5)+Chain!D27*(1-Assumptions!$B$18)*(1+IF($A19="Get Lucky Golf",Assumptions!$B$21-Assumptions!$B$20,0)*SUM(Assumptions!$D$70:$F$70)/Debt!$J$5)+Chain!D44*(1-Assumptions!$B$18)*(1+IF($A19="Get Lucky Golf",Assumptions!$B$21-Assumptions!$B$20,0)*SUM(Assumptions!$D$71:$F$71)/Debt!$P$5))+D19 -> 23628985 | F19: =(Chain!E77-($B19-Assumptions!$B$24)*Chain!E67-IF($A19="Get Lucky Golf",Assumptions!$B$21-Assumptions!$B$20,0)*(SUM(Assumptions!$D$69:$F$69)*Chain!E8+SUM(Assumptions!$D$70:$F$70)*Chain!E25+SUM(Assumptions!$D$71:$F$71)*Chain!E42)*Assumptions!$B$50)-((Debt!E87+Debt!E88)*(1+IF($A19="Get Lucky Golf",Assumptions!$B$21-Assumptions!$B$20,0)*SUM(Assumptions!$D$69:$F$69)/Debt!$D$5)+(Debt!E89+Debt!E90)*(1+IF($A19="Get Lucky Golf",Assumptions!$B$21-Assumptions!$B$20,0)*SUM(Assumptions!$D$70:$F$70)/Debt!$J$5)+(Debt!E91+Debt!E92)*(1+IF($A19="Get Lucky Golf",Assumptions!$B$21-Assumptions!$B$20,0)*SUM(Assumptions!$D$71:$F$71)/Debt!$P$5))-(Chain!E10*(1-Assumptions!$B$18)*(1+IF($A19="Get Lucky Golf",Assumptions!$B$21-Assumptions!$B$20,0)*SUM(Assumptions!$D$69:$F$69)/Debt!$D$5)+Chain!E27*(1-Assumptions!$B$18)*(1+IF($A19="Get Lucky Golf",Assumptions!$B$21-Assumptions!$B$20,0)*SUM(Assumptions!$D$70:$F$70)/Debt!$J$5)+Chain!E44*(1-Assumptions!$B$18)*(1+IF($A19="Get Lucky Golf",Assumptions!$B$21-Assumptions!$B$20,0)*SUM(Assumptions!$D$71:$F$71)/Debt!$P$5))+E19 -> 85804417 | G19: =(Chain!F77-($B19-Assumptions!$B$24)*Chain!F67-IF($A19="Get Lucky Golf",Assumptions!$B$21-Assumptions!$B$20,0)*(SUM(Assumptions!$D$69:$F$69)*Chain!F8+SUM(Assumptions!$D$70:$F$70)*Chain!F25+SUM(Assumptions!$D$71:$F$71)*Chain!F42)*Assumptions!$B$50)-((Debt!F87+Debt!F88)*(1+IF($A19="Get Lucky Golf",Assumptions!$B$21-Assumptions!$B$20,0)*SUM(Assumptions!$D$69:$F$69)/Debt!$D$5)+(Debt!F89+Debt!F90)*(1+IF($A19="Get Lucky Golf",Assumptions!$B$21-Assumptions!$B$20,0)*SUM(Assumptions!$D$70:$F$70)/Debt!$J$5)+(Debt!F91+Debt!F92)*(1+IF($A19="Get Lucky Golf",Assumptions!$B$21-Assumptions!$B$20,0)*SUM(Assumptions!$D$71:$F$71)/Debt!$P$5))-(Chain!F10*(1-Assumptions!$B$18)*(1+IF($A19="Get Lucky Golf",Assumptions!$B$21-Assumptions!$B$20,0)*SUM(Assumptions!$D$69:$F$69)/Debt!$D$5)+Chain!F27*(1-Assumptions!$B$18)*(1+IF($A19="Get Lucky Golf",Assumptions!$B$21-Assumptions!$B$20,0)*SUM(Assumptions!$D$70:$F$70)/Debt!$J$5)+Chain!F44*(1-Assumptions!$B$18)*(1+IF($A19="Get Lucky Golf",Assumptions!$B$21-Assumptions!$B$20,0)*SUM(Assumptions!$D$71:$F$71)/Debt!$P$5))+F19 -> 1.5598693e+08 | H19: =(Chain!G77-($B19-Assumptions!$B$24)*Chain!G67-IF($A19="Get Lucky Golf",Assumptions!$B$21-Assumptions!$B$20,0)*(SUM(Assumptions!$D$69:$F$69)*Chain!G8+SUM(Assumptions!$D$70:$F$70)*Chain!G25+SUM(Assumptions!$D$71:$F$71)*Chain!G42)*Assumptions!$B$50)-((Debt!G87+Debt!G88)*(1+IF($A19="Get Lucky Golf",Assumptions!$B$21-Assumptions!$B$20,0)*SUM(Assumptions!$D$69:$F$69)/Debt!$D$5)+(Debt!G89+Debt!G90)*(1+IF($A19="Get Lucky Golf",Assumptions!$B$21-Assumptions!$B$20,0)*SUM(Assumptions!$D$70:$F$70)/Debt!$J$5)+(Debt!G91+Debt!G92)*(1+IF($A19="Get Lucky Golf",Assumptions!$B$21-Assumptions!$B$20,0)*SUM(Assumptions!$D$71:$F$71)/Debt!$P$5))-(Chain!G10*(1-Assumptions!$B$18)*(1+IF($A19="Get Lucky Golf",Assumptions!$B$21-Assumptions!$B$20,0)*SUM(Assumptions!$D$69:$F$69)/Debt!$D$5)+Chain!G27*(1-Assumptions!$B$18)*(1+IF($A19="Get Lucky Golf",Assumptions!$B$21-Assumptions!$B$20,0)*SUM(Assumptions!$D$70:$F$70)/Debt!$J$5)+Chain!G44*(1-Assumptions!$B$18)*(1+IF($A19="Get Lucky Golf",Assumptions!$B$21-Assumptions!$B$20,0)*SUM(Assumptions!$D$71:$F$71)/Debt!$P$5))+G19 -> 2.2616944e+08
A20: Get Lucky Golf | B20: =B9 -> 0.2 | C20: =(Chain!B77-($B20-Assumptions!$B$24)*Chain!B67-IF($A20="Get Lucky Golf",Assumptions!$B$21-Assumptions!$B$20,0)*(SUM(Assumptions!$D$69:$F$69)*Chain!B8+SUM(Assumptions!$D$70:$F$70)*Chain!B25+SUM(Assumptions!$D$71:$F$71)*Chain!B42)*Assumptions!$B$50)-((Debt!B87+Debt!B88)*(1+IF($A20="Get Lucky Golf",Assumptions!$B$21-Assumptions!$B$20,0)*SUM(Assumptions!$D$69:$F$69)/Debt!$D$5)+(Debt!B89+Debt!B90)*(1+IF($A20="Get Lucky Golf",Assumptions!$B$21-Assumptions!$B$20,0)*SUM(Assumptions!$D$70:$F$70)/Debt!$J$5)+(Debt!B91+Debt!B92)*(1+IF($A20="Get Lucky Golf",Assumptions!$B$21-Assumptions!$B$20,0)*SUM(Assumptions!$D$71:$F$71)/Debt!$P$5))-(Chain!B10*(1-Assumptions!$B$18)*(1+IF($A20="Get Lucky Golf",Assumptions!$B$21-Assumptions!$B$20,0)*SUM(Assumptions!$D$69:$F$69)/Debt!$D$5)+Chain!B27*(1-Assumptions!$B$18)*(1+IF($A20="Get Lucky Golf",Assumptions!$B$21-Assumptions!$B$20,0)*SUM(Assumptions!$D$70:$F$70)/Debt!$J$5)+Chain!B44*(1-Assumptions!$B$18)*(1+IF($A20="Get Lucky Golf",Assumptions!$B$21-Assumptions!$B$20,0)*SUM(Assumptions!$D$71:$F$71)/Debt!$P$5)) -> -10064748 | D20: =(Chain!C77-($B20-Assumptions!$B$24)*Chain!C67-IF($A20="Get Lucky Golf",Assumptions!$B$21-Assumptions!$B$20,0)*(SUM(Assumptions!$D$69:$F$69)*Chain!C8+SUM(Assumptions!$D$70:$F$70)*Chain!C25+SUM(Assumptions!$D$71:$F$71)*Chain!C42)*Assumptions!$B$50)-((Debt!C87+Debt!C88)*(1+IF($A20="Get Lucky Golf",Assumptions!$B$21-Assumptions!$B$20,0)*SUM(Assumptions!$D$69:$F$69)/Debt!$D$5)+(Debt!C89+Debt!C90)*(1+IF($A20="Get Lucky Golf",Assumptions!$B$21-Assumptions!$B$20,0)*SUM(Assumptions!$D$70:$F$70)/Debt!$J$5)+(Debt!C91+Debt!C92)*(1+IF($A20="Get Lucky Golf",Assumptions!$B$21-Assumptions!$B$20,0)*SUM(Assumptions!$D$71:$F$71)/Debt!$P$5))-(Chain!C10*(1-Assumptions!$B$18)*(1+IF($A20="Get Lucky Golf",Assumptions!$B$21-Assumptions!$B$20,0)*SUM(Assumptions!$D$69:$F$69)/Debt!$D$5)+Chain!C27*(1-Assumptions!$B$18)*(1+IF($A20="Get Lucky Golf",Assumptions!$B$21-Assumptions!$B$20,0)*SUM(Assumptions!$D$70:$F$70)/Debt!$J$5)+Chain!C44*(1-Assumptions!$B$18)*(1+IF($A20="Get Lucky Golf",Assumptions!$B$21-Assumptions!$B$20,0)*SUM(Assumptions!$D$71:$F$71)/Debt!$P$5))+C20 -> -14151214 | E20: =(Chain!D77-($B20-Assumptions!$B$24)*Chain!D67-IF($A20="Get Lucky Golf",Assumptions!$B$21-Assumptions!$B$20,0)*(SUM(Assumptions!$D$69:$F$69)*Chain!D8+SUM(Assumptions!$D$70:$F$70)*Chain!D25+SUM(Assumptions!$D$71:$F$71)*Chain!D42)*Assumptions!$B$50)-((Debt!D87+Debt!D88)*(1+IF($A20="Get Lucky Golf",Assumptions!$B$21-Assumptions!$B$20,0)*SUM(Assumptions!$D$69:$F$69)/Debt!$D$5)+(Debt!D89+Debt!D90)*(1+IF($A20="Get Lucky Golf",Assumptions!$B$21-Assumptions!$B$20,0)*SUM(Assumptions!$D$70:$F$70)/Debt!$J$5)+(Debt!D91+Debt!D92)*(1+IF($A20="Get Lucky Golf",Assumptions!$B$21-Assumptions!$B$20,0)*SUM(Assumptions!$D$71:$F$71)/Debt!$P$5))-(Chain!D10*(1-Assumptions!$B$18)*(1+IF($A20="Get Lucky Golf",Assumptions!$B$21-Assumptions!$B$20,0)*SUM(Assumptions!$D$69:$F$69)/Debt!$D$5)+Chain!D27*(1-Assumptions!$B$18)*(1+IF($A20="Get Lucky Golf",Assumptions!$B$21-Assumptions!$B$20,0)*SUM(Assumptions!$D$70:$F$70)/Debt!$J$5)+Chain!D44*(1-Assumptions!$B$18)*(1+IF($A20="Get Lucky Golf",Assumptions!$B$21-Assumptions!$B$20,0)*SUM(Assumptions!$D$71:$F$71)/Debt!$P$5))+D20 -> 12907077 | F20: =(Chain!E77-($B20-Assumptions!$B$24)*Chain!E67-IF($A20="Get Lucky Golf",Assumptions!$B$21-Assumptions!$B$20,0)*(SUM(Assumptions!$D$69:$F$69)*Chain!E8+SUM(Assumptions!$D$70:$F$70)*Chain!E25+SUM(Assumptions!$D$71:$F$71)*Chain!E42)*Assumptions!$B$50)-((Debt!E87+Debt!E88)*(1+IF($A20="Get Lucky Golf",Assumptions!$B$21-Assumptions!$B$20,0)*SUM(Assumptions!$D$69:$F$69)/Debt!$D$5)+(Debt!E89+Debt!E90)*(1+IF($A20="Get Lucky Golf",Assumptions!$B$21-Assumptions!$B$20,0)*SUM(Assumptions!$D$70:$F$70)/Debt!$J$5)+(Debt!E91+Debt!E92)*(1+IF($A20="Get Lucky Golf",Assumptions!$B$21-Assumptions!$B$20,0)*SUM(Assumptions!$D$71:$F$71)/Debt!$P$5))-(Chain!E10*(1-Assumptions!$B$18)*(1+IF($A20="Get Lucky Golf",Assumptions!$B$21-Assumptions!$B$20,0)*SUM(Assumptions!$D$69:$F$69)/Debt!$D$5)+Chain!E27*(1-Assumptions!$B$18)*(1+IF($A20="Get Lucky Golf",Assumptions!$B$21-Assumptions!$B$20,0)*SUM(Assumptions!$D$70:$F$70)/Debt!$J$5)+Chain!E44*(1-Assumptions!$B$18)*(1+IF($A20="Get Lucky Golf",Assumptions!$B$21-Assumptions!$B$20,0)*SUM(Assumptions!$D$71:$F$71)/Debt!$P$5))+E20 -> 66289960 | G20: =(Chain!F77-($B20-Assumptions!$B$24)*Chain!F67-IF($A20="Get Lucky Golf",Assumptions!$B$21-Assumptions!$B$20,0)*(SUM(Assumptions!$D$69:$F$69)*Chain!F8+SUM(Assumptions!$D$70:$F$70)*Chain!F25+SUM(Assumptions!$D$71:$F$71)*Chain!F42)*Assumptions!$B$50)-((Debt!F87+Debt!F88)*(1+IF($A20="Get Lucky Golf",Assumptions!$B$21-Assumptions!$B$20,0)*SUM(Assumptions!$D$69:$F$69)/Debt!$D$5)+(Debt!F89+Debt!F90)*(1+IF($A20="Get Lucky Golf",Assumptions!$B$21-Assumptions!$B$20,0)*SUM(Assumptions!$D$70:$F$70)/Debt!$J$5)+(Debt!F91+Debt!F92)*(1+IF($A20="Get Lucky Golf",Assumptions!$B$21-Assumptions!$B$20,0)*SUM(Assumptions!$D$71:$F$71)/Debt!$P$5))-(Chain!F10*(1-Assumptions!$B$18)*(1+IF($A20="Get Lucky Golf",Assumptions!$B$21-Assumptions!$B$20,0)*SUM(Assumptions!$D$69:$F$69)/Debt!$D$5)+Chain!F27*(1-Assumptions!$B$18)*(1+IF($A20="Get Lucky Golf",Assumptions!$B$21-Assumptions!$B$20,0)*SUM(Assumptions!$D$70:$F$70)/Debt!$J$5)+Chain!F44*(1-Assumptions!$B$18)*(1+IF($A20="Get Lucky Golf",Assumptions!$B$21-Assumptions!$B$20,0)*SUM(Assumptions!$D$71:$F$71)/Debt!$P$5))+F20 -> 1.2716334e+08 | H20: =(Chain!G77-($B20-Assumptions!$B$24)*Chain!G67-IF($A20="Get Lucky Golf",Assumptions!$B$21-Assumptions!$B$20,0)*(SUM(Assumptions!$D$69:$F$69)*Chain!G8+SUM(Assumptions!$D$70:$F$70)*Chain!G25+SUM(Assumptions!$D$71:$F$71)*Chain!G42)*Assumptions!$B$50)-((Debt!G87+Debt!G88)*(1+IF($A20="Get Lucky Golf",Assumptions!$B$21-Assumptions!$B$20,0)*SUM(Assumptions!$D$69:$F$69)/Debt!$D$5)+(Debt!G89+Debt!G90)*(1+IF($A20="Get Lucky Golf",Assumptions!$B$21-Assumptions!$B$20,0)*SUM(Assumptions!$D$70:$F$70)/Debt!$J$5)+(Debt!G91+Debt!G92)*(1+IF($A20="Get Lucky Golf",Assumptions!$B$21-Assumptions!$B$20,0)*SUM(Assumptions!$D$71:$F$71)/Debt!$P$5))-(Chain!G10*(1-Assumptions!$B$18)*(1+IF($A20="Get Lucky Golf",Assumptions!$B$21-Assumptions!$B$20,0)*SUM(Assumptions!$D$69:$F$69)/Debt!$D$5)+Chain!G27*(1-Assumptions!$B$18)*(1+IF($A20="Get Lucky Golf",Assumptions!$B$21-Assumptions!$B$20,0)*SUM(Assumptions!$D$70:$F$70)/Debt!$J$5)+Chain!G44*(1-Assumptions!$B$18)*(1+IF($A20="Get Lucky Golf",Assumptions!$B$21-Assumptions!$B$20,0)*SUM(Assumptions!$D$71:$F$71)/Debt!$P$5))+G20 -> 1.8803671e+08
A21: Get Lucky Golf | B21: =B10 -> 0.25 | C21: =(Chain!B77-($B21-Assumptions!$B$24)*Chain!B67-IF($A21="Get Lucky Golf",Assumptions!$B$21-Assumptions!$B$20,0)*(SUM(Assumptions!$D$69:$F$69)*Chain!B8+SUM(Assumptions!$D$70:$F$70)*Chain!B25+SUM(Assumptions!$D$71:$F$71)*Chain!B42)*Assumptions!$B$50)-((Debt!B87+Debt!B88)*(1+IF($A21="Get Lucky Golf",Assumptions!$B$21-Assumptions!$B$20,0)*SUM(Assumptions!$D$69:$F$69)/Debt!$D$5)+(Debt!B89+Debt!B90)*(1+IF($A21="Get Lucky Golf",Assumptions!$B$21-Assumptions!$B$20,0)*SUM(Assumptions!$D$70:$F$70)/Debt!$J$5)+(Debt!B91+Debt!B92)*(1+IF($A21="Get Lucky Golf",Assumptions!$B$21-Assumptions!$B$20,0)*SUM(Assumptions!$D$71:$F$71)/Debt!$P$5))-(Chain!B10*(1-Assumptions!$B$18)*(1+IF($A21="Get Lucky Golf",Assumptions!$B$21-Assumptions!$B$20,0)*SUM(Assumptions!$D$69:$F$69)/Debt!$D$5)+Chain!B27*(1-Assumptions!$B$18)*(1+IF($A21="Get Lucky Golf",Assumptions!$B$21-Assumptions!$B$20,0)*SUM(Assumptions!$D$70:$F$70)/Debt!$J$5)+Chain!B44*(1-Assumptions!$B$18)*(1+IF($A21="Get Lucky Golf",Assumptions!$B$21-Assumptions!$B$20,0)*SUM(Assumptions!$D$71:$F$71)/Debt!$P$5)) -> -10782031 | D21: =(Chain!C77-($B21-Assumptions!$B$24)*Chain!C67-IF($A21="Get Lucky Golf",Assumptions!$B$21-Assumptions!$B$20,0)*(SUM(Assumptions!$D$69:$F$69)*Chain!C8+SUM(Assumptions!$D$70:$F$70)*Chain!C25+SUM(Assumptions!$D$71:$F$71)*Chain!C42)*Assumptions!$B$50)-((Debt!C87+Debt!C88)*(1+IF($A21="Get Lucky Golf",Assumptions!$B$21-Assumptions!$B$20,0)*SUM(Assumptions!$D$69:$F$69)/Debt!$D$5)+(Debt!C89+Debt!C90)*(1+IF($A21="Get Lucky Golf",Assumptions!$B$21-Assumptions!$B$20,0)*SUM(Assumptions!$D$70:$F$70)/Debt!$J$5)+(Debt!C91+Debt!C92)*(1+IF($A21="Get Lucky Golf",Assumptions!$B$21-Assumptions!$B$20,0)*SUM(Assumptions!$D$71:$F$71)/Debt!$P$5))-(Chain!C10*(1-Assumptions!$B$18)*(1+IF($A21="Get Lucky Golf",Assumptions!$B$21-Assumptions!$B$20,0)*SUM(Assumptions!$D$69:$F$69)/Debt!$D$5)+Chain!C27*(1-Assumptions!$B$18)*(1+IF($A21="Get Lucky Golf",Assumptions!$B$21-Assumptions!$B$20,0)*SUM(Assumptions!$D$70:$F$70)/Debt!$J$5)+Chain!C44*(1-Assumptions!$B$18)*(1+IF($A21="Get Lucky Golf",Assumptions!$B$21-Assumptions!$B$20,0)*SUM(Assumptions!$D$71:$F$71)/Debt!$P$5))+C21 -> -18115160 | E21: =(Chain!D77-($B21-Assumptions!$B$24)*Chain!D67-IF($A21="Get Lucky Golf",Assumptions!$B$21-Assumptions!$B$20,0)*(SUM(Assumptions!$D$69:$F$69)*Chain!D8+SUM(Assumptions!$D$70:$F$70)*Chain!D25+SUM(Assumptions!$D$71:$F$71)*Chain!D42)*Assumptions!$B$50)-((Debt!D87+Debt!D88)*(1+IF($A21="Get Lucky Golf",Assumptions!$B$21-Assumptions!$B$20,0)*SUM(Assumptions!$D$69:$F$69)/Debt!$D$5)+(Debt!D89+Debt!D90)*(1+IF($A21="Get Lucky Golf",Assumptions!$B$21-Assumptions!$B$20,0)*SUM(Assumptions!$D$70:$F$70)/Debt!$J$5)+(Debt!D91+Debt!D92)*(1+IF($A21="Get Lucky Golf",Assumptions!$B$21-Assumptions!$B$20,0)*SUM(Assumptions!$D$71:$F$71)/Debt!$P$5))-(Chain!D10*(1-Assumptions!$B$18)*(1+IF($A21="Get Lucky Golf",Assumptions!$B$21-Assumptions!$B$20,0)*SUM(Assumptions!$D$69:$F$69)/Debt!$D$5)+Chain!D27*(1-Assumptions!$B$18)*(1+IF($A21="Get Lucky Golf",Assumptions!$B$21-Assumptions!$B$20,0)*SUM(Assumptions!$D$70:$F$70)/Debt!$J$5)+Chain!D44*(1-Assumptions!$B$18)*(1+IF($A21="Get Lucky Golf",Assumptions!$B$21-Assumptions!$B$20,0)*SUM(Assumptions!$D$71:$F$71)/Debt!$P$5))+D21 -> 2185169.3 | F21: =(Chain!E77-($B21-Assumptions!$B$24)*Chain!E67-IF($A21="Get Lucky Golf",Assumptions!$B$21-Assumptions!$B$20,0)*(SUM(Assumptions!$D$69:$F$69)*Chain!E8+SUM(Assumptions!$D$70:$F$70)*Chain!E25+SUM(Assumptions!$D$71:$F$71)*Chain!E42)*Assumptions!$B$50)-((Debt!E87+Debt!E88)*(1+IF($A21="Get Lucky Golf",Assumptions!$B$21-Assumptions!$B$20,0)*SUM(Assumptions!$D$69:$F$69)/Debt!$D$5)+(Debt!E89+Debt!E90)*(1+IF($A21="Get Lucky Golf",Assumptions!$B$21-Assumptions!$B$20,0)*SUM(Assumptions!$D$70:$F$70)/Debt!$J$5)+(Debt!E91+Debt!E92)*(1+IF($A21="Get Lucky Golf",Assumptions!$B$21-Assumptions!$B$20,0)*SUM(Assumptions!$D$71:$F$71)/Debt!$P$5))-(Chain!E10*(1-Assumptions!$B$18)*(1+IF($A21="Get Lucky Golf",Assumptions!$B$21-Assumptions!$B$20,0)*SUM(Assumptions!$D$69:$F$69)/Debt!$D$5)+Chain!E27*(1-Assumptions!$B$18)*(1+IF($A21="Get Lucky Golf",Assumptions!$B$21-Assumptions!$B$20,0)*SUM(Assumptions!$D$70:$F$70)/Debt!$J$5)+Chain!E44*(1-Assumptions!$B$18)*(1+IF($A21="Get Lucky Golf",Assumptions!$B$21-Assumptions!$B$20,0)*SUM(Assumptions!$D$71:$F$71)/Debt!$P$5))+E21 -> 46775502 | G21: =(Chain!F77-($B21-Assumptions!$B$24)*Chain!F67-IF($A21="Get Lucky Golf",Assumptions!$B$21-Assumptions!$B$20,0)*(SUM(Assumptions!$D$69:$F$69)*Chain!F8+SUM(Assumptions!$D$70:$F$70)*Chain!F25+SUM(Assumptions!$D$71:$F$71)*Chain!F42)*Assumptions!$B$50)-((Debt!F87+Debt!F88)*(1+IF($A21="Get Lucky Golf",Assumptions!$B$21-Assumptions!$B$20,0)*SUM(Assumptions!$D$69:$F$69)/Debt!$D$5)+(Debt!F89+Debt!F90)*(1+IF($A21="Get Lucky Golf",Assumptions!$B$21-Assumptions!$B$20,0)*SUM(Assumptions!$D$70:$F$70)/Debt!$J$5)+(Debt!F91+Debt!F92)*(1+IF($A21="Get Lucky Golf",Assumptions!$B$21-Assumptions!$B$20,0)*SUM(Assumptions!$D$71:$F$71)/Debt!$P$5))-(Chain!F10*(1-Assumptions!$B$18)*(1+IF($A21="Get Lucky Golf",Assumptions!$B$21-Assumptions!$B$20,0)*SUM(Assumptions!$D$69:$F$69)/Debt!$D$5)+Chain!F27*(1-Assumptions!$B$18)*(1+IF($A21="Get Lucky Golf",Assumptions!$B$21-Assumptions!$B$20,0)*SUM(Assumptions!$D$70:$F$70)/Debt!$J$5)+Chain!F44*(1-Assumptions!$B$18)*(1+IF($A21="Get Lucky Golf",Assumptions!$B$21-Assumptions!$B$20,0)*SUM(Assumptions!$D$71:$F$71)/Debt!$P$5))+F21 -> 98339744 | H21: =(Chain!G77-($B21-Assumptions!$B$24)*Chain!G67-IF($A21="Get Lucky Golf",Assumptions!$B$21-Assumptions!$B$20,0)*(SUM(Assumptions!$D$69:$F$69)*Chain!G8+SUM(Assumptions!$D$70:$F$70)*Chain!G25+SUM(Assumptions!$D$71:$F$71)*Chain!G42)*Assumptions!$B$50)-((Debt!G87+Debt!G88)*(1+IF($A21="Get Lucky Golf",Assumptions!$B$21-Assumptions!$B$20,0)*SUM(Assumptions!$D$69:$F$69)/Debt!$D$5)+(Debt!G89+Debt!G90)*(1+IF($A21="Get Lucky Golf",Assumptions!$B$21-Assumptions!$B$20,0)*SUM(Assumptions!$D$70:$F$70)/Debt!$J$5)+(Debt!G91+Debt!G92)*(1+IF($A21="Get Lucky Golf",Assumptions!$B$21-Assumptions!$B$20,0)*SUM(Assumptions!$D$71:$F$71)/Debt!$P$5))-(Chain!G10*(1-Assumptions!$B$18)*(1+IF($A21="Get Lucky Golf",Assumptions!$B$21-Assumptions!$B$20,0)*SUM(Assumptions!$D$69:$F$69)/Debt!$D$5)+Chain!G27*(1-Assumptions!$B$18)*(1+IF($A21="Get Lucky Golf",Assumptions!$B$21-Assumptions!$B$20,0)*SUM(Assumptions!$D$70:$F$70)/Debt!$J$5)+Chain!G44*(1-Assumptions!$B$18)*(1+IF($A21="Get Lucky Golf",Assumptions!$B$21-Assumptions!$B$20,0)*SUM(Assumptions!$D$71:$F$71)/Debt!$P$5))+G21 -> 1.4990399e+08

Sheet Sources
A1: Sources and status of each input
A3: Virgin Active clubs and members | B3: 136 Southern African clubs, 623,000 members, 35% of group revenue: Virgin Active results to March 2026 as reported by IOL Business Report (13 Nov 2025) and Brait. Collection clubs: virginactive.co.za/memberships.
A4: Padel pricing | B4: About R400 an hour, R100 a player in a doubles game: Virgin Active padel pages and virginactivepadelclub.co.za.
A5: Simulator bay rates in South Africa | B5: Par 72 Pretoria R210 off-peak to R400 peak a bay-hour; Golf Bar R185 to R370; Golf Sim Centre Cape Town from R150 a person. Sept 2026.
A6: Golfzon hardware prices | B6: Golfzon commercial simulators published at $25,000 (TwoVision NX Standard) to $55,000–$90,000 a bay for commercial TwoVision NX (golfzongolf.com; rggolf.com 2026 comparison). Working assumptions until Golfzon quotes in October 2026.
A7: Golfzon bay footprint | B7: TwoVision NX: width 16 to 19 ft, length 15 ft 3 in plus 3 ft safety, height 10 ft 2 in minimum (golfzongolf.com plan-your-space). About 5.6 m × 5.5 m × 3.1 m, so a two-bay zone is about 60 m².
A8: Golfzon venue guidance | B8: $50 an hour, 10 booked hours a day, $150,000 to $175,000 a bay a year (golfzongolf.com, start a golf simulator business). The model runs at half the hours and a third of the rate.
A9: Prime rate | B9: 10.5% (repo 7.0%), effective 28 May 2026, unchanged 23 July 2026. Next MPC 23 September 2026.
A10: The Point | B10: Virgin Active's Collection Country Club at Green Point opened 19 February 2026 with a TrackMan simulator (Virgin Active SA build series; launch coverage). Chiswick Riverside in London runs a Trackman iO.
A11: Insured shot economics | B11: Stake, prize and 24% premium per the Get Lucky investor model (investgetlucky data/model.json). Santam underwrites.
A12: Everything else | B12: Working assumptions by Get Lucky Golf, September 2026: utilisation, yields, add-on take-up, cost lines, RMB margin and structure, landed factor, ramp. Each is an input on Assumptions and is meant to be challenged.
